Workbook
Name Slicer_Category: #N/A
Name Slicer_Region: #N/A

Sheet Sales Dashboard
A3: Sum of Sales
A4: 34765938 | D4: Count of Order ID | E4: unique order
D5: 500 | E5: =IF(COUNTIF($A$2:A2,A2)=1,1,0) -> 0 | G5: Order_Date | H5: Sum of Sales
G6: \ | H6: 1785
G7: 13/01/2025 | H7: 574930
G8: 13/01/2026 | H8: 275000
G9: 13/02/2025 | H9: 100
A10: Average Sales per Order | G10: 13/02/2026 | H10: 12080
A11: =IFERROR(A4/D5,0) -> 69531.875 | G11: 13/03/2025 | H11: 180000
G12: 13/03/2026 | H12: 305589.5
G13: 13/04/2025 | H13: 143760 | O13: Category | P13: Sum of Sales
G14: 13/05/2025 | H14: 15360 | O14: Home Appliances | P14: 7000575
G15: 13/05/2026 | H15: 69325 | O15: Grand Total | P15: 7000575
G16: 13/08/2025 | H16: 18780
A17: Region | B17: Sum of Sales | G17: 13/10/2025 | H17: 142408.25
A18: East | B18: 4041922 | G18: 13/12/2025 | H18: 21710
A19: Grand Total | B19: 4041922 | G19: 14/01/2026 | H19: 79800
G20: 14/02/2026 | H20: 1062
G21: 14/03/2025 | H21: 650.25
G22: 14/03/2026 | H22: 140
G23: 14/05/2025 | H23: 68
G24: 14/06/2025 | H24: 12320
G25: 14/07/2025 | H25: 28160
G26: 14/12/2025 | H26: 198900
G27: 15/01/2025 | H27: 20505
G28: 15/03/2026 | H28: 14820
G29: 15/04/2026 | H29: 59850
G30: 15/05/2025 | H30: 43732.5
G31: 15/06/2025 | H31: 10127
... G202: 31/12/2025 | H202: 224
G203: 45658 | H203: 15012.5
G204: 45659 | H204: 53200
G205: 45660 | H205: 10410
G206: 45661 | H206: 17050
G207: 45664 | H207: 132000
G208: 45665 | H208: 110000
G209: 45666 | H209: 441009.5
G210: 45667 | H210: 61251
G211: 45668 | H211: 3150
G212: 45669 | H212: 149985
G213: 45691 | H213: 17340
G214: 45693 | H214: 4800
... G331: 46361 | H331: 68400
G332: (blank) | H332: 832140
G333: Grand Total | H333: 34765938

Sheet Sheet1
A1: Order ID | B1: Customer_ID | C1: Product_ID | D1: Order_Date | E1: Delivery_Date | F1: Customer_Name | G1: Gender | H1: DOB | I1: City | J1: Region | K1: Category | L1: Product_Name | M1: Quantity | N1: Unit_Price | O1: Discount_% | P1: Sales | Q1: Rating | R1: Payment_Mode | S1: Salesperson | T1: Email | U1: Phone | V1: Order_Status | W1: Customer Classification | X1: Standarized Customer Name | Y1: Customer Code | Z1: Standerized Email | AA1: Customer age | AB1: Delivery Time | AC1: DELIVERY status
A2: ORD10001 | B2: C010 | C2: P101 | D2: 45725 | E2: 14/09/2025 | F2: pooja shah | G2: Female | H2: 16/09/1994 | I2: Bengaluru | J2: South | K2: Electronics | L2: Laptop | M2: 5 | N2: 55000 | O2: 5 | P2: 261250 | Q2: 3 | R2: NetBanking | S2: Aisha | T2: pooja.shah@company.com | U2: 9380975626 | V2: Pending | W2: =IF(OR(Q2<=2,V2="Cancelled"),"Blacklisted",IF(AND(P2>100000,Q2>=4,O2<=10%,V2="Completed"),"Platinum",IF(AND(P2>=50000,Q2>=3,V2="Completed"),"Gold",IF(AND(P2<50000,V2="Completed"),"Silver","")))) | X2: =PROPER(TRIM(F2)) -> Pooja Shah | Y2: =LEFT(F2,3)&MID(B2,2,3)&LEFT(I2,2) -> poo010Be | Z2: =IF(ISNUMBER(SEARCH("@",T2)),LOWER(TRIM(T2)),"invalid email") -> pooja.shah@company.com | AA2: =IF(H4="","",IFERROR(DATEDIF(IF(ISNUMBER(H4),H4,DATE(VALUE(RIGHT(H4,4)),VALUE(MID(H4,3,2)),VALUE(LEFT(H4,2)))),TODAY(),"Y"),"")) | AB2: =IF(OR(D2="",E2=""),"",IFERROR(DATE(MID(E2,7,4),MID(E2,4,2),LEFT(E2,2))-DATE(MID(D2,7,4),MID(D2,4,2),LEFT(D2,2)),"")) | AC2: =IF(E2="","Pending",IF(AB2<=5,"On time","Delayed")) -> Delayed
A3: ORD10001 | B3: C008 | C3: P202 | D3: 18/09/2025 | E3: 22/09/2025 | F3: Kavya Nair | G3: Female | H3: 27767 | I3: Hyderabad | J3: South | K3: Home Appliances | L3: Iron | M3: 4 | N3: 2200 | O3: 10 | P3: 7920 | Q3: 4 | R3: Cash | S3: Ritika | T3: KAvya.nair@company.com | U3: 9431429797 | V3: Completed | W3: =IF(OR(Q3<=2,V3="Cancelled"),"Blacklisted",IF(AND(P3>100000,Q3>=4,O3<=10%,V3="Completed"),"Platinum",IF(AND(P3>=50000,Q3>=3,V3="Completed"),"Gold",IF(AND(P3<50000,V3="Completed"),"Silver","")))) -> Silver | X3: =PROPER(TRIM(F3)) -> Kavya Nair | Y3: =LEFT(F3,3)&MID(B3,2,3)&LEFT(I3,2) -> Kav008Hy | Z3: =IF(ISNUMBER(SEARCH("@",T3)),LOWER(TRIM(T3)),"invalid email") -> kavya.nair@company.com | AA3: =DATEDIF(H3,TODAY(),"Y") -> 50 | AB3: =IF(OR(D3="",E3=""),"",IFERROR(DATE(MID(E3,7,4),MID(E3,4,2),LEFT(E3,2))-DATE(MID(D3,7,4),MID(D3,4,2),LEFT(D3,2)),"")) -> 4 | AC3: =IF(E3="","Pending",IF(AB3<=5,"On time","Delayed")) -> On time
A4: ORD10001 | B4: C008 | C4: P104 | D4: 27/04/2025 | E4: 45752 | F4: Kavya Nair | G4: Female | H4: 16/10/2000 | I4: Delhi | J4: North | K4: Electronics | L4: Monitor | M4: 17 | N4: 12000 | O4: 10 | P4: 183600 | Q4: 1 | R4: NetBanking | S4: Rahul | T4: kavya.nair@company.com | U4: 9129865339 | V4: Completed | W4: =IF(OR(Q4<=2,V4="Cancelled"),"Blacklisted",IF(AND(P4>100000,Q4>=4,O4<=10%,V4="Completed"),"Platinum",IF(AND(P4>=50000,Q4>=3,V4="Completed"),"Gold",IF(AND(P4<50000,V4="Completed"),"Silver","")))) -> Blacklisted | X4: =PROPER(TRIM(F4)) -> Kavya Nair | Y4: =LEFT(F4,3)&MID(B4,2,3)&LEFT(I4,2) -> Kav008De | Z4: =IF(ISNUMBER(SEARCH("@",T4)),LOWER(TRIM(T4)),"invalid email") -> kavya.nair@company.com | AA4: =IF(H3="","",IFERROR(DATEDIF(IF(ISNUMBER(H3),H3,DATE(VALUE(RIGHT(H3,4)),VALUE(MID(H3,3,2)),VALUE(LEFT(H3,2)))),TODAY(),"Y"),"")) -> 50 | AB4: =IF(OR(D4="",E4=""),"",IFERROR(DATE(MID(E4,7,4),MID(E4,4,2),LEFT(E4,2))-DATE(MID(D4,7,4),MID(D4,4,2),LEFT(D4,2)),"")) | AC4: =IF(E4="","Pending",IF(AB4<=5,"On time","Delayed")) -> Delayed
A5: ORD10001 | B5: C008 | C5: P202 | D5: 21/03/2026 | E5: 46057 | F5: Kavya Nair | G5: Female | H5: 38171 | I5: Bengaluru | J5: South | K5: Home Appliances | L5: Iron | M5: 5 | N5: 2200 | O5: 5 | P5: 10450 | Q5: 5 | R5: NetBanking | S5: Aisha | T5: kavya.nair@company.com | U5: 9600261125 | V5: Cancelled | W5: =IF(OR(Q5<=2,V5="Cancelled"),"Blacklisted",IF(AND(P5>100000,Q5>=4,O5<=10%,V5="Completed"),"Platinum",IF(AND(P5>=50000,Q5>=3,V5="Completed"),"Gold",IF(AND(P5<50000,V5="Completed"),"Silver","")))) -> Blacklisted | X5: =PROPER(TRIM(F5)) -> Kavya Nair | Y5: =LEFT(F5,3)&MID(B5,2,3)&LEFT(I5,2) -> Kav008Be | Z5: =IF(ISNUMBER(SEARCH("@",T5)),LOWER(TRIM(T5)),"invalid email") -> kavya.nair@company.com | AA5: =IF(H2="","",IFERROR(DATEDIF(IF(ISNUMBER(H2),H2,DATE(VALUE(RIGHT(H2,4)),VALUE(MID(H2,3,2)),VALUE(LEFT(H2,2)))),TODAY(),"Y"),"")) | AB5: =IF(OR(D5="",E5=""),"",IFERROR(DATE(MID(E5,7,4),MID(E5,4,2),LEFT(E5,2))-DATE(MID(D5,7,4),MID(D5,4,2),LEFT(D5,2)),"")) | AC5: =IF(E5="","Pending",IF(AB5<=5,"On time","Delayed")) -> Delayed
A6: ORD10001 | B6: C009 | C6: P103 | D6: 27/09/2025 | E6: 45848 | F6: Mohit Verma | G6: Male | H6: 13/04/1976 | I6: Delhi | J6: North | K6: Electronics | L6: Keyboard | M6: 8 | N6: 1200 | O6: 5 | P6: 9120 | Q6: 2 | R6: Card | S6: Aisha | T6: mohit.verma@company.com | U6: 9724635978 | V6: Pending | W6: =IF(OR(Q6<=2,V6="Cancelled"),"Blacklisted",IF(AND(P6>100000,Q6>=4,O6<=10%,V6="Completed"),"Platinum",IF(AND(P6>=50000,Q6>=3,V6="Completed"),"Gold",IF(AND(P6<50000,V6="Completed"),"Silver","")))) -> Blacklisted | X6: =PROPER(TRIM(F6)) -> Mohit Verma | Y6: =LEFT(F6,3)&MID(B6,2,3)&LEFT(I6,2) -> Moh009De | Z6: =IF(ISNUMBER(SEARCH("@",T6)),LOWER(TRIM(T6)),"invalid email") -> mohit.verma@company.com | AA6: =IF(H5="","",IFERROR(DATEDIF(IF(ISNUMBER(H5),H5,DATE(VALUE(RIGHT(H5,4)),VALUE(MID(H5,3,2)),VALUE(LEFT(H5,2)))),TODAY(),"Y"),"")) -> 22 | AB6: =IF(OR(D6="",E6=""),"",IFERROR(DATE(MID(E6,7,4),MID(E6,4,2),LEFT(E6,2))-DATE(MID(D6,7,4),MID(D6,4,2),LEFT(D6,2)),"")) | AC6: =IF(E6="","Pending",IF(AB6<=5,"On time","Delayed")) -> Delayed
A7: ORD10006 | B7: C007 | C7: P202 | D7: 46113 | E7: 46357 | F7: arjun Rao | G7: Male | H7: 32326 | I7: Hyderabad | J7: South | K7: Home Appliances | L7: Iron | M7: 4 | N7: 2200 | O7: 0 | P7: 8800 | Q7: 1 | R7: UPI | S7: Ritika | T7: arjun.rao@company.com | U7: 9780584905 | V7: Completed | W7: =IF(OR(Q7<=2,V7="Cancelled"),"Blacklisted",IF(AND(P7>100000,Q7>=4,O7<=10%,V7="Completed"),"Platinum",IF(AND(P7>=50000,Q7>=3,V7="Completed"),"Gold",IF(AND(P7<50000,V7="Completed"),"Silver","")))) -> Blacklisted | X7: =PROPER(TRIM(F7)) -> Arjun Rao | Y7: =LEFT(F7,3)&MID(B7,2,3)&LEFT(I7,2) -> arj007Hy | Z7: =IF(ISNUMBER(SEARCH("@",T7)),LOWER(TRIM(T7)),"invalid email") -> arjun.rao@company.com | AA7: =IF(H6="","",IFERROR(DATEDIF(IF(ISNUMBER(H6),H6,DATE(VALUE(RIGHT(H6,4)),VALUE(MID(H6,3,2)),VALUE(LEFT(H6,2)))),TODAY(),"Y"),"")) | AB7: =IF(OR(D7="",E7=""),"",IFERROR(DATE(MID(E7,7,4),MID(E7,4,2),LEFT(E7,2))-DATE(MID(D7,7,4),MID(D7,4,2),LEFT(D7,2)),"")) | AC7: =IF(E7="","Pending",IF(AB7<=5,"On time","Delayed")) -> Delayed
A8: ORD10007 | B8: C008 | C8: P201 | D8: 31/02/2025 | E8: 25/02/2026 | F8: Kavya Nair | G8: Female | H8: 20/03/2003 | I8: Hyderabad | J8: South | K8: Home Appliances | L8: Mixer | M8: 2 | N8: 3500 | O8: 5 | P8: 6650 | Q8: 1 | R8: UPI | S8: Ritika | T8: kavya.nair@company.com | U8: 9958252176 | V8: Completed | W8: =IF(OR(Q8<=2,V8="Cancelled"),"Blacklisted",IF(AND(P8>100000,Q8>=4,O8<=10%,V8="Completed"),"Platinum",IF(AND(P8>=50000,Q8>=3,V8="Completed"),"Gold",IF(AND(P8<50000,V8="Completed"),"Silver","")))) -> Blacklisted | X8: =PROPER(TRIM(F8)) -> Kavya Nair | Y8: =LEFT(F8,3)&MID(B8,2,3)&LEFT(I8,2) -> Kav008Hy | Z8: =IF(ISNUMBER(SEARCH("@",T8)),LOWER(TRIM(T8)),"invalid email") -> kavya.nair@company.com | AA8: =IF(H7="","",IFERROR(DATEDIF(IF(ISNUMBER(H7),H7,DATE(VALUE(RIGHT(H7,4)),VALUE(MID(H7,3,2)),VALUE(LEFT(H7,2)))),TODAY(),"Y"),"")) -> 38 | AB8: =IF(OR(D8="",E8=""),"",IFERROR(DATE(MID(E8,7,4),MID(E8,4,2),LEFT(E8,2))-DATE(MID(D8,7,4),MID(D8,4,2),LEFT(D8,2)),"")) -> 359 | AC8: =IF(E8="","Pending",IF(AB8<=5,"On time","Delayed")) -> Delayed
A9: ORD10008 | B9: C002 | C9: P104 | D9: 13/04/2025 | E9: 19/04/2025 | F9: Priya Patel | G9: Female | H9: 34883 | I9: Mumbai | J9: West | K9: Home Appliances | L9: Monitor | M9: 14 | N9: 12000 | O9: 15 | P9: 142800 | Q9: 4 | R9: NetBanking | S9: Ritika | T9: priYa.patel@company.com | U9: 9705521654 | V9: Completed | W9: =IF(OR(Q9<=2,V9="Cancelled"),"Blacklisted",IF(AND(P9>100000,Q9>=4,O9<=10%,V9="Completed"),"Platinum",IF(AND(P9>=50000,Q9>=3,V9="Completed"),"Gold",IF(AND(P9<50000,V9="Completed"),"Silver","")))) -> Gold | X9: =PROPER(TRIM(F9)) -> Priya Patel | Y9: =LEFT(F9,3)&MID(B9,2,3)&LEFT(I9,2) -> Pri002Mu | Z9: =IF(ISNUMBER(SEARCH("@",T9)),LOWER(TRIM(T9)),"invalid email") -> priya.patel@company.com | AA9: =IF(H8="","",IFERROR(DATEDIF(IF(ISNUMBER(H8),H8,DATE(VALUE(RIGHT(H8,4)),VALUE(MID(H8,3,2)),VALUE(LEFT(H8,2)))),TODAY(),"Y"),"")) | AB9: =IF(OR(D9="",E9=""),"",IFERROR(DATE(MID(E9,7,4),MID(E9,4,2),LEFT(E9,2))-DATE(MID(D9,7,4),MID(D9,4,2),LEFT(D9,2)),"")) -> 6 | AC9: =IF(E9="","Pending",IF(AB9<=5,"On time","Delayed")) -> Delayed
A10: ORD10009 | B10: C008 | C10: P104 | D10: 31/01/2026 | E10: 46055 | F10: kavya Nair | G10: Female | H10: 35585 | I10: Pune | J10: West | K10: Home Appliances | L10: Monitor | M10: 4 | N10: 12000 | O10: 15 | P10: 40800 | Q10: 4 | R10: UPI | S10: Neha | T10: kavya.nair@company.com | U10: 9588041011 | V10: Completed | W10: =IF(OR(Q10<=2,V10="Cancelled"),"Blacklisted",IF(AND(P10>100000,Q10>=4,O10<=10%,V10="Completed"),"Platinum",IF(AND(P10>=50000,Q10>=3,V10="Completed"),"Gold",IF(AND(P10<50000,V10="Completed"),"Silver","")))) -> Silver | X10: =PROPER(TRIM(F10)) -> Kavya Nair | Y10: =LEFT(F10,3)&MID(B10,2,3)&LEFT(I10,2) -> kav008Pu | Z10: =IF(ISNUMBER(SEARCH("@",T10)),LOWER(TRIM(T10)),"invalid email") -> kavya.nair@company.com | AA10: =IF(H9="","",IFERROR(DATEDIF(IF(ISNUMBER(H9),H9,DATE(VALUE(RIGHT(H9,4)),VALUE(MID(H9,3,2)),VALUE(LEFT(H9,2)))),TODAY(),"Y"),"")) -> 31 | AB10: =IF(OR(D10="",E10=""),"",IFERROR(DATE(MID(E10,7,4),MID(E10,4,2),LEFT(E10,2))-DATE(MID(D10,7,4),MID(D10,4,2),LEFT(D10,2)),"")) | AC10: =IF(E10="","Pending",IF(AB10<=5,"On time","Delayed")) -> Delayed
A11: ORD10010 | B11: C002 | C11: P301 | D11: 25/03/2025 | E11: 27/03/2025 | F11: Priya Patel | G11: Female | H11: 33055 | I11: Mumbai | J11: West | K11: Stationery | L11: Notebook | M11: 6 | N11: 60 | O11: 0 | P11: 360 | Q11: 4 | R11: Card | S11: Neha | T11: PRiya.patel@company.com | U11: 9340540608 | V11: Completed | W11: =IF(OR(Q11<=2,V11="Cancelled"),"Blacklisted",IF(AND(P11>100000,Q11>=4,O11<=10%,V11="Completed"),"Platinum",IF(AND(P11>=50000,Q11>=3,V11="Completed"),"Gold",IF(AND(P11<50000,V11="Completed"),"Silver","")))) -> Silver | X11: =PROPER(TRIM(F11)) -> Priya Patel | Y11: =LEFT(F11,3)&MID(B11,2,3)&LEFT(I11,2) -> Pri002Mu | Z11: =IF(ISNUMBER(SEARCH("@",T11)),LOWER(TRIM(T11)),"invalid email") -> priya.patel@company.com | AA11: =IF(H10="","",IFERROR(DATEDIF(IF(ISNUMBER(H10),H10,DATE(VALUE(RIGHT(H10,4)),VALUE(MID(H10,3,2)),VALUE(LEFT(H10,2)))),TODAY(),"Y"),"")) -> 29 | AB11: =IF(OR(D11="",E11=""),"",IFERROR(DATE(MID(E11,7,4),MID(E11,4,2),LEFT(E11,2))-DATE(MID(D11,7,4),MID(D11,4,2),LEFT(D11,2)),"")) -> 2 | AC11: =IF(E11="","Pending",IF(AB11<=5,"On time","Delayed")) -> On time
A12: ORD10011 | B12: C003 | C12: P202 | D12: 19/09/2025 | E12: 23/09/2025 | F12: Rohit Singh | G12: Male | H12: 30229 | I12: Delhi | J12: North | K12: Home Appliances | L12: Iron | M12: -3 | N12: 2200 | O12: 0 | P12: 35200 | Q12: 2 | R12: Card | S12: Rahul | T12: rohit.singh@company.com | U12: 9521710321 | V12: Pending | W12: =IF(OR(Q12<=2,V12="Cancelled"),"Blacklisted",IF(AND(P12>100000,Q12>=4,O12<=10%,V12="Completed"),"Platinum",IF(AND(P12>=50000,Q12>=3,V12="Completed"),"Gold",IF(AND(P12<50000,V12="Completed"),"Silver","")))) -> Blacklisted | X12: =PROPER(TRIM(F12)) -> Rohit Singh | Y12: =LEFT(F12,3)&MID(B12,2,3)&LEFT(I12,2) -> Roh003De | Z12: =IF(ISNUMBER(SEARCH("@",T12)),LOWER(TRIM(T12)),"invalid email") -> rohit.singh@company.com | AA12: =IF(H11="","",IFERROR(DATEDIF(IF(ISNUMBER(H11),H11,DATE(VALUE(RIGHT(H11,4)),VALUE(MID(H11,3,2)),VALUE(LEFT(H11,2)))),TODAY(),"Y"),"")) -> 36 | AB12: =IF(OR(D12="",E12=""),"",IFERROR(DATE(MID(E12,7,4),MID(E12,4,2),LEFT(E12,2))-DATE(MID(D12,7,4),MID(D12,4,2),LEFT(D12,2)),"")) -> 4 | AC12: =IF(E12="","Pending",IF(AB12<=5,"On time","Delayed")) -> On time
A13: ORD10012 | B13: C008 | C13: P201 | D13: 45872 | E13: 15/03/2025 | F13: Kavya Nair | G13: Female | H13: 23/01/1982 | I13: Ahmedabad | J13: West | K13: Home Appliances | L13: Mixer | M13: 10 | N13: 3500 | O13: 5 | P13: 33250 | Q13: 5 | R13: Card | S13: Aisha | T13: kavya.nair@company.com | U13: 9123535241 | V13: Cancelled | W13: =IF(OR(Q13<=2,V13="Cancelled"),"Blacklisted",IF(AND(P13>100000,Q13>=4,O13<=10%,V13="Completed"),"Platinum",IF(AND(P13>=50000,Q13>=3,V13="Completed"),"Gold",IF(AND(P13<50000,V13="Completed"),"Silver","")))) -> Blacklisted | X13: =PROPER(TRIM(F13)) -> Kavya Nair | Y13: =LEFT(F13,3)&MID(B13,2,3)&LEFT(I13,2) -> Kav008Ah | Z13: =IF(ISNUMBER(SEARCH("@",T13)),LOWER(TRIM(T13)),"invalid email") -> kavya.nair@company.com | AA13: =IF(H12="","",IFERROR(DATEDIF(IF(ISNUMBER(H12),H12,DATE(VALUE(RIGHT(H12,4)),VALUE(MID(H12,3,2)),VALUE(LEFT(H12,2)))),TODAY(),"Y"),"")) -> 44 | AB13: =IF(OR(D13="",E13=""),"",IFERROR(DATE(MID(E13,7,4),MID(E13,4,2),LEFT(E13,2))-DATE(MID(D13,7,4),MID(D13,4,2),LEFT(D13,2)),"")) | AC13: =IF(E13="","Pending",IF(AB13<=5,"On time","Delayed")) -> Delayed
A14: ORD10013 | B14: C002 | C14: P202 | D14: 45931 | E14: 15/01/2025 | F14: Priya Patel | G14: Female | H14: 33762 | I14: Pune | J14: West | K14: Home Appliances | L14: Iron | M14: 15 | N14: 2200 | O14: 10 | P14: 29700 | Q14: 1 | R14: UPI | S14: Neha | T14: priya.patel@company.com | U14: 9367316892 | V14: Pending | W14: =IF(OR(Q14<=2,V14="Cancelled"),"Blacklisted",IF(AND(P14>100000,Q14>=4,O14<=10%,V14="Completed"),"Platinum",IF(AND(P14>=50000,Q14>=3,V14="Completed"),"Gold",IF(AND(P14<50000,V14="Completed"),"Silver","")))) -> Blacklisted | X14: =PROPER(TRIM(F14)) -> Priya Patel | Y14: =LEFT(F14,3)&MID(B14,2,3)&LEFT(I14,2) -> Pri002Pu | Z14: =IF(ISNUMBER(SEARCH("@",T14)),LOWER(TRIM(T14)),"invalid email") -> priya.patel@company.com | AA14: =IF(H13="","",IFERROR(DATEDIF(IF(ISNUMBER(H13),H13,DATE(VALUE(RIGHT(H13,4)),VALUE(MID(H13,3,2)),VALUE(LEFT(H13,2)))),TODAY(),"Y"),"")) | AB14: =IF(OR(D14="",E14=""),"",IFERROR(DATE(MID(E14,7,4),MID(E14,4,2),LEFT(E14,2))-DATE(MID(D14,7,4),MID(D14,4,2),LEFT(D14,2)),"")) | AC14: =IF(E14="","Pending",IF(AB14<=5,"On time","Delayed")) -> Delayed
A15: ORD10014 | B15: C003 | C15: P202 | D15: 45903 | E15: 13/03/2025 | F15: rohit Singh | G15: Male | H15: 19/03/2002 | I15: Mumbai | J15: West | K15: Home Appliances | L15: Iron | M15: 17 | N15: 2200 | O15: 5 | P15: 35530 | Q15: 1 | R15: Cash | S15: Karan | T15: rOhit.singh@company.com | U15: 9778489803 | V15: Completed | W15: =IF(OR(Q15<=2,V15="Cancelled"),"Blacklisted",IF(AND(P15>100000,Q15>=4,O15<=10%,V15="Completed"),"Platinum",IF(AND(P15>=50000,Q15>=3,V15="Completed"),"Gold",IF(AND(P15<50000,V15="Completed"),"Silver","")))) -> Blacklisted | X15: =PROPER(TRIM(F15)) -> Rohit Singh | Y15: =LEFT(F15,3)&MID(B15,2,3)&LEFT(I15,2) -> roh003Mu | Z15: =IF(ISNUMBER(SEARCH("@",T15)),LOWER(TRIM(T15)),"invalid email") -> rohit.singh@company.com | AA15: =IF(H14="","",IFERROR(DATEDIF(IF(ISNUMBER(H14),H14,DATE(VALUE(RIGHT(H14,4)),VALUE(MID(H14,3,2)),VALUE(LEFT(H14,2)))),TODAY(),"Y"),"")) -> 34 | AB15: =IF(OR(D15="",E15=""),"",IFERROR(DATE(MID(E15,7,4),MID(E15,4,2),LEFT(E15,2))-DATE(MID(D15,7,4),MID(D15,4,2),LEFT(D15,2)),"")) | AC15: =IF(E15="","Pending",IF(AB15<=5,"On time","Delayed")) -> Delayed
A16: ORD10015 | B16: C008 | C16: P201 | D16: 26/07/2025 | E16: 45846 | F16: Kavya nair | G16: Female | H16: 17/01/2001 | I16: Mumbai | J16: West | K16: Home Appliances | L16: Mixer | M16: 15 | N16: 3500 | O16: 15 | P16: 44625 | Q16: 2 | R16: Cash | S16: Neha | T16: kavya.nair@company.com | U16: 9582960180 | V16: Cancelled | W16: =IF(OR(Q16<=2,V16="Cancelled"),"Blacklisted",IF(AND(P16>100000,Q16>=4,O16<=10%,V16="Completed"),"Platinum",IF(AND(P16>=50000,Q16>=3,V16="Completed"),"Gold",IF(AND(P16<50000,V16="Completed"),"Silver","")))) -> Blacklisted | X16: =PROPER(TRIM(F16)) -> Kavya Nair | Y16: =LEFT(F16,3)&MID(B16,2,3)&LEFT(I16,2) -> Kav008Mu | Z16: =IF(ISNUMBER(SEARCH("@",T16)),LOWER(TRIM(T16)),"invalid email") -> kavya.nair@company.com | AA16: =IF(H15="","",IFERROR(DATEDIF(IF(ISNUMBER(H15),H15,DATE(VALUE(RIGHT(H15,4)),VALUE(MID(H15,3,2)),VALUE(LEFT(H15,2)))),TODAY(),"Y"),"")) | AB16: =IF(OR(D16="",E16=""),"",IFERROR(DATE(MID(E16,7,4),MID(E16,4,2),LEFT(E16,2))-DATE(MID(D16,7,4),MID(D16,4,2),LEFT(D16,2)),"")) | AC16: =IF(E16="","Pending",IF(AB16<=5,"On time","Delayed")) -> Delayed
A17: ORD10016 | B17: C010 | C17: P103 | D17: 46238 | E17: 46330 | F17: Pooja Shah | G17: Female | H17: 37564 | I17: Hyderabad | J17: South | K17: Electronics | L17: Keyboard | M17: 3 | N17: 1200 | O17: 5 | P17: 3420 | Q17: 5 | R17: UPI | S17: Ritika | T17: pooja.shahcompany.com | U17: 9611394005 | V17: Completed | W17: =IF(OR(Q17<=2,V17="Cancelled"),"Blacklisted",IF(AND(P17>100000,Q17>=4,O17<=10%,V17="Completed"),"Platinum",IF(AND(P17>=50000,Q17>=3,V17="Completed"),"Gold",IF(AND(P17<50000,V17="Completed"),"Silver","")))) -> Silver | X17: =PROPER(TRIM(F17)) -> Pooja Shah | Y17: =LEFT(F17,3)&MID(B17,2,3)&LEFT(I17,2) -> Poo010Hy | Z17: =IF(ISNUMBER(SEARCH("@",T17)),LOWER(TRIM(T17)),"invalid email") -> invalid email | AA17: =IF(H16="","",IFERROR(DATEDIF(IF(ISNUMBER(H16),H16,DATE(VALUE(RIGHT(H16,4)),VALUE(MID(H16,3,2)),VALUE(LEFT(H16,2)))),TODAY(),"Y"),"")) | AB17: =IF(OR(D17="",E17=""),"",IFERROR(DATE(MID(E17,7,4),MID(E17,4,2),LEFT(E17,2))-DATE(MID(D17,7,4),MID(D17,4,2),LEFT(D17,2)),"")) | AC17: =IF(E17="","Pending",IF(AB17<=5,"On time","Delayed")) -> Delayed
A18: ORD10017 | B18: C004 | C18: P203 | D18: 22/02/2026 | E18: 46084 | F18: Amit Sharma | G18: Female | H18: 16/01/2002 | I18: Pune | J18: West | K18: Home Appliances | L18: Microwave | M18: 13 | N18: 8500 | O18: 20 | P18: 88400 | Q18: 4 | R18: Card | S18: Rahul | T18: anita.gupta@company.com | U18: 9692599404 | V18: Pending | W18: =IF(OR(Q18<=2,V18="Cancelled"),"Blacklisted",IF(AND(P18>100000,Q18>=4,O18<=10%,V18="Completed"),"Platinum",IF(AND(P18>=50000,Q18>=3,V18="Completed"),"Gold",IF(AND(P18<50000,V18="Completed"),"Silver","")))) | X18: =PROPER(TRIM(F18)) -> Amit Sharma | Y18: =LEFT(F18,3)&MID(B18,2,3)&LEFT(I18,2) -> Ami004Pu | Z18: =IF(ISNUMBER(SEARCH("@",T18)),LOWER(TRIM(T18)),"invalid email") -> anita.gupta@company.com | AA18: =IF(H17="","",IFERROR(DATEDIF(IF(ISNUMBER(H17),H17,DATE(VALUE(RIGHT(H17,4)),VALUE(MID(H17,3,2)),VALUE(LEFT(H17,2)))),TODAY(),"Y"),"")) -> 23 | AB18: =IF(OR(D18="",E18=""),"",IFERROR(DATE(MID(E18,7,4),MID(E18,4,2),LEFT(E18,2))-DATE(MID(D18,7,4),MID(D18,4,2),LEFT(D18,2)),"")) | AC18: =IF(E18="","Pending",IF(AB18<=5,"On time","Delayed")) -> Delayed
A19: ORD10018 | B19: C007 | C19: P203 | D19: 28/02/2026 | E19: 46145 | F19: Arjun Rao | G19: Male | H19: 32761 | I19: Ahmedabad | J19: West | K19: Home Appliances | L19: Microwave | M19: 4 | N19: 8500 | O19: 20 | P19: 27200 | Q19: 5 | R19: Card | S19: Aisha | T19: arjun.rao@company.com | U19: 9426119622 | V19: Pending | W19: =IF(OR(Q19<=2,V19="Cancelled"),"Blacklisted",IF(AND(P19>100000,Q19>=4,O19<=10%,V19="Completed"),"Platinum",IF(AND(P19>=50000,Q19>=3,V19="Completed"),"Gold",IF(AND(P19<50000,V19="Completed"),"Silver","")))) | X19: =PROPER(TRIM(F19)) -> Arjun Rao | Y19: =LEFT(F19,3)&MID(B19,2,3)&LEFT(I19,2) -> Arj007Ah | Z19: =IF(ISNUMBER(SEARCH("@",T19)),LOWER(TRIM(T19)),"invalid email") -> arjun.rao@company.com | AA19: =IF(H18="","",IFERROR(DATEDIF(IF(ISNUMBER(H18),H18,DATE(VALUE(RIGHT(H18,4)),VALUE(MID(H18,3,2)),VALUE(LEFT(H18,2)))),TODAY(),"Y"),"")) | AB19: =IF(OR(D19="",E19=""),"",IFERROR(DATE(MID(E19,7,4),MID(E19,4,2),LEFT(E19,2))-DATE(MID(D19,7,4),MID(D19,4,2),LEFT(D19,2)),"")) | AC19: =IF(E19="","Pending",IF(AB19<=5,"On time","Delayed")) -> Delayed
A20: ORD10019 | B20: C007 | C20: P102 | D20: 45669 | E20: 45759 | F20: arjun rao | G20: Male | H20: 28/10/1991 | I20: Mumbai | J20: West | K20: Electronics | L20: Mouse | M20: 9 | N20: 700 | O20: 5 | P20: 5985 | Q20: 3 | R20: UPI | S20: Ritika | T20: arjun.Rao@company.com | U20: 9184436009 | V20: Pending | W20: =IF(OR(Q20<=2,V20="Cancelled"),"Blacklisted",IF(AND(P20>100000,Q20>=4,O20<=10%,V20="Completed"),"Platinum",IF(AND(P20>=50000,Q20>=3,V20="Completed"),"Gold",IF(AND(P20<50000,V20="Completed"),"Silver","")))) | X20: =PROPER(TRIM(F20)) -> Arjun Rao | Y20: =LEFT(F20,3)&MID(B20,2,3)&LEFT(I20,2) -> arj007Mu | Z20: =IF(ISNUMBER(SEARCH("@",T20)),LOWER(TRIM(T20)),"invalid email") -> arjun.rao@company.com | AA20: =IF(H19="","",IFERROR(DATEDIF(IF(ISNUMBER(H19),H19,DATE(VALUE(RIGHT(H19,4)),VALUE(MID(H19,3,2)),VALUE(LEFT(H19,2)))),TODAY(),"Y"),"")) -> 37 | AB20: =IF(OR(D20="",E20=""),"",IFERROR(DATE(MID(E20,7,4),MID(E20,4,2),LEFT(E20,2))-DATE(MID(D20,7,4),MID(D20,4,2),LEFT(D20,2)),"")) | AC20: =IF(E20="","Pending",IF(AB20<=5,"On time","Delayed")) -> Delayed
A21: ORD10020 | B21: C008 | C21: P101 | D21: 25/06/2025 | E21: 45723 | F21: Kavya Nair | G21: Female | H21: 32876 | I21: Ahmedabad | J21: West | K21: Electronics | L21: Laptop | M21: 8 | N21: 55000 | O21: 20 | P21: 352000 | Q21: 1 | R21: Cash | S21: Karan | T21: kavya.nair@company.com | U21: 9263774934 | V21: Completed | W21: =IF(OR(Q21<=2,V21="Cancelled"),"Blacklisted",IF(AND(P21>100000,Q21>=4,O21<=10%,V21="Completed"),"Platinum",IF(AND(P21>=50000,Q21>=3,V21="Completed"),"Gold",IF(AND(P21<50000,V21="Completed"),"Silver","")))) -> Blacklisted | X21: =PROPER(TRIM(F21)) -> Kavya Nair | Y21: =LEFT(F21,3)&MID(B21,2,3)&LEFT(I21,2) -> Kav008Ah | Z21: =IF(ISNUMBER(SEARCH("@",T21)),LOWER(TRIM(T21)),"invalid email") -> kavya.nair@company.com | AA21: =IF(H20="","",IFERROR(DATEDIF(IF(ISNUMBER(H20),H20,DATE(VALUE(RIGHT(H20,4)),VALUE(MID(H20,3,2)),VALUE(LEFT(H20,2)))),TODAY(),"Y"),"")) | AB21: =IF(OR(D21="",E21=""),"",IFERROR(DATE(MID(E21,7,4),MID(E21,4,2),LEFT(E21,2))-DATE(MID(D21,7,4),MID(D21,4,2),LEFT(D21,2)),"")) | AC21: =IF(E21="","Pending",IF(AB21<=5,"On time","Delayed")) -> Delayed
A22: ORD10021 | B22: C003 | C22: P102 | D22: 26/04/2025 | E22: 45782 | F22: Rohit Singh | G22: Male | H22: 18/07/2002 | I22: Delhi | J22: North | K22: electronics | L22: Mouse | M22: 10 | N22: 700 | O22: 20 | P22: 5600 | Q22: 4 | R22: Card | S22: Aisha | T22: rohit.singh@company.com | U22: 9473159572 | V22: Cancelled | W22: =IF(OR(Q22<=2,V22="Cancelled"),"Blacklisted",IF(AND(P22>100000,Q22>=4,O22<=10%,V22="Completed"),"Platinum",IF(AND(P22>=50000,Q22>=3,V22="Completed"),"Gold",IF(AND(P22<50000,V22="Completed"),"Silver","")))) -> Blacklisted | X22: =PROPER(TRIM(F22)) -> Rohit Singh | Y22: =LEFT(F22,3)&MID(B22,2,3)&LEFT(I22,2) -> Roh003De | Z22: =IF(ISNUMBER(SEARCH("@",T22)),LOWER(TRIM(T22)),"invalid email") -> rohit.singh@company.com | AA22: =IF(H21="","",IFERROR(DATEDIF(IF(ISNUMBER(H21),H21,DATE(VALUE(RIGHT(H21,4)),VALUE(MID(H21,3,2)),VALUE(LEFT(H21,2)))),TODAY(),"Y"),"")) -> 36 | AB22: =IF(OR(D22="",E22=""),"",IFERROR(DATE(MID(E22,7,4),MID(E22,4,2),LEFT(E22,2))-DATE(MID(D22,7,4),MID(D22,4,2),LEFT(D22,2)),"")) | AC22: =IF(E22="","Pending",IF(AB22<=5,"On time","Delayed")) -> Delayed
A23: ORD10022 | B23: C008 | C23: P201 | D23: 45717 | E23: 45870 | F23: kavya Nair | G23: Female | H23: 15/12/2004 | I23: Bengaluru | J23: South | K23: Home Appliances | L23: Mixer | M23: 1 | N23: 3500 | O23: 5 | P23: 3325 | Q23: 3 | R23: UPI | S23: Neha | T23: kavya.nair@company.com | U23: 9660493688 | V23: Cancelled | W23: =IF(OR(Q23<=2,V23="Cancelled"),"Blacklisted",IF(AND(P23>100000,Q23>=4,O23<=10%,V23="Completed"),"Platinum",IF(AND(P23>=50000,Q23>=3,V23="Completed"),"Gold",IF(AND(P23<50000,V23="Completed"),"Silver","")))) -> Blacklisted | X23: =PROPER(TRIM(F23)) -> Kavya Nair | Y23: =LEFT(F23,3)&MID(B23,2,3)&LEFT(I23,2) -> kav008Be | Z23: =IF(ISNUMBER(SEARCH("@",T23)),LOWER(TRIM(T23)),"invalid email") -> kavya.nair@company.com | AA23: =IF(H22="","",IFERROR(DATEDIF(IF(ISNUMBER(H22),H22,DATE(VALUE(RIGHT(H22,4)),VALUE(MID(H22,3,2)),VALUE(LEFT(H22,2)))),TODAY(),"Y"),"")) | AB23: =IF(OR(D23="",E23=""),"",IFERROR(DATE(MID(E23,7,4),MID(E23,4,2),LEFT(E23,2))-DATE(MID(D23,7,4),MID(D23,4,2),LEFT(D23,2)),"")) | AC23: =IF(E23="","Pending",IF(AB23<=5,"On time","Delayed")) -> Delayed
A24: ORD10023 | B24: C002 | C24: P102 | D24: 19/04/2025 | E24: 30/04/2025 | F24: Priya Patel | G24: Female | H24: 30779 | I24: Jaipur | J24: North | K24: Electronics | L24: Mouse | M24: 19 | N24: 700 | O24: 15 | P24: 11305 | Q24: 3 | R24: NetBanking | S24: Karan | T24: priya.patel@company.com | U24: 9513325819 | V24: Pending | W24: =IF(OR(Q24<=2,V24="Cancelled"),"Blacklisted",IF(AND(P24>100000,Q24>=4,O24<=10%,V24="Completed"),"Platinum",IF(AND(P24>=50000,Q24>=3,V24="Completed"),"Gold",IF(AND(P24<50000,V24="Completed"),"Silver","")))) | X24: =PROPER(TRIM(F24)) -> Priya Patel | Y24: =LEFT(F24,3)&MID(B24,2,3)&LEFT(I24,2) -> Pri002Ja | Z24: =IF(ISNUMBER(SEARCH("@",T24)),LOWER(TRIM(T24)),"invalid email") -> priya.patel@company.com | AA24: =IF(H23="","",IFERROR(DATEDIF(IF(ISNUMBER(H23),H23,DATE(VALUE(RIGHT(H23,4)),VALUE(MID(H23,3,2)),VALUE(LEFT(H23,2)))),TODAY(),"Y"),"")) | AB24: =IF(OR(D24="",E24=""),"",IFERROR(DATE(MID(E24,7,4),MID(E24,4,2),LEFT(E24,2))-DATE(MID(D24,7,4),MID(D24,4,2),LEFT(D24,2)),"")) -> 11 | AC24: =IF(E24="","Pending",IF(AB24<=5,"On time","Delayed")) -> Delayed
A25: ORD10024 | B25: C009 | C25: P101 | D25: 22/12/2025 | E25: 46023 | F25: Mohit Verma | G25: Male | H25: 25/02/1978 | I25: Bengaluru | J25: South | K25: Electronics | L25: Laptop | M25: 12 | N25: 55000 | O25: 0 | P25: 660000 | Q25: 1 | R25: Card | S25: Rahul | T25: mohit.verma@company.com | U25: 9641063242 | V25: Pending | W25: =IF(OR(Q25<=2,V25="Cancelled"),"Blacklisted",IF(AND(P25>100000,Q25>=4,O25<=10%,V25="Completed"),"Platinum",IF(AND(P25>=50000,Q25>=3,V25="Completed"),"Gold",IF(AND(P25<50000,V25="Completed"),"Silver","")))) -> Blacklisted | X25: =PROPER(TRIM(F25)) -> Mohit Verma | Y25: =LEFT(F25,3)&MID(B25,2,3)&LEFT(I25,2) -> Moh009Be | Z25: =IF(ISNUMBER(SEARCH("@",T25)),LOWER(TRIM(T25)),"invalid email") -> mohit.verma@company.com | AA25: =IF(H24="","",IFERROR(DATEDIF(IF(ISNUMBER(H24),H24,DATE(VALUE(RIGHT(H24,4)),VALUE(MID(H24,3,2)),VALUE(LEFT(H24,2)))),TODAY(),"Y"),"")) -> 42 | AB25: =IF(OR(D25="",E25=""),"",IFERROR(DATE(MID(E25,7,4),MID(E25,4,2),LEFT(E25,2))-DATE(MID(D25,7,4),MID(D25,4,2),LEFT(D25,2)),"")) | AC25: =IF(E25="","Pending",IF(AB25<=5,"On time","Delayed")) -> Delayed
A26: ORD10025 | B26: C005 | C26: P302 | D26: 46269 | E26: 20/04/2026 | F26: Vikas Mehta | G26: Male | H26: 33305 | I26: Mumbai | J26: West | K26: Stationery | L26: Pen | M26: 1 | N26: 20 | O26: 5 | P26: 19 | Q26: 5 | R26: Card | S26: Ritika | T26: vikas.mehta@company.com | U26: 9277372518 | V26: Cancelled | W26: =IF(OR(Q26<=2,V26="Cancelled"),"Blacklisted",IF(AND(P26>100000,Q26>=4,O26<=10%,V26="Completed"),"Platinum",IF(AND(P26>=50000,Q26>=3,V26="Completed"),"Gold",IF(AND(P26<50000,V26="Completed"),"Silver","")))) -> Blacklisted | X26: =PROPER(TRIM(F26)) -> Vikas Mehta | Y26: =LEFT(F26,3)&MID(B26,2,3)&LEFT(I26,2) -> Vik005Mu | Z26: =IF(ISNUMBER(SEARCH("@",T26)),LOWER(TRIM(T26)),"invalid email") -> vikas.mehta@company.com | AA26: =IF(H25="","",IFERROR(DATEDIF(IF(ISNUMBER(H25),H25,DATE(VALUE(RIGHT(H25,4)),VALUE(MID(H25,3,2)),VALUE(LEFT(H25,2)))),TODAY(),"Y"),"")) | AB26: =IF(OR(D26="",E26=""),"",IFERROR(DATE(MID(E26,7,4),MID(E26,4,2),LEFT(E26,2))-DATE(MID(D26,7,4),MID(D26,4,2),LEFT(D26,2)),"")) | AC26: =IF(E26="","Pending",IF(AB26<=5,"On time","Delayed")) -> Delayed
A27: ORD10026 | B27: C007 | C27: P302 | D27: 24/06/2025 | E27: 45695 | F27: Arjun Rao | G27: Male | H27: 28441 | I27: Mumbai | J27: West | K27: Stationery | L27: Pen | M27: 2 | N27: 20 | O27: 15 | P27: 34 | Q27: 1 | R27: UPI | S27: Ritika | T27: arjun.rao@company.com | U27: 9193154372 | V27: Pending | W27: =IF(OR(Q27<=2,V27="Cancelled"),"Blacklisted",IF(AND(P27>100000,Q27>=4,O27<=10%,V27="Completed"),"Platinum",IF(AND(P27>=50000,Q27>=3,V27="Completed"),"Gold",IF(AND(P27<50000,V27="Completed"),"Silver","")))) -> Blacklisted | X27: =PROPER(TRIM(F27)) -> Arjun Rao | Y27: =LEFT(F27,3)&MID(B27,2,3)&LEFT(I27,2) -> Arj007Mu | Z27: =IF(ISNUMBER(SEARCH("@",T27)),LOWER(TRIM(T27)),"invalid email") -> arjun.rao@company.com | AA27: =IF(H26="","",IFERROR(DATEDIF(IF(ISNUMBER(H26),H26,DATE(VALUE(RIGHT(H26,4)),VALUE(MID(H26,3,2)),VALUE(LEFT(H26,2)))),TODAY(),"Y"),"")) -> 35 | AB27: =IF(OR(D27="",E27=""),"",IFERROR(DATE(MID(E27,7,4),MID(E27,4,2),LEFT(E27,2))-DATE(MID(D27,7,4),MID(D27,4,2),LEFT(D27,2)),"")) | AC27: =IF(E27="","Pending",IF(AB27<=5,"On time","Delayed")) -> Delayed
A28: ORD10027 | B28: C009 | C28: P201 | D28: 22/05/2025 | E28: 25/05/2025 | F28: Mohit Verma | G28: Male | H28: 33818 | I28: Ahmedabad | J28: West | K28: Home Appliances | L28: Mixer | M28: 12 | N28: 3500 | O28: 15 | P28: 35700 | Q28: 4 | R28: Cash | S28: Rahul | T28: mohit.verma@company.com | U28: 9400073244 | V28: Cancelled | W28: =IF(OR(Q28<=2,V28="Cancelled"),"Blacklisted",IF(AND(P28>100000,Q28>=4,O28<=10%,V28="Completed"),"Platinum",IF(AND(P28>=50000,Q28>=3,V28="Completed"),"Gold",IF(AND(P28<50000,V28="Completed"),"Silver","")))) -> Blacklisted | X28: =PROPER(TRIM(F28)) -> Mohit Verma | Y28: =LEFT(F28,3)&MID(B28,2,3)&LEFT(I28,2) -> Moh009Ah | Z28: =IF(ISNUMBER(SEARCH("@",T28)),LOWER(TRIM(T28)),"invalid email") -> mohit.verma@company.com | AA28: =IF(H27="","",IFERROR(DATEDIF(IF(ISNUMBER(H27),H27,DATE(VALUE(RIGHT(H27,4)),VALUE(MID(H27,3,2)),VALUE(LEFT(H27,2)))),TODAY(),"Y"),"")) -> 48 | AB28: =IF(OR(D28="",E28=""),"",IFERROR(DATE(MID(E28,7,4),MID(E28,4,2),LEFT(E28,2))-DATE(MID(D28,7,4),MID(D28,4,2),LEFT(D28,2)),"")) -> 3 | AC28: =IF(E28="","Pending",IF(AB28<=5,"On time","Delayed")) -> On time
A29: ORD10028 | B29: C008 | C29: P103 | D29: 13/03/2026 | E29: 20/03/2026 | F29: Kavya Nair | G29: Female | H29: 38113 | I29: Ahmedabad | J29: West | K29: Electronics | L29: Keyboard | M29: 11 | N29: 1200 | O29: 0 | P29: 13200 | Q29: 2 | R29: UPI | S29: Karan | T29: kavya.nair@company.com | U29: 9771556720 | V29: Completed | W29: =IF(OR(Q29<=2,V29="Cancelled"),"Blacklisted",IF(AND(P29>100000,Q29>=4,O29<=10%,V29="Completed"),"Platinum",IF(AND(P29>=50000,Q29>=3,V29="Completed"),"Gold",IF(AND(P29<50000,V29="Completed"),"Silver","")))) -> Blacklisted | X29: =PROPER(TRIM(F29)) -> Kavya Nair | Y29: =LEFT(F29,3)&MID(B29,2,3)&LEFT(I29,2) -> Kav008Ah | Z29: =IF(ISNUMBER(SEARCH("@",T29)),LOWER(TRIM(T29)),"invalid email") -> kavya.nair@company.com | AA29: =IF(H28="","",IFERROR(DATEDIF(IF(ISNUMBER(H28),H28,DATE(VALUE(RIGHT(H28,4)),VALUE(MID(H28,3,2)),VALUE(LEFT(H28,2)))),TODAY(),"Y"),"")) -> 34 | AB29: =IF(OR(D29="",E29=""),"",IFERROR(DATE(MID(E29,7,4),MID(E29,4,2),LEFT(E29,2))-DATE(MID(D29,7,4),MID(D29,4,2),LEFT(D29,2)),"")) -> 7 | AC29: =IF(E29="","Pending",IF(AB29<=5,"On time","Delayed")) -> Delayed
A30: ORD10029 | B30: C003 | C30: P203 | D30: 45878 | E30: 20/09/2025 | F30: Rohit Singh | G30: Male | H30: 37203 | I30: Pune | J30: West | K30: Home Appliances | L30: Microwave | M30: 6 | N30: 8500 | O30: 65 | P30: 51000 | Q30: 1 | R30: Card | S30: Aisha | T30: rohit.singh@company.com | U30: 9127480734 | V30: Completed | W30: =IF(OR(Q30<=2,V30="Cancelled"),"Blacklisted",IF(AND(P30>100000,Q30>=4,O30<=10%,V30="Completed"),"Platinum",IF(AND(P30>=50000,Q30>=3,V30="Completed"),"Gold",IF(AND(P30<50000,V30="Completed"),"Silver","")))) -> Blacklisted | X30: =PROPER(TRIM(F30)) -> Rohit Singh | Y30: =LEFT(F30,3)&MID(B30,2,3)&LEFT(I30,2) -> Roh003Pu | Z30: =IF(ISNUMBER(SEARCH("@",T30)),LOWER(TRIM(T30)),"invalid email") -> rohit.singh@company.com | AA30: =IF(H29="","",IFERROR(DATEDIF(IF(ISNUMBER(H29),H29,DATE(VALUE(RIGHT(H29,4)),VALUE(MID(H29,3,2)),VALUE(LEFT(H29,2)))),TODAY(),"Y"),"")) -> 22 | AB30: =IF(OR(D30="",E30=""),"",IFERROR(DATE(MID(E30,7,4),MID(E30,4,2),LEFT(E30,2))-DATE(MID(D30,7,4),MID(D30,4,2),LEFT(D30,2)),"")) | AC30: =IF(E30="","Pending",IF(AB30<=5,"On time","Delayed")) -> Delayed
A31: ORD10030 | B31: C006 | C31: P301 | D31: 46327 | E31: 16/01/2026 | F31: Sneha Joshi | G31: Female | H31: 29680 | I31: Pune | J31: West | K31: Stationery | L31: Notebook | M31: 2 | N31: 60 | O31: 5 | P31: 114 | Q31: 3 | R31: Cash | S31: Karan | T31: sneha.joshi@company.com | U31: 9512997042 | V31: Cancelled | W31: =IF(OR(Q31<=2,V31="Cancelled"),"Blacklisted",IF(AND(P31>100000,Q31>=4,O31<=10%,V31="Completed"),"Platinum",IF(AND(P31>=50000,Q31>=3,V31="Completed"),"Gold",IF(AND(P31<50000,V31="Completed"),"Silver","")))) -> Blacklisted | X31: =PROPER(TRIM(F31)) -> Sneha Joshi | Y31: =LEFT(F31,3)&MID(B31,2,3)&LEFT(I31,2) -> Sne006Pu | Z31: =IF(ISNUMBER(SEARCH("@",T31)),LOWER(TRIM(T31)),"invalid email") -> sneha.joshi@company.com | AA31: =IF(H30="","",IFERROR(DATEDIF(IF(ISNUMBER(H30),H30,DATE(VALUE(RIGHT(H30,4)),VALUE(MID(H30,3,2)),VALUE(LEFT(H30,2)))),TODAY(),"Y"),"")) -> 24 | AB31: =IF(OR(D31="",E31=""),"",IFERROR(DATE(MID(E31,7,4),MID(E31,4,2),LEFT(E31,2))-DATE(MID(D31,7,4),MID(D31,4,2),LEFT(D31,2)),"")) | AC31: =IF(E31="","Pending",IF(AB31<=5,"On time","Delayed")) -> Delayed
A32: ORD10031 | B32: C008 | C32: P303 | D32: 16/06/2025 | E32: 26/06/2025 | F32: Kavya Nair | G32: Female | H32: 35102 | I32: Bengaluru | J32: South | K32: Stationery | L32: Marker | M32: 19 | N32: 45 | O32: 20 | P32: 684 | Q32: 4 | R32: NetBanking | S32: Aisha | T32: kavya.nair@company.com | U32: 9372748661 | V32: Cancelled | W32: =IF(OR(Q32<=2,V32="Cancelled"),"Blacklisted",IF(AND(P32>100000,Q32>=4,O32<=10%,V32="Completed"),"Platinum",IF(AND(P32>=50000,Q32>=3,V32="Completed"),"Gold",IF(AND(P32<50000,V32="Completed"),"Silver","")))) -> Blacklisted | X32: =PROPER(TRIM(F32)) -> Kavya Nair | Y32: =LEFT(F32,3)&MID(B32,2,3)&LEFT(I32,2) -> Kav008Be | Z32: =IF(ISNUMBER(SEARCH("@",T32)),LOWER(TRIM(T32)),"invalid email") -> kavya.nair@company.com | AA32: =IF(H31="","",IFERROR(DATEDIF(IF(ISNUMBER(H31),H31,DATE(VALUE(RIGHT(H31,4)),VALUE(MID(H31,3,2)),VALUE(LEFT(H31,2)))),TODAY(),"Y"),"")) -> 45 | AB32: =IF(OR(D32="",E32=""),"",IFERROR(DATE(MID(E32,7,4),MID(E32,4,2),LEFT(E32,2))-DATE(MID(D32,7,4),MID(D32,4,2),LEFT(D32,2)),"")) -> 10 | AC32: =IF(E32="","Pending",IF(AB32<=5,"On time","Delayed")) -> Delayed
A33: ORD10032 | B33: C002 | C33: P104 | D33: 45664 | E33: 13/07/2025 | F33: Priya Patel | G33: Female | H33: 15/11/1976 | I33: Ahmedabad | J33: West | K33: Electronics | L33: Monitor | M33: 11 | N33: 12000 | O33: 0 | P33: 132000 | Q33: 3 | R33: UPI | S33: Ritika | T33: priya.patel@company.com | U33: 9570437805 | V33: Pending | W33: =IF(OR(Q33<=2,V33="Cancelled"),"Blacklisted",IF(AND(P33>100000,Q33>=4,O33<=10%,V33="Completed"),"Platinum",IF(AND(P33>=50000,Q33>=3,V33="Completed"),"Gold",IF(AND(P33<50000,V33="Completed"),"Silver","")))) | X33: =PROPER(TRIM(F33)) -> Priya Patel | Y33: =LEFT(F33,3)&MID(B33,2,3)&LEFT(I33,2) -> Pri002Ah | Z33: =IF(ISNUMBER(SEARCH("@",T33)),LOWER(TRIM(T33)),"invalid email") -> priya.patel@company.com | AA33: =IF(H32="","",IFERROR(DATEDIF(IF(ISNUMBER(H32),H32,DATE(VALUE(RIGHT(H32,4)),VALUE(MID(H32,3,2)),VALUE(LEFT(H32,2)))),TODAY(),"Y"),"")) -> 30 | AB33: =IF(OR(D33="",E33=""),"",IFERROR(DATE(MID(E33,7,4),MID(E33,4,2),LEFT(E33,2))-DATE(MID(D33,7,4),MID(D33,4,2),LEFT(D33,2)),"")) | AC33: =IF(E33="","Pending",IF(AB33<=5,"On time","Delayed")) -> Delayed
A34: ORD10033 | B34: C006 | C34: P202 | D34: 45841 | E34: 15/03/2025 | F34: Sneha Joshi | G34: Female | H34: 28/10/1988 | I34: Bengaluru | J34: South | K34: Home Appliances | L34: Iron | M34: 20 | N34: 2200 | O34: 5 | P34: 41800 | Q34: 1 | R34: Cash | S34: Rahul | T34: sneha.joshi@company.com | U34: 9310669113 | V34: Pending | W34: =IF(OR(Q34<=2,V34="Cancelled"),"Blacklisted",IF(AND(P34>100000,Q34>=4,O34<=10%,V34="Completed"),"Platinum",IF(AND(P34>=50000,Q34>=3,V34="Completed"),"Gold",IF(AND(P34<50000,V34="Completed"),"Silver","")))) -> Blacklisted | X34: =PROPER(TRIM(F34)) -> Sneha Joshi | Y34: =LEFT(F34,3)&MID(B34,2,3)&LEFT(I34,2) -> Sne006Be | Z34: =IF(ISNUMBER(SEARCH("@",T34)),LOWER(TRIM(T34)),"invalid email") -> sneha.joshi@company.com | AA34: =IF(H33="","",IFERROR(DATEDIF(IF(ISNUMBER(H33),H33,DATE(VALUE(RIGHT(H33,4)),VALUE(MID(H33,3,2)),VALUE(LEFT(H33,2)))),TODAY(),"Y"),"")) | AB34: =IF(OR(D34="",E34=""),"",IFERROR(DATE(MID(E34,7,4),MID(E34,4,2),LEFT(E34,2))-DATE(MID(D34,7,4),MID(D34,4,2),LEFT(D34,2)),"")) | AC34: =IF(E34="","Pending",IF(AB34<=5,"On time","Delayed")) -> Delayed
A35: ORD10034 | B35: C007 | C35: P302 | D35: 24/06/2025 | E35: 45754 | F35: Arjun Rao | G35: Male | H35: 23/06/2004 | I35: Ahmedabad | J35: West | K35: Stationery | L35: Pen | M35: 3 | N35: 20 | O35: 0 | P35: 60 | Q35: 2 | R35: Card | S35: Ritika | T35: wrongmail | U35: 9437132894 | V35: Cancelled | W35: =IF(OR(Q35<=2,V35="Cancelled"),"Blacklisted",IF(AND(P35>100000,Q35>=4,O35<=10%,V35="Completed"),"Platinum",IF(AND(P35>=50000,Q35>=3,V35="Completed"),"Gold",IF(AND(P35<50000,V35="Completed"),"Silver","")))) -> Blacklisted | X35: =PROPER(TRIM(F35)) -> Arjun Rao | Y35: =LEFT(F35,3)&MID(B35,2,3)&LEFT(I35,2) -> Arj007Ah | Z35: =IF(ISNUMBER(SEARCH("@",T35)),LOWER(TRIM(T35)),"invalid email") -> invalid email | AA35: =IF(H34="","",IFERROR(DATEDIF(IF(ISNUMBER(H34),H34,DATE(VALUE(RIGHT(H34,4)),VALUE(MID(H34,3,2)),VALUE(LEFT(H34,2)))),TODAY(),"Y"),"")) | AB35: =IF(OR(D35="",E35=""),"",IFERROR(DATE(MID(E35,7,4),MID(E35,4,2),LEFT(E35,2))-DATE(MID(D35,7,4),MID(D35,4,2),LEFT(D35,2)),"")) | AC35: =IF(E35="","Pending",IF(AB35<=5,"On time","Delayed")) -> Delayed
A36: ORD10035 | B36: C003 | C36: P303 | D36: 45910 | E36: 19/10/2025 | F36: Rohit Singh | G36: Male | H36: 22/04/1996 | I36: Pune | J36: West | K36: Stationery | L36: Marker | M36: 18 | N36: 45 | O36: 20 | P36: 648 | Q36: 4 | R36: NetBanking | S36: Ritika | T36: rohit.singh@company.com | U36: 9762437243 | V36: Cancelled | W36: =IF(OR(Q36<=2,V36="Cancelled"),"Blacklisted",IF(AND(P36>100000,Q36>=4,O36<=10%,V36="Completed"),"Platinum",IF(AND(P36>=50000,Q36>=3,V36="Completed"),"Gold",IF(AND(P36<50000,V36="Completed"),"Silver","")))) -> Blacklisted | X36: =PROPER(TRIM(F36)) -> Rohit Singh | Y36: =LEFT(F36,3)&MID(B36,2,3)&LEFT(I36,2) -> Roh003Pu | Z36: =IF(ISNUMBER(SEARCH("@",T36)),LOWER(TRIM(T36)),"invalid email") -> rohit.singh@company.com | AA36: =IF(H35="","",IFERROR(DATEDIF(IF(ISNUMBER(H35),H35,DATE(VALUE(RIGHT(H35,4)),VALUE(MID(H35,3,2)),VALUE(LEFT(H35,2)))),TODAY(),"Y"),"")) | AB36: =IF(OR(D36="",E36=""),"",IFERROR(DATE(MID(E36,7,4),MID(E36,4,2),LEFT(E36,2))-DATE(MID(D36,7,4),MID(D36,4,2),LEFT(D36,2)),"")) | AC36: =IF(E36="","Pending",IF(AB36<=5,"On time","Delayed")) -> Delayed
A37: ORD10036 | B37: C003 | C37: P103 | D37: 19/11/2025 | E37: 26/11/2025 | F37: Rohit Singh | G37: Male | H37: 29043 | I37: Bengaluru | J37: South | K37: Electronics | L37: Keyboard | M37: 4 | N37: 1200 | O37: 20 | P37: 3840 | Q37: 3 | R37: NetBanking | S37: Aisha | T37: rohit.singh@company.com | U37: 9149046970 | V37: Completed | W37: =IF(OR(Q37<=2,V37="Cancelled"),"Blacklisted",IF(AND(P37>100000,Q37>=4,O37<=10%,V37="Completed"),"Platinum",IF(AND(P37>=50000,Q37>=3,V37="Completed"),"Gold",IF(AND(P37<50000,V37="Completed"),"Silver","")))) -> Silver | X37: =PROPER(TRIM(F37)) -> Rohit Singh | Y37: =LEFT(F37,3)&MID(B37,2,3)&LEFT(I37,2) -> Roh003Be | Z37: =IF(ISNUMBER(SEARCH("@",T37)),LOWER(TRIM(T37)),"invalid email") -> rohit.singh@company.com | AA37: =IF(H36="","",IFERROR(DATEDIF(IF(ISNUMBER(H36),H36,DATE(VALUE(RIGHT(H36,4)),VALUE(MID(H36,3,2)),VALUE(LEFT(H36,2)))),TODAY(),"Y"),"")) | AB37: =IF(OR(D37="",E37=""),"",IFERROR(DATE(MID(E37,7,4),MID(E37,4,2),LEFT(E37,2))-DATE(MID(D37,7,4),MID(D37,4,2),LEFT(D37,2)),"")) -> 7 | AC37: =IF(E37="","Pending",IF(AB37<=5,"On time","Delayed")) -> Delayed
A38: ORD10037 | B38: C009 | C38: P101 | D38: 45788 | E38: 14/11/2025 | F38: Mohit Verma | G38: Male | H38: 27/09/1980 | I38: Kolkata | J38: East | K38: Electronics | L38: Laptop | M38: 10 | N38: 55000 | O38: 0 | P38: 550000 | Q38: 1 | R38: UPI | S38: Rahul | T38: mohit.verma@company.com | U38: 9869182901 | V38: Cancelled | W38: =IF(OR(Q38<=2,V38="Cancelled"),"Blacklisted",IF(AND(P38>100000,Q38>=4,O38<=10%,V38="Completed"),"Platinum",IF(AND(P38>=50000,Q38>=3,V38="Completed"),"Gold",IF(AND(P38<50000,V38="Completed"),"Silver","")))) -> Blacklisted | X38: =PROPER(TRIM(F38)) -> Mohit Verma | Y38: =LEFT(F38,3)&MID(B38,2,3)&LEFT(I38,2) -> Moh009Ko | Z38: =IF(ISNUMBER(SEARCH("@",T38)),LOWER(TRIM(T38)),"invalid email") -> mohit.verma@company.com | AA38: =IF(H37="","",IFERROR(DATEDIF(IF(ISNUMBER(H37),H37,DATE(VALUE(RIGHT(H37,4)),VALUE(MID(H37,3,2)),VALUE(LEFT(H37,2)))),TODAY(),"Y"),"")) -> 47 | AB38: =IF(OR(D38="",E38=""),"",IFERROR(DATE(MID(E38,7,4),MID(E38,4,2),LEFT(E38,2))-DATE(MID(D38,7,4),MID(D38,4,2),LEFT(D38,2)),"")) | AC38: =IF(E38="","Pending",IF(AB38<=5,"On time","Delayed")) -> Delayed
A39: ORD10038 | B39: C006 | C39: P201 | D39: 46237 | E39: 20/03/2026 | F39: Sneha Joshi | G39: Female | H39: 21/06/1980 | I39: Delhi | J39: North | K39: Home Appliances | L39: Mixer | M39: 20 | N39: 3500 | O39: 10 | P39: 63000 | Q39: 3 | R39: Card | S39: Rahul | T39: sneha.joshi@company.com | U39: 9283578533 | V39: Cancelled | W39: =IF(OR(Q39<=2,V39="Cancelled"),"Blacklisted",IF(AND(P39>100000,Q39>=4,O39<=10%,V39="Completed"),"Platinum",IF(AND(P39>=50000,Q39>=3,V39="Completed"),"Gold",IF(AND(P39<50000,V39="Completed"),"Silver","")))) -> Blacklisted | X39: =PROPER(TRIM(F39)) -> Sneha Joshi | Y39: =LEFT(F39,3)&MID(B39,2,3)&LEFT(I39,2) -> Sne006De | Z39: =IF(ISNUMBER(SEARCH("@",T39)),LOWER(TRIM(T39)),"invalid email") -> sneha.joshi@company.com | AA39: =IF(H38="","",IFERROR(DATEDIF(IF(ISNUMBER(H38),H38,DATE(VALUE(RIGHT(H38,4)),VALUE(MID(H38,3,2)),VALUE(LEFT(H38,2)))),TODAY(),"Y"),"")) | AB39: =IF(OR(D39="",E39=""),"",IFERROR(DATE(MID(E39,7,4),MID(E39,4,2),LEFT(E39,2))-DATE(MID(D39,7,4),MID(D39,4,2),LEFT(D39,2)),"")) | AC39: =IF(E39="","Pending",IF(AB39<=5,"On time","Delayed")) -> Delayed
A40: ORD10039 | B40: C008 | C40: P302 | D40: 13/02/2025 | E40: 19/02/2025 | F40: Kavya Nair | G40: Female | H40: 17/06/1979 | I40: Pune | J40: West | K40: Stationery | L40: Pen | M40: 5 | N40: 1200 | O40: 0 | P40: 100 | Q40: 1 | R40: Cash | S40: Rahul | T40: kavya.nair@company.com | U40: 9963005771 | V40: Cancelled | W40: =IF(OR(Q40<=2,V40="Cancelled"),"Blacklisted",IF(AND(P40>100000,Q40>=4,O40<=10%,V40="Completed"),"Platinum",IF(AND(P40>=50000,Q40>=3,V40="Completed"),"Gold",IF(AND(P40<50000,V40="Completed"),"Silver","")))) -> Blacklisted | X40: =PROPER(TRIM(F40)) -> Kavya Nair | Y40: =LEFT(F40,3)&MID(B40,2,3)&LEFT(I40,2) -> Kav008Pu | Z40: =IF(ISNUMBER(SEARCH("@",T40)),LOWER(TRIM(T40)),"invalid email") -> kavya.nair@company.com | AA40: =IF(H39="","",IFERROR(DATEDIF(IF(ISNUMBER(H39),H39,DATE(VALUE(RIGHT(H39,4)),VALUE(MID(H39,3,2)),VALUE(LEFT(H39,2)))),TODAY(),"Y"),"")) | AB40: =IF(OR(D40="",E40=""),"",IFERROR(DATE(MID(E40,7,4),MID(E40,4,2),LEFT(E40,2))-DATE(MID(D40,7,4),MID(D40,4,2),LEFT(D40,2)),"")) -> 6 | AC40: =IF(E40="","Pending",IF(AB40<=5,"On time","Delayed")) -> Delayed
A41: ORD10040 | B41: C010 | C41: P203 | D41: 45787 | E41: 15/10/2025 | F41: Pooja Shah | G41: Female | H41: 18/06/1992 | I41: Mumbai | J41: West | K41: Home Appliances | L41: Microwave | M41: 20 | N41: 8500 | O41: 0 | P41: 170000 | Q41: 1 | R41: UPI | S41: Neha | T41: pooja.shah@company.com | U41: 9484632635 | V41: Cancelled | W41: =IF(OR(Q41<=2,V41="Cancelled"),"Blacklisted",IF(AND(P41>100000,Q41>=4,O41<=10%,V41="Completed"),"Platinum",IF(AND(P41>=50000,Q41>=3,V41="Completed"),"Gold",IF(AND(P41<50000,V41="Completed"),"Silver","")))) -> Blacklisted | X41: =PROPER(TRIM(F41)) -> Pooja Shah | Y41: =LEFT(F41,3)&MID(B41,2,3)&LEFT(I41,2) -> Poo010Mu | Z41: =IF(ISNUMBER(SEARCH("@",T41)),LOWER(TRIM(T41)),"invalid email") -> pooja.shah@company.com | AA41: =IF(H40="","",IFERROR(DATEDIF(IF(ISNUMBER(H40),H40,DATE(VALUE(RIGHT(H40,4)),VALUE(MID(H40,3,2)),VALUE(LEFT(H40,2)))),TODAY(),"Y"),"")) | AB41: =IF(OR(D41="",E41=""),"",IFERROR(DATE(MID(E41,7,4),MID(E41,4,2),LEFT(E41,2))-DATE(MID(D41,7,4),MID(D41,4,2),LEFT(D41,2)),"")) | AC41: =IF(E41="","Pending",IF(AB41<=5,"On time","Delayed")) -> Delayed
A42: ORD10041 | B42: C007 | C42: P301 | D42: 46297 | E42: 46358 | F42: Arjun Rao | G42: Male | H42: 34491 | I42: Bengaluru | J42: South | K42: Stationery | L42: Notebook | M42: 8 | N42: 60 | O42: 15 | P42: 408 | Q42: 5 | R42: UPI | S42: Rahul | T42: arjun.rao@company.com | U42: 9276319484 | V42: Pending | W42: =IF(OR(Q42<=2,V42="Cancelled"),"Blacklisted",IF(AND(P42>100000,Q42>=4,O42<=10%,V42="Completed"),"Platinum",IF(AND(P42>=50000,Q42>=3,V42="Completed"),"Gold",IF(AND(P42<50000,V42="Completed"),"Silver","")))) | X42: =PROPER(TRIM(F42)) -> Arjun Rao | Y42: =LEFT(F42,3)&MID(B42,2,3)&LEFT(I42,2) -> Arj007Be | Z42: =IF(ISNUMBER(SEARCH("@",T42)),LOWER(TRIM(T42)),"invalid email") -> arjun.rao@company.com | AA42: =IF(H41="","",IFERROR(DATEDIF(IF(ISNUMBER(H41),H41,DATE(VALUE(RIGHT(H41,4)),VALUE(MID(H41,3,2)),VALUE(LEFT(H41,2)))),TODAY(),"Y"),"")) | AB42: =IF(OR(D42="",E42=""),"",IFERROR(DATE(MID(E42,7,4),MID(E42,4,2),LEFT(E42,2))-DATE(MID(D42,7,4),MID(D42,4,2),LEFT(D42,2)),"")) | AC42: =IF(E42="","Pending",IF(AB42<=5,"On time","Delayed")) -> Delayed
A43: ORD10042 | B43: C010 | C43: P201 | D43: 45753 | E43: 16/06/2025 | F43: Pooja Shah | G43: Female | H43: 22/09/1988 | I43: Pune | J43: West | K43: Home Appliances | L43: Mixer | M43: 8 | N43: 3500 | O43: 5 | P43: 26600 | Q43: 1 | R43: Card | S43: Neha | T43: pooja.shah@company.com | U43: 9619034852 | V43: Pending | W43: =IF(OR(Q43<=2,V43="Cancelled"),"Blacklisted",IF(AND(P43>100000,Q43>=4,O43<=10%,V43="Completed"),"Platinum",IF(AND(P43>=50000,Q43>=3,V43="Completed"),"Gold",IF(AND(P43<50000,V43="Completed"),"Silver","")))) -> Blacklisted | X43: =PROPER(TRIM(F43)) -> Pooja Shah | Y43: =LEFT(F43,3)&MID(B43,2,3)&LEFT(I43,2) -> Poo010Pu | Z43: =IF(ISNUMBER(SEARCH("@",T43)),LOWER(TRIM(T43)),"invalid email") -> pooja.shah@company.com | AA43: =IF(H42="","",IFERROR(DATEDIF(IF(ISNUMBER(H42),H42,DATE(VALUE(RIGHT(H42,4)),VALUE(MID(H42,3,2)),VALUE(LEFT(H42,2)))),TODAY(),"Y"),"")) -> 32 | AB43: =IF(OR(D43="",E43=""),"",IFERROR(DATE(MID(E43,7,4),MID(E43,4,2),LEFT(E43,2))-DATE(MID(D43,7,4),MID(D43,4,2),LEFT(D43,2)),"")) | AC43: =IF(E43="","Pending",IF(AB43<=5,"On time","Delayed")) -> Delayed
A44: ORD10043 | B44: C009 | C44: P203 | D44: 46236 | E44: 14/02/2026 | F44: Mohit Verma | G44: Male | H44: 14/07/2001 | I44: Jaipur | J44: North | K44: Home Appliances | L44: Microwave | M44: 1 | N44: 8500 | O44: 0 | P44: 8500 | Q44: 2 | R44: Card | S44: Neha | T44: mohit.verma@company.com | U44: 9636416962 | V44: Pending | W44: =IF(OR(Q44<=2,V44="Cancelled"),"Blacklisted",IF(AND(P44>100000,Q44>=4,O44<=10%,V44="Completed"),"Platinum",IF(AND(P44>=50000,Q44>=3,V44="Completed"),"Gold",IF(AND(P44<50000,V44="Completed"),"Silver","")))) -> Blacklisted | X44: =PROPER(TRIM(F44)) -> Mohit Verma | Y44: =LEFT(F44,3)&MID(B44,2,3)&LEFT(I44,2) -> Moh009Ja | Z44: =IF(ISNUMBER(SEARCH("@",T44)),LOWER(TRIM(T44)),"invalid email") -> mohit.verma@company.com | AA44: =IF(H43="","",IFERROR(DATEDIF(IF(ISNUMBER(H43),H43,DATE(VALUE(RIGHT(H43,4)),VALUE(MID(H43,3,2)),VALUE(LEFT(H43,2)))),TODAY(),"Y"),"")) | AB44: =IF(OR(D44="",E44=""),"",IFERROR(DATE(MID(E44,7,4),MID(E44,4,2),LEFT(E44,2))-DATE(MID(D44,7,4),MID(D44,4,2),LEFT(D44,2)),"")) | AC44: =IF(E44="","Pending",IF(AB44<=5,"On time","Delayed")) -> Delayed
A45: ORD10044 | B45: C001 | C45: P303 | D45: 30/03/2025 | E45: 31/03/2025 | F45: amit Sharma | G45: Male | H45: 33489 | I45: Pune | J45: West | K45: Stationery | L45: Marker | M45: 8 | N45: 45 | O45: 15 | P45: 306 | Q45: 2 | R45: Card | S45: Aisha | T45: amit.sharma@company.com | U45: 9357133880 | V45: Completed | W45: =IF(OR(Q45<=2,V45="Cancelled"),"Blacklisted",IF(AND(P45>100000,Q45>=4,O45<=10%,V45="Completed"),"Platinum",IF(AND(P45>=50000,Q45>=3,V45="Completed"),"Gold",IF(AND(P45<50000,V45="Completed"),"Silver","")))) -> Blacklisted | X45: =PROPER(TRIM(F45)) -> Amit Sharma | Y45: =LEFT(F45,3)&MID(B45,2,3)&LEFT(I45,2) -> ami001Pu | Z45: =IF(ISNUMBER(SEARCH("@",T45)),LOWER(TRIM(T45)),"invalid email") -> amit.sharma@company.com | AA45: =IF(H44="","",IFERROR(DATEDIF(IF(ISNUMBER(H44),H44,DATE(VALUE(RIGHT(H44,4)),VALUE(MID(H44,3,2)),VALUE(LEFT(H44,2)))),TODAY(),"Y"),"")) | AB45: =IF(OR(D45="",E45=""),"",IFERROR(DATE(MID(E45,7,4),MID(E45,4,2),LEFT(E45,2))-DATE(MID(D45,7,4),MID(D45,4,2),LEFT(D45,2)),"")) -> 1 | AC45: =IF(E45="","Pending",IF(AB45<=5,"On time","Delayed")) -> On time
A46: ORD10045 | B46: C006 | C46: P202 | D46: 25/04/2025 | E46: 28/04/2025 | F46: Sneha Joshi | G46: Female | H46: 21/10/1988 | I46: Pune | J46: West | K46: Home Appliances | L46: Iron | M46: 16 | N46: 2200 | O46: 5 | P46: 33440 | Q46: 5 | R46: Card | S46: Aisha | T46: sneha.joshi@company.com | U46: 9575210324 | V46: Cancelled | W46: =IF(OR(Q46<=2,V46="Cancelled"),"Blacklisted",IF(AND(P46>100000,Q46>=4,O46<=10%,V46="Completed"),"Platinum",IF(AND(P46>=50000,Q46>=3,V46="Completed"),"Gold",IF(AND(P46<50000,V46="Completed"),"Silver","")))) -> Blacklisted | X46: =PROPER(TRIM(F46)) -> Sneha Joshi | Y46: =LEFT(F46,3)&MID(B46,2,3)&LEFT(I46,2) -> Sne006Pu | Z46: =IF(ISNUMBER(SEARCH("@",T46)),LOWER(TRIM(T46)),"invalid email") -> sneha.joshi@company.com | AA46: =IF(H45="","",IFERROR(DATEDIF(IF(ISNUMBER(H45),H45,DATE(VALUE(RIGHT(H45,4)),VALUE(MID(H45,3,2)),VALUE(LEFT(H45,2)))),TODAY(),"Y"),"")) -> 35 | AB46: =IF(OR(D46="",E46=""),"",IFERROR(DATE(MID(E46,7,4),MID(E46,4,2),LEFT(E46,2))-DATE(MID(D46,7,4),MID(D46,4,2),LEFT(D46,2)),"")) -> 3 | AC46: =IF(E46="","Pending",IF(AB46<=5,"On time","Delayed")) -> On time
A47: ORD10046 | B47: C009 | C47: P201 | D47: 13/10/2025 | E47: 23/10/2025 | F47: Mohit Verma | G47: Male | H47: 19/11/2002 | I47: Bengaluru | J47: South | K47: Home Appliances | L47: Mixer | M47: 19 | N47: 3500 | O47: 20 | P47: 53200 | Q47: 3 | R47: Cash | S47: Karan | T47: mohit.verma@company.com | U47: 9276080204 | V47: Cancelled | W47: =IF(OR(Q47<=2,V47="Cancelled"),"Blacklisted",IF(AND(P47>100000,Q47>=4,O47<=10%,V47="Completed"),"Platinum",IF(AND(P47>=50000,Q47>=3,V47="Completed"),"Gold",IF(AND(P47<50000,V47="Completed"),"Silver","")))) -> Blacklisted | X47: =PROPER(TRIM(F47)) -> Mohit Verma | Y47: =LEFT(F47,3)&MID(B47,2,3)&LEFT(I47,2) -> Moh009Be | Z47: =IF(ISNUMBER(SEARCH("@",T47)),LOWER(TRIM(T47)),"invalid email") -> mohit.verma@company.com | AA47: =IF(H46="","",IFERROR(DATEDIF(IF(ISNUMBER(H46),H46,DATE(VALUE(RIGHT(H46,4)),VALUE(MID(H46,3,2)),VALUE(LEFT(H46,2)))),TODAY(),"Y"),"")) | AB47: =IF(OR(D47="",E47=""),"",IFERROR(DATE(MID(E47,7,4),MID(E47,4,2),LEFT(E47,2))-DATE(MID(D47,7,4),MID(D47,4,2),LEFT(D47,2)),"")) -> 10 | AC47: =IF(E47="","Pending",IF(AB47<=5,"On time","Delayed")) -> Delayed
A48: ORD10047 | B48: C006 | C48: P102 | D48: 45971 | E48: 14/10/2025 | F48: Sneha Joshi | G48: Female | H48: 36684 | I48: Pune | J48: West | K48: Electronics | L48: Mouse | M48: 15 | N48: 700 | O48: 15 | P48: 8925 | Q48: 4 | R48: UPI | S48: Neha | T48: sneha.joshicompany.com | U48: 9856624471 | V48: Completed | W48: =IF(OR(Q48<=2,V48="Cancelled"),"Blacklisted",IF(AND(P48>100000,Q48>=4,O48<=10%,V48="Completed"),"Platinum",IF(AND(P48>=50000,Q48>=3,V48="Completed"),"Gold",IF(AND(P48<50000,V48="Completed"),"Silver","")))) -> Silver | X48: =PROPER(TRIM(F48)) -> Sneha Joshi | Y48: =LEFT(F48,3)&MID(B48,2,3)&LEFT(I48,2) -> Sne006Pu | Z48: =IF(ISNUMBER(SEARCH("@",T48)),LOWER(TRIM(T48)),"invalid email") -> invalid email | AA48: =IF(H47="","",IFERROR(DATEDIF(IF(ISNUMBER(H47),H47,DATE(VALUE(RIGHT(H47,4)),VALUE(MID(H47,3,2)),VALUE(LEFT(H47,2)))),TODAY(),"Y"),"")) | AB48: =IF(OR(D48="",E48=""),"",IFERROR(DATE(MID(E48,7,4),MID(E48,4,2),LEFT(E48,2))-DATE(MID(D48,7,4),MID(D48,4,2),LEFT(D48,2)),"")) | AC48: =IF(E48="","Pending",IF(AB48<=5,"On time","Delayed")) -> Delayed
A49: ORD10048 | B49: C006 | C49: P102 | D49: 27/11/2025 | E49: 45728 | F49: Sneha Joshi | G49: Female | H49: 26/11/1998 | I49: Jaipur | J49: North | K49: Electronics | L49: Mouse | M49: 19 | N49: 700 | O49: 20 | P49: 10640 | Q49: 1 | R49: Cash | S49: Neha | T49: sneha.joshi@company.com | U49: 9238141322 | V49: Completed | W49: =IF(OR(Q49<=2,V49="Cancelled"),"Blacklisted",IF(AND(P49>100000,Q49>=4,O49<=10%,V49="Completed"),"Platinum",IF(AND(P49>=50000,Q49>=3,V49="Completed"),"Gold",IF(AND(P49<50000,V49="Completed"),"Silver","")))) -> Blacklisted | X49: =PROPER(TRIM(F49)) -> Sneha Joshi | Y49: =LEFT(F49,3)&MID(B49,2,3)&LEFT(I49,2) -> Sne006Ja | Z49: =IF(ISNUMBER(SEARCH("@",T49)),LOWER(TRIM(T49)),"invalid email") -> sneha.joshi@company.com | AA49: =IF(H48="","",IFERROR(DATEDIF(IF(ISNUMBER(H48),H48,DATE(VALUE(RIGHT(H48,4)),VALUE(MID(H48,3,2)),VALUE(LEFT(H48,2)))),TODAY(),"Y"),"")) -> 26 | AB49: =IF(OR(D49="",E49=""),"",IFERROR(DATE(MID(E49,7,4),MID(E49,4,2),LEFT(E49,2))-DATE(MID(D49,7,4),MID(D49,4,2),LEFT(D49,2)),"")) | AC49: =IF(E49="","Pending",IF(AB49<=5,"On time","Delayed")) -> Delayed
A50: ORD10049 | B50: C009 | C50: P104 | D50: 19/04/2026 | F50: Mohit Verma | G50: Male | H50: 35130 | I50: Delhi | J50: North | K50: Electronics | L50: Monitor | M50: 19 | N50: 12000 | O50: 0 | P50: 228000 | Q50: 1 | R50: NetBanking | S50: Aisha | T50: mohit.verma@company.com | U50: 9890380030 | V50: Completed | W50: =IF(OR(Q50<=2,V50="Cancelled"),"Blacklisted",IF(AND(P50>100000,Q50>=4,O50<=10%,V50="Completed"),"Platinum",IF(AND(P50>=50000,Q50>=3,V50="Completed"),"Gold",IF(AND(P50<50000,V50="Completed"),"Silver","")))) -> Blacklisted | X50: =PROPER(TRIM(F50)) -> Mohit Verma | Y50: =LEFT(F50,3)&MID(B50,2,3)&LEFT(I50,2) -> Moh009De | Z50: =IF(ISNUMBER(SEARCH("@",T50)),LOWER(TRIM(T50)),"invalid email") -> mohit.verma@company.com | AA50: =IF(H49="","",IFERROR(DATEDIF(IF(ISNUMBER(H49),H49,DATE(VALUE(RIGHT(H49,4)),VALUE(MID(H49,3,2)),VALUE(LEFT(H49,2)))),TODAY(),"Y"),"")) | AB50: =IF(OR(D50="",E50=""),"",IFERROR(DATE(MID(E50,7,4),MID(E50,4,2),LEFT(E50,2))-DATE(MID(D50,7,4),MID(D50,4,2),LEFT(D50,2)),"")) | AC50: =IF(E50="","Pending",IF(AB50<=5,"On time","Delayed")) -> Pending
A51: ORD10050 | B51: C004 | C51: P103 | D51: 19/04/2026 | E51: 21/04/2026 | F51: Anita Gupta | G51: Female | H51: 15/03/1987 | I51: Pune | J51: West | K51: Electronics | L51: Keyboard | M51: 6 | N51: 1200 | O51: 5 | P51: 6840 | Q51: 2 | R51: Cash | S51: Ritika | T51: anita.gupta@company.com | U51: 9495893170 | V51: Pending | W51: =IF(OR(Q51<=2,V51="Cancelled"),"Blacklisted",IF(AND(P51>100000,Q51>=4,O51<=10%,V51="Completed"),"Platinum",IF(AND(P51>=50000,Q51>=3,V51="Completed"),"Gold",IF(AND(P51<50000,V51="Completed"),"Silver","")))) -> Blacklisted | X51: =PROPER(TRIM(F51)) -> Anita Gupta | Y51: =LEFT(F51,3)&MID(B51,2,3)&LEFT(I51,2) -> Ani004Pu | Z51: =IF(ISNUMBER(SEARCH("@",T51)),LOWER(TRIM(T51)),"invalid email") -> anita.gupta@company.com | AA51: =IF(H50="","",IFERROR(DATEDIF(IF(ISNUMBER(H50),H50,DATE(VALUE(RIGHT(H50,4)),VALUE(MID(H50,3,2)),VALUE(LEFT(H50,2)))),TODAY(),"Y"),"")) -> 30 | AB51: =IF(OR(D51="",E51=""),"",IFERROR(DATE(MID(E51,7,4),MID(E51,4,2),LEFT(E51,2))-DATE(MID(D51,7,4),MID(D51,4,2),LEFT(D51,2)),"")) -> 2 | AC51: =IF(E51="","Pending",IF(AB51<=5,"On time","Delayed")) -> On time
A52: ORD10051 | B52: C010 | C52: P202 | D52: 28/03/2025 | E52: 45842 | F52: POoja Shah | G52: Female | H52: 20/02/1979 | I52: Bengaluru | J52: South | K52: Home Appliances | L52: Iron | M52: 7 | N52: 2200 | O52: 15 | P52: 13090 | Q52: 1 | R52: UPI | S52: Aisha | T52: pooja.shah@company.com | U52: 9485166307 | V52: Completed | W52: =IF(OR(Q52<=2,V52="Cancelled"),"Blacklisted",IF(AND(P52>100000,Q52>=4,O52<=10%,V52="Completed"),"Platinum",IF(AND(P52>=50000,Q52>=3,V52="Completed"),"Gold",IF(AND(P52<50000,V52="Completed"),"Silver","")))) -> Blacklisted | X52: =PROPER(TRIM(F52)) -> Pooja Shah | Y52: =LEFT(F52,3)&MID(B52,2,3)&LEFT(I52,2) -> POo010Be | Z52: =IF(ISNUMBER(SEARCH("@",T52)),LOWER(TRIM(T52)),"invalid email") -> pooja.shah@company.com | AA52: =IF(H51="","",IFERROR(DATEDIF(IF(ISNUMBER(H51),H51,DATE(VALUE(RIGHT(H51,4)),VALUE(MID(H51,3,2)),VALUE(LEFT(H51,2)))),TODAY(),"Y"),"")) | AB52: =IF(OR(D52="",E52=""),"",IFERROR(DATE(MID(E52,7,4),MID(E52,4,2),LEFT(E52,2))-DATE(MID(D52,7,4),MID(D52,4,2),LEFT(D52,2)),"")) | AC52: =IF(E52="","Pending",IF(AB52<=5,"On time","Delayed")) -> Delayed
A53: ORD10052 | B53: C002 | C53: P301 | D53: 25/08/2025 | E53: 28/08/2025 | F53: Priya Patel | G53: Female | H53: 36777 | I53: Jaipur | J53: North | K53: Stationery | L53: Notebook | M53: 8 | N53: 60 | O53: 10 | P53: 432 | Q53: 5 | R53: Card | S53: Aisha | T53: priya.patel@company.com | U53: 9924709648 | V53: Cancelled | W53: =IF(OR(Q53<=2,V53="Cancelled"),"Blacklisted",IF(AND(P53>100000,Q53>=4,O53<=10%,V53="Completed"),"Platinum",IF(AND(P53>=50000,Q53>=3,V53="Completed"),"Gold",IF(AND(P53<50000,V53="Completed"),"Silver","")))) -> Blacklisted | X53: =PROPER(TRIM(F53)) -> Priya Patel | Y53: =LEFT(F53,3)&MID(B53,2,3)&LEFT(I53,2) -> Pri002Ja | Z53: =IF(ISNUMBER(SEARCH("@",T53)),LOWER(TRIM(T53)),"invalid email") -> priya.patel@company.com | AA53: =IF(H52="","",IFERROR(DATEDIF(IF(ISNUMBER(H52),H52,DATE(VALUE(RIGHT(H52,4)),VALUE(MID(H52,3,2)),VALUE(LEFT(H52,2)))),TODAY(),"Y"),"")) | AB53: =IF(OR(D53="",E53=""),"",IFERROR(DATE(MID(E53,7,4),MID(E53,4,2),LEFT(E53,2))-DATE(MID(D53,7,4),MID(D53,4,2),LEFT(D53,2)),"")) -> 3 | AC53: =IF(E53="","Pending",IF(AB53<=5,"On time","Delayed")) -> On time
A54: ORD10053 | B54: C005 | C54: P101 | D54: 19/08/2025 | E54: 23/08/2025 | F54: Vikas Mehta | G54: Male | H54: 17/01/1976 | I54: Kolkata | J54: East | K54: Electronics | L54: Laptop | M54: 12 | N54: 55000 | O54: 5 | P54: 627000 | Q54: 2 | R54: UPI | S54: Rahul | T54: vikas.mehta@company.com | U54: 9350554626 | V54: Pending | W54: =IF(OR(Q54<=2,V54="Cancelled"),"Blacklisted",IF(AND(P54>100000,Q54>=4,O54<=10%,V54="Completed"),"Platinum",IF(AND(P54>=50000,Q54>=3,V54="Completed"),"Gold",IF(AND(P54<50000,V54="Completed"),"Silver","")))) -> Blacklisted | X54: =PROPER(TRIM(F54)) -> Vikas Mehta | Y54: =LEFT(F54,3)&MID(B54,2,3)&LEFT(I54,2) -> Vik005Ko | Z54: =IF(ISNUMBER(SEARCH("@",T54)),LOWER(TRIM(T54)),"invalid email") -> vikas.mehta@company.com | AA54: =IF(H53="","",IFERROR(DATEDIF(IF(ISNUMBER(H53),H53,DATE(VALUE(RIGHT(H53,4)),VALUE(MID(H53,3,2)),VALUE(LEFT(H53,2)))),TODAY(),"Y"),"")) -> 26 | AB54: =IF(OR(D54="",E54=""),"",IFERROR(DATE(MID(E54,7,4),MID(E54,4,2),LEFT(E54,2))-DATE(MID(D54,7,4),MID(D54,4,2),LEFT(D54,2)),"")) -> 4 | AC54: =IF(E54="","Pending",IF(AB54<=5,"On time","Delayed")) -> On time
A55: ORD10054 | B55: C008 | C55: P102 | D55: 27/07/2025 | E55: 45785 | F55: Kavya Nair | G55: Female | H55: 27488 | I55: Jaipur | J55: North | K55: Electronics | L55: Mouse | M55: 3 | N55: 700 | O55: 0 | P55: 2100 | Q55: 3 | R55: Card | S55: Karan | T55: kavya.nair@company.com | U55: 9743295580 | V55: Cancelled | W55: =IF(OR(Q55<=2,V55="Cancelled"),"Blacklisted",IF(AND(P55>100000,Q55>=4,O55<=10%,V55="Completed"),"Platinum",IF(AND(P55>=50000,Q55>=3,V55="Completed"),"Gold",IF(AND(P55<50000,V55="Completed"),"Silver","")))) -> Blacklisted | X55: =PROPER(TRIM(F55)) -> Kavya Nair | Y55: =LEFT(F55,3)&MID(B55,2,3)&LEFT(I55,2) -> Kav008Ja | Z55: =IF(ISNUMBER(SEARCH("@",T55)),LOWER(TRIM(T55)),"invalid email") -> kavya.nair@company.com | AA55: =IF(H54="","",IFERROR(DATEDIF(IF(ISNUMBER(H54),H54,DATE(VALUE(RIGHT(H54,4)),VALUE(MID(H54,3,2)),VALUE(LEFT(H54,2)))),TODAY(),"Y"),"")) | AB55: =IF(OR(D55="",E55=""),"",IFERROR(DATE(MID(E55,7,4),MID(E55,4,2),LEFT(E55,2))-DATE(MID(D55,7,4),MID(D55,4,2),LEFT(D55,2)),"")) | AC55: =IF(E55="","Pending",IF(AB55<=5,"On time","Delayed")) -> Delayed
A56: ORD10055 | B56: C003 | C56: P301 | D56: 21/02/2025 | E56: 26/02/2025 | F56: RoHit Singh | G56: Male | H56: 28076 | I56: Ahmedabad | J56: West | K56: Stationery | L56: Notebook | M56: 19 | N56: 60 | O56: 15 | P56: 969 | Q56: 4 | R56: Card | S56: Rahul | T56: rohit.singh@company.com | U56: 9822926495 | V56: Cancelled | W56: =IF(OR(Q56<=2,V56="Cancelled"),"Blacklisted",IF(AND(P56>100000,Q56>=4,O56<=10%,V56="Completed"),"Platinum",IF(AND(P56>=50000,Q56>=3,V56="Completed"),"Gold",IF(AND(P56<50000,V56="Completed"),"Silver","")))) -> Blacklisted | X56: =PROPER(TRIM(F56)) -> Rohit Singh | Y56: =LEFT(F56,3)&MID(B56,2,3)&LEFT(I56,2) -> RoH003Ah | Z56: =IF(ISNUMBER(SEARCH("@",T56)),LOWER(TRIM(T56)),"invalid email") -> rohit.singh@company.com | AA56: =IF(H55="","",IFERROR(DATEDIF(IF(ISNUMBER(H55),H55,DATE(VALUE(RIGHT(H55,4)),VALUE(MID(H55,3,2)),VALUE(LEFT(H55,2)))),TODAY(),"Y"),"")) -> 51 | AB56: =IF(OR(D56="",E56=""),"",IFERROR(DATE(MID(E56,7,4),MID(E56,4,2),LEFT(E56,2))-DATE(MID(D56,7,4),MID(D56,4,2),LEFT(D56,2)),"")) -> 5 | AC56: =IF(E56="","Pending",IF(AB56<=5,"On time","Delayed")) -> On time
A57: ORD10056 | B57: C001 | C57: P301 | D57: 45938 | E57: 45969 | F57: Amit Sharma | G57: Male | H57: 28926 | I57: Jaipur | J57: North | K57: Stationery | L57: Notebook | M57: 9 | N57: 60 | O57: 20 | P57: 432 | Q57: 1 | R57: NetBanking | S57: Neha | T57: amit.sharma@company.com | U57: 9518298190 | V57: Pending | W57: =IF(OR(Q57<=2,V57="Cancelled"),"Blacklisted",IF(AND(P57>100000,Q57>=4,O57<=10%,V57="Completed"),"Platinum",IF(AND(P57>=50000,Q57>=3,V57="Completed"),"Gold",IF(AND(P57<50000,V57="Completed"),"Silver","")))) -> Blacklisted | X57: =PROPER(TRIM(F57)) -> Amit Sharma | Y57: =LEFT(F57,3)&MID(B57,2,3)&LEFT(I57,2) -> Ami001Ja | Z57: =IF(ISNUMBER(SEARCH("@",T57)),LOWER(TRIM(T57)),"invalid email") -> amit.sharma@company.com | AA57: =IF(H56="","",IFERROR(DATEDIF(IF(ISNUMBER(H56),H56,DATE(VALUE(RIGHT(H56,4)),VALUE(MID(H56,3,2)),VALUE(LEFT(H56,2)))),TODAY(),"Y"),"")) -> 49 | AB57: =IF(OR(D57="",E57=""),"",IFERROR(DATE(MID(E57,7,4),MID(E57,4,2),LEFT(E57,2))-DATE(MID(D57,7,4),MID(D57,4,2),LEFT(D57,2)),"")) | AC57: =IF(E57="","Pending",IF(AB57<=5,"On time","Delayed")) -> Delayed
A58: ORD10057 | B58: C001 | C58: P102 | D58: 24/03/2026 | E58: 30/03/2026 | F58: Amit Sharma | G58: Male | H58: 27/12/1978 | I58: Bengaluru | J58: South | K58: Electronics | L58: Mouse | M58: 6 | N58: 700 | O58: 0 | P58: 4200 | Q58: 4 | R58: UPI | S58: Rahul | T58: amit.sharmcompany.com | U58: 9366223547 | V58: Cancelled | W58: =IF(OR(Q58<=2,V58="Cancelled"),"Blacklisted",IF(AND(P58>100000,Q58>=4,O58<=10%,V58="Completed"),"Platinum",IF(AND(P58>=50000,Q58>=3,V58="Completed"),"Gold",IF(AND(P58<50000,V58="Completed"),"Silver","")))) -> Blacklisted | X58: =PROPER(TRIM(F58)) -> Amit Sharma | Y58: =LEFT(F58,3)&MID(B58,2,3)&LEFT(I58,2) -> Ami001Be | Z58: =IF(ISNUMBER(SEARCH("@",T58)),LOWER(TRIM(T58)),"invalid email") -> invalid email | AA58: =IF(H57="","",IFERROR(DATEDIF(IF(ISNUMBER(H57),H57,DATE(VALUE(RIGHT(H57,4)),VALUE(MID(H57,3,2)),VALUE(LEFT(H57,2)))),TODAY(),"Y"),"")) -> 47 | AB58: =IF(OR(D58="",E58=""),"",IFERROR(DATE(MID(E58,7,4),MID(E58,4,2),LEFT(E58,2))-DATE(MID(D58,7,4),MID(D58,4,2),LEFT(D58,2)),"")) -> 6 | AC58: =IF(E58="","Pending",IF(AB58<=5,"On time","Delayed")) -> Delayed
A59: ORD10058 | B59: C003 | C59: P303 | D59: 13/03/2026 | E59: 19/03/2026 | F59: Rohit Singh | G59: Male | H59: 15/04/1975 | I59: Delhi | J59: North | K59: Stationery | L59: Marker | M59: 18 | N59: 45 | O59: 5 | P59: 769.5 | Q59: 1 | R59: Card | S59: Aisha | T59: rohit.singh@company.com | U59: 9701988524 | V59: Pending | W59: =IF(OR(Q59<=2,V59="Cancelled"),"Blacklisted",IF(AND(P59>100000,Q59>=4,O59<=10%,V59="Completed"),"Platinum",IF(AND(P59>=50000,Q59>=3,V59="Completed"),"Gold",IF(AND(P59<50000,V59="Completed"),"Silver","")))) -> Blacklisted | X59: =PROPER(TRIM(F59)) -> Rohit Singh | Y59: =LEFT(F59,3)&MID(B59,2,3)&LEFT(I59,2) -> Roh003De | Z59: =IF(ISNUMBER(SEARCH("@",T59)),LOWER(TRIM(T59)),"invalid email") -> rohit.singh@company.com | AA59: =IF(H58="","",IFERROR(DATEDIF(IF(ISNUMBER(H58),H58,DATE(VALUE(RIGHT(H58,4)),VALUE(MID(H58,3,2)),VALUE(LEFT(H58,2)))),TODAY(),"Y"),"")) | AB59: =IF(OR(D59="",E59=""),"",IFERROR(DATE(MID(E59,7,4),MID(E59,4,2),LEFT(E59,2))-DATE(MID(D59,7,4),MID(D59,4,2),LEFT(D59,2)),"")) -> 6 | AC59: =IF(E59="","Pending",IF(AB59<=5,"On time","Delayed")) -> Delayed
A60: ORD10059 | B60: C007 | C60: P302 | D60: 15/06/2025 | E60: 26/06/2025 | F60: Arjun Rao | G60: Male | H60: 19/12/1988 | I60: Jaipur | J60: North | K60: Stationery | L60: Pen | M60: 8 | N60: 20 | O60: 5 | P60: 152 | Q60: 1 | R60: Card | S60: Ritika | T60: arjun.rao@company.com | U60: 9836327649 | V60: completed | W60: =IF(OR(Q60<=2,V60="Cancelled"),"Blacklisted",IF(AND(P60>100000,Q60>=4,O60<=10%,V60="Completed"),"Platinum",IF(AND(P60>=50000,Q60>=3,V60="Completed"),"Gold",IF(AND(P60<50000,V60="Completed"),"Silver","")))) -> Blacklisted | X60: =PROPER(TRIM(F60)) -> Arjun Rao | Y60: =LEFT(F60,3)&MID(B60,2,3)&LEFT(I60,2) -> Arj007Ja | Z60: =IF(ISNUMBER(SEARCH("@",T60)),LOWER(TRIM(T60)),"invalid email") -> arjun.rao@company.com | AA60: =IF(H59="","",IFERROR(DATEDIF(IF(ISNUMBER(H59),H59,DATE(VALUE(RIGHT(H59,4)),VALUE(MID(H59,3,2)),VALUE(LEFT(H59,2)))),TODAY(),"Y"),"")) | AB60: =IF(OR(D60="",E60=""),"",IFERROR(DATE(MID(E60,7,4),MID(E60,4,2),LEFT(E60,2))-DATE(MID(D60,7,4),MID(D60,4,2),LEFT(D60,2)),"")) -> 11 | AC60: =IF(E60="","Pending",IF(AB60<=5,"On time","Delayed")) -> Delayed
A61: ORD10060 | B61: C005 | C61: P102 | D61: 45780 | E61: 45811 | F61: Vikas Mehta | G61: Male | H61: 29039 | I61: Jaipur | J61: North | K61: Electronics | L61: Mouse | M61: 8 | N61: 700 | O61: 10 | P61: 5040 | Q61: 1 | R61: NetBanking | S61: Aisha | T61: Vikas.mehta@company.com | U61: 9261800516 | V61: Cancelled | W61: =IF(OR(Q61<=2,V61="Cancelled"),"Blacklisted",IF(AND(P61>100000,Q61>=4,O61<=10%,V61="Completed"),"Platinum",IF(AND(P61>=50000,Q61>=3,V61="Completed"),"Gold",IF(AND(P61<50000,V61="Completed"),"Silver","")))) -> Blacklisted | X61: =PROPER(TRIM(F61)) -> Vikas Mehta | Y61: =LEFT(F61,3)&MID(B61,2,3)&LEFT(I61,2) -> Vik005Ja | Z61: =IF(ISNUMBER(SEARCH("@",T61)),LOWER(TRIM(T61)),"invalid email") -> vikas.mehta@company.com | AA61: =IF(H60="","",IFERROR(DATEDIF(IF(ISNUMBER(H60),H60,DATE(VALUE(RIGHT(H60,4)),VALUE(MID(H60,3,2)),VALUE(LEFT(H60,2)))),TODAY(),"Y"),"")) | AB61: =IF(OR(D61="",E61=""),"",IFERROR(DATE(MID(E61,7,4),MID(E61,4,2),LEFT(E61,2))-DATE(MID(D61,7,4),MID(D61,4,2),LEFT(D61,2)),"")) | AC61: =IF(E61="","Pending",IF(AB61<=5,"On time","Delayed")) -> Delayed
A62: ORD10061 | B62: C008 | C62: P302 | D62: 46269 | E62: 19/04/2026 | F62: Kavya Nair | G62: Female | H62: 17/12/2003 | I62: Delhi | J62: North | K62: Stationery | L62: Pen | M62: 7 | N62: 20 | O62: 15 | P62: 119 | Q62: 5 | R62: Card | S62: Rahul | T62: kavya.nair@company.com | U62: 9950802015 | V62: Completed | W62: =IF(OR(Q62<=2,V62="Cancelled"),"Blacklisted",IF(AND(P62>100000,Q62>=4,O62<=10%,V62="Completed"),"Platinum",IF(AND(P62>=50000,Q62>=3,V62="Completed"),"Gold",IF(AND(P62<50000,V62="Completed"),"Silver","")))) -> Silver | X62: =PROPER(TRIM(F62)) -> Kavya Nair | Y62: =LEFT(F62,3)&MID(B62,2,3)&LEFT(I62,2) -> Kav008De | Z62: =IF(ISNUMBER(SEARCH("@",T62)),LOWER(TRIM(T62)),"invalid email") -> kavya.nair@company.com | AA62: =IF(H61="","",IFERROR(DATEDIF(IF(ISNUMBER(H61),H61,DATE(VALUE(RIGHT(H61,4)),VALUE(MID(H61,3,2)),VALUE(LEFT(H61,2)))),TODAY(),"Y"),"")) -> 47 | AB62: =IF(OR(D62="",E62=""),"",IFERROR(DATE(MID(E62,7,4),MID(E62,4,2),LEFT(E62,2))-DATE(MID(D62,7,4),MID(D62,4,2),LEFT(D62,2)),"")) | AC62: =IF(E62="","Pending",IF(AB62<=5,"On time","Delayed")) -> Delayed
A63: ORD10062 | B63: C002 | C63: P302 | D63: 16/08/2025 | E63: 25/08/2025 | F63: Priya Patel | G63: Female | H63: 30806 | I63: Pune | J63: West | K63: Stationery | L63: Pen | M63: 16 | N63: 20 | O63: 0 | P63: 320 | Q63: 5 | R63: NetBanking | S63: Aisha | T63: priya.patel@company.com | U63: 9595183767 | V63: Pending | W63: =IF(OR(Q63<=2,V63="Cancelled"),"Blacklisted",IF(AND(P63>100000,Q63>=4,O63<=10%,V63="Completed"),"Platinum",IF(AND(P63>=50000,Q63>=3,V63="Completed"),"Gold",IF(AND(P63<50000,V63="Completed"),"Silver","")))) | X63: =PROPER(TRIM(F63)) -> Priya Patel | Y63: =LEFT(F63,3)&MID(B63,2,3)&LEFT(I63,2) -> Pri002Pu | Z63: =IF(ISNUMBER(SEARCH("@",T63)),LOWER(TRIM(T63)),"invalid email") -> priya.patel@company.com | AA63: =IF(H62="","",IFERROR(DATEDIF(IF(ISNUMBER(H62),H62,DATE(VALUE(RIGHT(H62,4)),VALUE(MID(H62,3,2)),VALUE(LEFT(H62,2)))),TODAY(),"Y"),"")) | AB63: =IF(OR(D63="",E63=""),"",IFERROR(DATE(MID(E63,7,4),MID(E63,4,2),LEFT(E63,2))-DATE(MID(D63,7,4),MID(D63,4,2),LEFT(D63,2)),"")) -> 9 | AC63: =IF(E63="","Pending",IF(AB63<=5,"On time","Delayed")) -> Delayed
A64: ORD10063 | B64: C010 | C64: P303 | D64: 13/05/2026 | E64: 20/05/2026 | F64: Pooja Shah | G64: Female | H64: 13/04/1996 | I64: Mumbai | J64: West | K64: Stationery | L64: Marker | M64: 15 | N64: 45 | O64: 0 | P64: 675 | Q64: 4 | R64: Cash | S64: Aisha | T64: pooja.shah@company.com | U64: 9560201307 | V64: Cancelled | W64: =IF(OR(Q64<=2,V64="Cancelled"),"Blacklisted",IF(AND(P64>100000,Q64>=4,O64<=10%,V64="Completed"),"Platinum",IF(AND(P64>=50000,Q64>=3,V64="Completed"),"Gold",IF(AND(P64<50000,V64="Completed"),"Silver","")))) -> Blacklisted | X64: =PROPER(TRIM(F64)) -> Pooja Shah | Y64: =LEFT(F64,3)&MID(B64,2,3)&LEFT(I64,2) -> Poo010Mu | Z64: =IF(ISNUMBER(SEARCH("@",T64)),LOWER(TRIM(T64)),"invalid email") -> pooja.shah@company.com | AA64: =IF(H63="","",IFERROR(DATEDIF(IF(ISNUMBER(H63),H63,DATE(VALUE(RIGHT(H63,4)),VALUE(MID(H63,3,2)),VALUE(LEFT(H63,2)))),TODAY(),"Y"),"")) -> 42 | AB64: =IF(OR(D64="",E64=""),"",IFERROR(DATE(MID(E64,7,4),MID(E64,4,2),LEFT(E64,2))-DATE(MID(D64,7,4),MID(D64,4,2),LEFT(D64,2)),"")) -> 7 | AC64: =IF(E64="","Pending",IF(AB64<=5,"On time","Delayed")) -> Delayed
A65: ORD10064 | B65: C006 | C65: P102 | D65: 45660 | E65: 45780 | F65: Sneha Joshi | G65: Female | H65: 37842 | I65: Ahmedabad | J65: West | K65: Electronics | L65: Mouse | M65: 15 | N65: 700 | O65: 10 | P65: 9450 | Q65: 3 | R65: NetBanking | S65: Karan | T65: sneha.joshi@company.com | U65: 9826484650 | V65: Completed | W65: =IF(OR(Q65<=2,V65="Cancelled"),"Blacklisted",IF(AND(P65>100000,Q65>=4,O65<=10%,V65="Completed"),"Platinum",IF(AND(P65>=50000,Q65>=3,V65="Completed"),"Gold",IF(AND(P65<50000,V65="Completed"),"Silver","")))) -> Silver | X65: =PROPER(TRIM(F65)) -> Sneha Joshi | Y65: =LEFT(F65,3)&MID(B65,2,3)&LEFT(I65,2) -> Sne006Ah | Z65: =IF(ISNUMBER(SEARCH("@",T65)),LOWER(TRIM(T65)),"invalid email") -> sneha.joshi@company.com | AA65: =IF(H64="","",IFERROR(DATEDIF(IF(ISNUMBER(H64),H64,DATE(VALUE(RIGHT(H64,4)),VALUE(MID(H64,3,2)),VALUE(LEFT(H64,2)))),TODAY(),"Y"),"")) | AB65: =IF(OR(D65="",E65=""),"",IFERROR(DATE(MID(E65,7,4),MID(E65,4,2),LEFT(E65,2))-DATE(MID(D65,7,4),MID(D65,4,2),LEFT(D65,2)),"")) | AC65: =IF(E65="","Pending",IF(AB65<=5,"On time","Delayed")) -> Delayed
A66: ORD10065 | B66: C010 | C66: P303 | D66: 45902 | E66: 45993 | F66: Pooja Shah | G66: Female | H66: 24/09/1992 | I66: Kolkata | J66: East | K66: Stationery | L66: Marker | M66: 3 | N66: 45 | O66: 15 | P66: 114.75 | Q66: 2 | R66: UPI | S66: Neha | T66: pooja.shah@company.com | U66: 9219978007 | V66: Pending | W66: =IF(OR(Q66<=2,V66="Cancelled"),"Blacklisted",IF(AND(P66>100000,Q66>=4,O66<=10%,V66="Completed"),"Platinum",IF(AND(P66>=50000,Q66>=3,V66="Completed"),"Gold",IF(AND(P66<50000,V66="Completed"),"Silver","")))) -> Blacklisted | X66: =PROPER(TRIM(F66)) -> Pooja Shah | Y66: =LEFT(F66,3)&MID(B66,2,3)&LEFT(I66,2) -> Poo010Ko | Z66: =IF(ISNUMBER(SEARCH("@",T66)),LOWER(TRIM(T66)),"invalid email") -> pooja.shah@company.com | AA66: =IF(H65="","",IFERROR(DATEDIF(IF(ISNUMBER(H65),H65,DATE(VALUE(RIGHT(H65,4)),VALUE(MID(H65,3,2)),VALUE(LEFT(H65,2)))),TODAY(),"Y"),"")) -> 23 | AB66: =IF(OR(D66="",E66=""),"",IFERROR(DATE(MID(E66,7,4),MID(E66,4,2),LEFT(E66,2))-DATE(MID(D66,7,4),MID(D66,4,2),LEFT(D66,2)),"")) | AC66: =IF(E66="","Pending",IF(AB66<=5,"On time","Delayed")) -> Delayed
A67: ORD10066 | B67: C002 | C67: P202 | D67: 46266 | E67: 46296 | F67: Priya Patel | G67: Female | H67: 19/09/1986 | I67: Kolkata | J67: East | K67: Home Appliances | L67: Iron | M67: 7 | N67: 2200 | O67: 15 | P67: 13090 | Q67: 5 | R67: UPI | S67: Neha | T67: priya.patel@company.com | U67: 9662063276 | V67: Completed | W67: =IF(OR(Q67<=2,V67="Cancelled"),"Blacklisted",IF(AND(P67>100000,Q67>=4,O67<=10%,V67="Completed"),"Platinum",IF(AND(P67>=50000,Q67>=3,V67="Completed"),"Gold",IF(AND(P67<50000,V67="Completed"),"Silver","")))) -> Silver | X67: =PROPER(TRIM(F67)) -> Priya Patel | Y67: =LEFT(F67,3)&MID(B67,2,3)&LEFT(I67,2) -> Pri002Ko | Z67: =IF(ISNUMBER(SEARCH("@",T67)),LOWER(TRIM(T67)),"invalid email") -> priya.patel@company.com | AA67: =IF(H66="","",IFERROR(DATEDIF(IF(ISNUMBER(H66),H66,DATE(VALUE(RIGHT(H66,4)),VALUE(MID(H66,3,2)),VALUE(LEFT(H66,2)))),TODAY(),"Y"),"")) | AB67: =IF(OR(D67="",E67=""),"",IFERROR(DATE(MID(E67,7,4),MID(E67,4,2),LEFT(E67,2))-DATE(MID(D67,7,4),MID(D67,4,2),LEFT(D67,2)),"")) | AC67: =IF(E67="","Pending",IF(AB67<=5,"On time","Delayed")) -> Delayed
A68: ORD10067 | B68: C008 | C68: P303 | D68: 45666 | E68: 45786 | F68: Kavya Nair | G68: Female | H68: 28/05/1985 | I68: Delhi | J68: North | K68: Stationery | L68: Marker | M68: 19 | N68: 45 | O68: 10 | P68: 769.5 | Q68: 5 | R68: Card | S68: Neha | T68: kavya.nair@company.com | U68: 9190393639 | V68: Cancelled | W68: =IF(OR(Q68<=2,V68="Cancelled"),"Blacklisted",IF(AND(P68>100000,Q68>=4,O68<=10%,V68="Completed"),"Platinum",IF(AND(P68>=50000,Q68>=3,V68="Completed"),"Gold",IF(AND(P68<50000,V68="Completed"),"Silver","")))) -> Blacklisted | X68: =PROPER(TRIM(F68)) -> Kavya Nair | Y68: =LEFT(F68,3)&MID(B68,2,3)&LEFT(I68,2) -> Kav008De | Z68: =IF(ISNUMBER(SEARCH("@",T68)),LOWER(TRIM(T68)),"invalid email") -> kavya.nair@company.com | AA68: =IF(H67="","",IFERROR(DATEDIF(IF(ISNUMBER(H67),H67,DATE(VALUE(RIGHT(H67,4)),VALUE(MID(H67,3,2)),VALUE(LEFT(H67,2)))),TODAY(),"Y"),"")) | AB68: =IF(OR(D68="",E68=""),"",IFERROR(DATE(MID(E68,7,4),MID(E68,4,2),LEFT(E68,2))-DATE(MID(D68,7,4),MID(D68,4,2),LEFT(D68,2)),"")) | AC68: =IF(E68="","Pending",IF(AB68<=5,"On time","Delayed")) -> Delayed
A69: ORD10068 | B69: C006 | C69: P201 | D69: 46267 | E69: 14/02/2026 | F69: Sneha Joshi | G69: Female | H69: 27/08/1979 | I69: Hyderabad | J69: South | K69: Home Appliances | L69: Mixer | M69: 7 | N69: 3500 | O69: 15 | P69: 20825 | Q69: 1 | R69: Cash | S69: Karan | T69: sneha.joshi@company.com | U69: 9106328582 | V69: Pending | W69: =IF(OR(Q69<=2,V69="Cancelled"),"Blacklisted",IF(AND(P69>100000,Q69>=4,O69<=10%,V69="Completed"),"Platinum",IF(AND(P69>=50000,Q69>=3,V69="Completed"),"Gold",IF(AND(P69<50000,V69="Completed"),"Silver","")))) -> Blacklisted | X69: =PROPER(TRIM(F69)) -> Sneha Joshi | Y69: =LEFT(F69,3)&MID(B69,2,3)&LEFT(I69,2) -> Sne006Hy | Z69: =IF(ISNUMBER(SEARCH("@",T69)),LOWER(TRIM(T69)),"invalid email") -> sneha.joshi@company.com | AA69: =IF(H68="","",IFERROR(DATEDIF(IF(ISNUMBER(H68),H68,DATE(VALUE(RIGHT(H68,4)),VALUE(MID(H68,3,2)),VALUE(LEFT(H68,2)))),TODAY(),"Y"),"")) | AB69: =IF(OR(D69="",E69=""),"",IFERROR(DATE(MID(E69,7,4),MID(E69,4,2),LEFT(E69,2))-DATE(MID(D69,7,4),MID(D69,4,2),LEFT(D69,2)),"")) | AC69: =IF(E69="","Pending",IF(AB69<=5,"On time","Delayed")) -> Delayed
A70: ORD10069 | B70: C010 | C70: P203 | D70: 14/12/2025 | E70: 19/12/2025 | F70: Pooja Shah | G70: Female | H70: 22/12/1976 | I70: Jaipur | J70: North | K70: Home Appliances | L70: Microwave | M70: 7 | N70: 8500 | O70: 20 | P70: 47600 | Q70: 4 | R70: NetBanking | S70: Neha | T70: pooja.shah@company.com | U70: 9264401015 | V70: Completed | W70: =IF(OR(Q70<=2,V70="Cancelled"),"Blacklisted",IF(AND(P70>100000,Q70>=4,O70<=10%,V70="Completed"),"Platinum",IF(AND(P70>=50000,Q70>=3,V70="Completed"),"Gold",IF(AND(P70<50000,V70="Completed"),"Silver","")))) -> Silver | X70: =PROPER(TRIM(F70)) -> Pooja Shah | Y70: =LEFT(F70,3)&MID(B70,2,3)&LEFT(I70,2) -> Poo010Ja | Z70: =IF(ISNUMBER(SEARCH("@",T70)),LOWER(TRIM(T70)),"invalid email") -> pooja.shah@company.com | AA70: =IF(H69="","",IFERROR(DATEDIF(IF(ISNUMBER(H69),H69,DATE(VALUE(RIGHT(H69,4)),VALUE(MID(H69,3,2)),VALUE(LEFT(H69,2)))),TODAY(),"Y"),"")) | AB70: =IF(OR(D70="",E70=""),"",IFERROR(DATE(MID(E70,7,4),MID(E70,4,2),LEFT(E70,2))-DATE(MID(D70,7,4),MID(D70,4,2),LEFT(D70,2)),"")) -> 5 | AC70: =IF(E70="","Pending",IF(AB70<=5,"On time","Delayed")) -> On time
A71: ORD10070 | B71: C008 | C71: P101 | D71: 45842 | E71: 45934 | F71: Kavya Nair | G71: Female | H71: 36648 | I71: Bengaluru | J71: South | K71: Electronics | L71: Laptop | M71: 16 | N71: 55000 | O71: 10 | P71: 792000 | Q71: 1 | R71: Card | S71: Aisha | T71: kavya.nair@company.com | U71: 9959237375 | V71: Completed | W71: =IF(OR(Q71<=2,V71="Cancelled"),"Blacklisted",IF(AND(P71>100000,Q71>=4,O71<=10%,V71="Completed"),"Platinum",IF(AND(P71>=50000,Q71>=3,V71="Completed"),"Gold",IF(AND(P71<50000,V71="Completed"),"Silver","")))) -> Blacklisted | X71: =PROPER(TRIM(F71)) -> Kavya Nair | Y71: =LEFT(F71,3)&MID(B71,2,3)&LEFT(I71,2) -> Kav008Be | Z71: =IF(ISNUMBER(SEARCH("@",T71)),LOWER(TRIM(T71)),"invalid email") -> kavya.nair@company.com | AA71: =IF(H70="","",IFERROR(DATEDIF(IF(ISNUMBER(H70),H70,DATE(VALUE(RIGHT(H70,4)),VALUE(MID(H70,3,2)),VALUE(LEFT(H70,2)))),TODAY(),"Y"),"")) | AB71: =IF(OR(D71="",E71=""),"",IFERROR(DATE(MID(E71,7,4),MID(E71,4,2),LEFT(E71,2))-DATE(MID(D71,7,4),MID(D71,4,2),LEFT(D71,2)),"")) | AC71: =IF(E71="","Pending",IF(AB71<=5,"On time","Delayed")) -> Delayed
A72: ORD10071 | B72: C004 | C72: P104 | D72: 24/12/2025 | E72: 46082 | F72: Anita Gupta | G72: Female | H72: 24/02/1987 | I72: Mumbai | J72: West | K72: Electronics | L72: Monitor | M72: 2 | N72: 12000 | O72: 20 | P72: 19200 | Q72: 1 | R72: Cash | S72: Karan | T72: Anita.gupta@company.com | U72: 9561836580 | V72: Pending | W72: =IF(OR(Q72<=2,V72="Cancelled"),"Blacklisted",IF(AND(P72>100000,Q72>=4,O72<=10%,V72="Completed"),"Platinum",IF(AND(P72>=50000,Q72>=3,V72="Completed"),"Gold",IF(AND(P72<50000,V72="Completed"),"Silver","")))) -> Blacklisted | X72: =PROPER(TRIM(F72)) -> Anita Gupta | Y72: =LEFT(F72,3)&MID(B72,2,3)&LEFT(I72,2) -> Ani004Mu | Z72: =IF(ISNUMBER(SEARCH("@",T72)),LOWER(TRIM(T72)),"invalid email") -> anita.gupta@company.com | AA72: =IF(H71="","",IFERROR(DATEDIF(IF(ISNUMBER(H71),H71,DATE(VALUE(RIGHT(H71,4)),VALUE(MID(H71,3,2)),VALUE(LEFT(H71,2)))),TODAY(),"Y"),"")) -> 26 | AB72: =IF(OR(D72="",E72=""),"",IFERROR(DATE(MID(E72,7,4),MID(E72,4,2),LEFT(E72,2))-DATE(MID(D72,7,4),MID(D72,4,2),LEFT(D72,2)),"")) | AC72: =IF(E72="","Pending",IF(AB72<=5,"On time","Delayed")) -> Delayed
A73: ORD10072 | B73: C003 | C73: P303 | D73: 30/08/2025 | E73: 45786 | F73: Rohit Singh | G73: Male | H73: 24/07/1984 | I73: Bengaluru | J73: South | K73: Stationery | L73: Marker | M73: 4 | N73: 45 | O73: 5 | P73: 171 | Q73: 1 | R73: Card | S73: Rahul | T73: rohit.singh@company.com | U73: 9512666401 | V73: Pending | W73: =IF(OR(Q73<=2,V73="Cancelled"),"Blacklisted",IF(AND(P73>100000,Q73>=4,O73<=10%,V73="Completed"),"Platinum",IF(AND(P73>=50000,Q73>=3,V73="Completed"),"Gold",IF(AND(P73<50000,V73="Completed"),"Silver","")))) -> Blacklisted | X73: =PROPER(TRIM(F73)) -> Rohit Singh | Y73: =LEFT(F73,3)&MID(B73,2,3)&LEFT(I73,2) -> Roh003Be | Z73: =IF(ISNUMBER(SEARCH("@",T73)),LOWER(TRIM(T73)),"invalid email") -> rohit.singh@company.com | AA73: =IF(H72="","",IFERROR(DATEDIF(IF(ISNUMBER(H72),H72,DATE(VALUE(RIGHT(H72,4)),VALUE(MID(H72,3,2)),VALUE(LEFT(H72,2)))),TODAY(),"Y"),"")) | AB73: =IF(OR(D73="",E73=""),"",IFERROR(DATE(MID(E73,7,4),MID(E73,4,2),LEFT(E73,2))-DATE(MID(D73,7,4),MID(D73,4,2),LEFT(D73,2)),"")) | AC73: =IF(E73="","Pending",IF(AB73<=5,"On time","Delayed")) -> Delayed
A74: ORD10073 | B74: C008 | C74: P103 | D74: 13/12/2025 | E74: 23/12/2025 | F74: Kavya Nair | G74: Female | H74: 22/09/1981 | I74: Jaipur | J74: North | K74: Electronics | L74: Keyboard | M74: 1 | N74: 1200 | O74: 5 | P74: 1140 | Q74: 3 | R74: UPI | S74: Aisha | T74: kavya.nair@company.com | U74: 9808988530 | V74: Cancelled | W74: =IF(OR(Q74<=2,V74="Cancelled"),"Blacklisted",IF(AND(P74>100000,Q74>=4,O74<=10%,V74="Completed"),"Platinum",IF(AND(P74>=50000,Q74>=3,V74="Completed"),"Gold",IF(AND(P74<50000,V74="Completed"),"Silver","")))) -> Blacklisted | X74: =PROPER(TRIM(F74)) -> Kavya Nair | Y74: =LEFT(F74,3)&MID(B74,2,3)&LEFT(I74,2) -> Kav008Ja | Z74: =IF(ISNUMBER(SEARCH("@",T74)),LOWER(TRIM(T74)),"invalid email") -> kavya.nair@company.com | AA74: =IF(H73="","",IFERROR(DATEDIF(IF(ISNUMBER(H73),H73,DATE(VALUE(RIGHT(H73,4)),VALUE(MID(H73,3,2)),VALUE(LEFT(H73,2)))),TODAY(),"Y"),"")) | AB74: =IF(OR(D74="",E74=""),"",IFERROR(DATE(MID(E74,7,4),MID(E74,4,2),LEFT(E74,2))-DATE(MID(D74,7,4),MID(D74,4,2),LEFT(D74,2)),"")) -> 10 | AC74: =IF(E74="","Pending",IF(AB74<=5,"On time","Delayed")) -> Delayed
A75: ORD10074 | B75: C010 | C75: P202 | D75: 46114 | E75: 16/02/2026 | F75: Pooja Shah | G75: Female | H75: 20/06/1980 | J75: South | K75: Home Appliances | L75: Iron | M75: 1 | N75: 2200 | O75: 15 | P75: 1870 | Q75: 4 | R75: Card | S75: Aisha | T75: pooja.shah@company.com | U75: 9286410494 | V75: Completed | W75: =IF(OR(Q75<=2,V75="Cancelled"),"Blacklisted",IF(AND(P75>100000,Q75>=4,O75<=10%,V75="Completed"),"Platinum",IF(AND(P75>=50000,Q75>=3,V75="Completed"),"Gold",IF(AND(P75<50000,V75="Completed"),"Silver","")))) -> Silver | X75: =PROPER(TRIM(F75)) -> Pooja Shah | Y75: =LEFT(F75,3)&MID(B75,2,3)&LEFT(I75,2) -> Poo010 | Z75: =IF(ISNUMBER(SEARCH("@",T75)),LOWER(TRIM(T75)),"invalid email") -> pooja.shah@company.com | AA75: =IF(H74="","",IFERROR(DATEDIF(IF(ISNUMBER(H74),H74,DATE(VALUE(RIGHT(H74,4)),VALUE(MID(H74,3,2)),VALUE(LEFT(H74,2)))),TODAY(),"Y"),"")) | AB75: =IF(OR(D75="",E75=""),"",IFERROR(DATE(MID(E75,7,4),MID(E75,4,2),LEFT(E75,2))-DATE(MID(D75,7,4),MID(D75,4,2),LEFT(D75,2)),"")) | AC75: =IF(E75="","Pending",IF(AB75<=5,"On time","Delayed")) -> Delayed
A76: ORD10075 | B76: C003 | C76: P103 | D76: 26/01/2026 | E76: 28/01/2026 | F76: Rohit Singh | G76: Male | H76: 29993 | I76: Pune | J76: West | K76: Electronics | L76: Keyboard | M76: 3 | N76: 1200 | O76: 10 | P76: 3240 | Q76: 5 | R76: Cash | S76: Rahul | T76: rohit.singh@company.com | U76: 9311555196 | V76: Completed | W76: =IF(OR(Q76<=2,V76="Cancelled"),"Blacklisted",IF(AND(P76>100000,Q76>=4,O76<=10%,V76="Completed"),"Platinum",IF(AND(P76>=50000,Q76>=3,V76="Completed"),"Gold",IF(AND(P76<50000,V76="Completed"),"Silver","")))) -> Silver | X76: =PROPER(TRIM(F76)) -> Rohit Singh | Y76: =LEFT(F76,3)&MID(B76,2,3)&LEFT(I76,2) -> Roh003Pu | Z76: =IF(ISNUMBER(SEARCH("@",T76)),LOWER(TRIM(T76)),"invalid email") -> rohit.singh@company.com | AA76: =IF(H75="","",IFERROR(DATEDIF(IF(ISNUMBER(H75),H75,DATE(VALUE(RIGHT(H75,4)),VALUE(MID(H75,3,2)),VALUE(LEFT(H75,2)))),TODAY(),"Y"),"")) | AB76: =IF(OR(D76="",E76=""),"",IFERROR(DATE(MID(E76,7,4),MID(E76,4,2),LEFT(E76,2))-DATE(MID(D76,7,4),MID(D76,4,2),LEFT(D76,2)),"")) -> 2 | AC76: =IF(E76="","Pending",IF(AB76<=5,"On time","Delayed")) -> On time
A77: ORD10076 | B77: C008 | C77: P201 | D77: 27/06/2025 | E77: 45845 | F77: Kavya Nair | G77: Female | H77: 29495 | I77: Bengaluru | J77: South | K77: Home Appliances | L77: Mixer | M77: 10 | N77: 3500 | O77: 20 | P77: 28000 | Q77: 5 | R77: Card | S77: Ritika | T77: kavya.nair@company.com | U77: 9101810266 | V77: Completed | W77: =IF(OR(Q77<=2,V77="Cancelled"),"Blacklisted",IF(AND(P77>100000,Q77>=4,O77<=10%,V77="Completed"),"Platinum",IF(AND(P77>=50000,Q77>=3,V77="Completed"),"Gold",IF(AND(P77<50000,V77="Completed"),"Silver","")))) -> Silver | X77: =PROPER(TRIM(F77)) -> Kavya Nair | Y77: =LEFT(F77,3)&MID(B77,2,3)&LEFT(I77,2) -> Kav008Be | Z77: =IF(ISNUMBER(SEARCH("@",T77)),LOWER(TRIM(T77)),"invalid email") -> kavya.nair@company.com | AA77: =IF(H76="","",IFERROR(DATEDIF(IF(ISNUMBER(H76),H76,DATE(VALUE(RIGHT(H76,4)),VALUE(MID(H76,3,2)),VALUE(LEFT(H76,2)))),TODAY(),"Y"),"")) -> 44 | AB77: =IF(OR(D77="",E77=""),"",IFERROR(DATE(MID(E77,7,4),MID(E77,4,2),LEFT(E77,2))-DATE(MID(D77,7,4),MID(D77,4,2),LEFT(D77,2)),"")) | AC77: =IF(E77="","Pending",IF(AB77<=5,"On time","Delayed")) -> Delayed
A78: ORD10077 | B78: C007 | C78: P102 | D78: 17/03/2026 | E78: 19/03/2026 | F78: Arjun Rao | G78: Male | H78: 27/04/1981 | I78: Delhi | J78: North | K78: Electronics | L78: Mouse | M78: 18 | N78: 700 | O78: 5 | P78: 11970 | Q78: 3 | R78: Card | S78: Neha | T78: arjun.rao@company.com | U78: 9464556593 | V78: Cancelled | W78: =IF(OR(Q78<=2,V78="Cancelled"),"Blacklisted",IF(AND(P78>100000,Q78>=4,O78<=10%,V78="Completed"),"Platinum",IF(AND(P78>=50000,Q78>=3,V78="Completed"),"Gold",IF(AND(P78<50000,V78="Completed"),"Silver","")))) -> Blacklisted | X78: =PROPER(TRIM(F78)) -> Arjun Rao | Y78: =LEFT(F78,3)&MID(B78,2,3)&LEFT(I78,2) -> Arj007De | Z78: =IF(ISNUMBER(SEARCH("@",T78)),LOWER(TRIM(T78)),"invalid email") -> arjun.rao@company.com | AA78: =IF(H77="","",IFERROR(DATEDIF(IF(ISNUMBER(H77),H77,DATE(VALUE(RIGHT(H77,4)),VALUE(MID(H77,3,2)),VALUE(LEFT(H77,2)))),TODAY(),"Y"),"")) -> 46 | AB78: =IF(OR(D78="",E78=""),"",IFERROR(DATE(MID(E78,7,4),MID(E78,4,2),LEFT(E78,2))-DATE(MID(D78,7,4),MID(D78,4,2),LEFT(D78,2)),"")) -> 2 | AC78: =IF(E78="","Pending",IF(AB78<=5,"On time","Delayed")) -> On time
A79: ORD10078 | B79: C005 | C79: P102 | D79: 45906 | E79: 18/06/2025 | F79: Vikas Mehta | G79: Male | H79: 31384 | I79: Bengaluru | J79: South | K79: Electronics | L79: Mouse | M79: 12 | N79: 700 | O79: 15 | P79: 7140 | Q79: 2 | R79: UPI | S79: Rahul | T79: vikas.mehta@company.com | U79: 9338278358 | V79: Completed | W79: =IF(OR(Q79<=2,V79="Cancelled"),"Blacklisted",IF(AND(P79>100000,Q79>=4,O79<=10%,V79="Completed"),"Platinum",IF(AND(P79>=50000,Q79>=3,V79="Completed"),"Gold",IF(AND(P79<50000,V79="Completed"),"Silver","")))) -> Blacklisted | X79: =PROPER(TRIM(F79)) -> Vikas Mehta | Y79: =LEFT(F79,3)&MID(B79,2,3)&LEFT(I79,2) -> Vik005Be | Z79: =IF(ISNUMBER(SEARCH("@",T79)),LOWER(TRIM(T79)),"invalid email") -> vikas.mehta@company.com | AA79: =IF(H78="","",IFERROR(DATEDIF(IF(ISNUMBER(H78),H78,DATE(VALUE(RIGHT(H78,4)),VALUE(MID(H78,3,2)),VALUE(LEFT(H78,2)))),TODAY(),"Y"),"")) | AB79: =IF(OR(D79="",E79=""),"",IFERROR(DATE(MID(E79,7,4),MID(E79,4,2),LEFT(E79,2))-DATE(MID(D79,7,4),MID(D79,4,2),LEFT(D79,2)),"")) | AC79: =IF(E79="","Pending",IF(AB79<=5,"On time","Delayed")) -> Delayed
A80: ORD10079 | B80: C009 | C80: P103 | D80: 15/11/2025 | E80: 16/11/2025 | F80: Mohit Verma | G80: Male | H80: 15/03/1999 | I80: Mumbai | J80: West | K80: Electronics | L80: Keyboard | M80: 8 | N80: 1200 | O80: 0 | P80: 9600 | Q80: 4 | R80: Card | S80: Rahul | T80: mohit.verma@company.com | U80: 9621410770 | V80: Pending | W80: =IF(OR(Q80<=2,V80="Cancelled"),"Blacklisted",IF(AND(P80>100000,Q80>=4,O80<=10%,V80="Completed"),"Platinum",IF(AND(P80>=50000,Q80>=3,V80="Completed"),"Gold",IF(AND(P80<50000,V80="Completed"),"Silver","")))) | X80: =PROPER(TRIM(F80)) -> Mohit Verma | Y80: =LEFT(F80,3)&MID(B80,2,3)&LEFT(I80,2) -> Moh009Mu | Z80: =IF(ISNUMBER(SEARCH("@",T80)),LOWER(TRIM(T80)),"invalid email") -> mohit.verma@company.com | AA80: =IF(H79="","",IFERROR(DATEDIF(IF(ISNUMBER(H79),H79,DATE(VALUE(RIGHT(H79,4)),VALUE(MID(H79,3,2)),VALUE(LEFT(H79,2)))),TODAY(),"Y"),"")) -> 40 | AB80: =IF(OR(D80="",E80=""),"",IFERROR(DATE(MID(E80,7,4),MID(E80,4,2),LEFT(E80,2))-DATE(MID(D80,7,4),MID(D80,4,2),LEFT(D80,2)),"")) -> 1 | AC80: =IF(E80="","Pending",IF(AB80<=5,"On time","Delayed")) -> On time
A81: ORD10080 | B81: C003 | C81: P301 | D81: 45819 | E81: 45941 | F81: Rohit Singh | G81: Male | H81: 30504 | I81: Pune | J81: West | K81: Stationery | L81: Notebook | M81: 2 | N81: 60 | O81: 0 | P81: 120 | Q81: 2 | R81: UPI | S81: Rahul | T81: rohit.singh@company.com | U81: 9981333189 | V81: Completed | W81: =IF(OR(Q81<=2,V81="Cancelled"),"Blacklisted",IF(AND(P81>100000,Q81>=4,O81<=10%,V81="Completed"),"Platinum",IF(AND(P81>=50000,Q81>=3,V81="Completed"),"Gold",IF(AND(P81<50000,V81="Completed"),"Silver","")))) -> Blacklisted | X81: =PROPER(TRIM(F81)) -> Rohit Singh | Y81: =LEFT(F81,3)&MID(B81,2,3)&LEFT(I81,2) -> Roh003Pu | Z81: =IF(ISNUMBER(SEARCH("@",T81)),LOWER(TRIM(T81)),"invalid email") -> rohit.singh@company.com | AA81: =IF(H80="","",IFERROR(DATEDIF(IF(ISNUMBER(H80),H80,DATE(VALUE(RIGHT(H80,4)),VALUE(MID(H80,3,2)),VALUE(LEFT(H80,2)))),TODAY(),"Y"),"")) | AB81: =IF(OR(D81="",E81=""),"",IFERROR(DATE(MID(E81,7,4),MID(E81,4,2),LEFT(E81,2))-DATE(MID(D81,7,4),MID(D81,4,2),LEFT(D81,2)),"")) | AC81: =IF(E81="","Pending",IF(AB81<=5,"On time","Delayed")) -> Delayed
A82: ORD10081 | B82: C001 | C82: P303 | D82: 45658 | E82: 45839 | F82: Amit Sharma | G82: Male | H82: 32662 | I82: Pune | J82: West | K82: Stationery | L82: Marker | M82: 10 | N82: 45 | O82: 15 | P82: 382.5 | Q82: 3 | R82: NetBanking | S82: Ritika | T82: amit.sharma@company.com | U82: 9723450355 | V82: Cancelled | W82: =IF(OR(Q82<=2,V82="Cancelled"),"Blacklisted",IF(AND(P82>100000,Q82>=4,O82<=10%,V82="Completed"),"Platinum",IF(AND(P82>=50000,Q82>=3,V82="Completed"),"Gold",IF(AND(P82<50000,V82="Completed"),"Silver","")))) -> Blacklisted | X82: =PROPER(TRIM(F82)) -> Amit Sharma | Y82: =LEFT(F82,3)&MID(B82,2,3)&LEFT(I82,2) -> Ami001Pu | Z82: =IF(ISNUMBER(SEARCH("@",T82)),LOWER(TRIM(T82)),"invalid email") -> amit.sharma@company.com | AA82: =IF(H81="","",IFERROR(DATEDIF(IF(ISNUMBER(H81),H81,DATE(VALUE(RIGHT(H81,4)),VALUE(MID(H81,3,2)),VALUE(LEFT(H81,2)))),TODAY(),"Y"),"")) -> 43 | AB82: =IF(OR(D82="",E82=""),"",IFERROR(DATE(MID(E82,7,4),MID(E82,4,2),LEFT(E82,2))-DATE(MID(D82,7,4),MID(D82,4,2),LEFT(D82,2)),"")) | AC82: =IF(E82="","Pending",IF(AB82<=5,"On time","Delayed")) -> Delayed
A83: ORD10082 | B83: C005 | C83: P201 | D83: 25/04/2026 | E83: 46086 | F83: Vikas Mehta | G83: Male | H83: 20/06/1982 | I83: Kolkata | J83: East | K83: Home Appliances | L83: Mixer | M83: 12 | N83: 3500 | O83: 5 | P83: 39900 | Q83: 3 | R83: NetBanking | S83: Aisha | T83: vikas.mehta@company.com | U83: 9886243907 | V83: Pending | W83: =IF(OR(Q83<=2,V83="Cancelled"),"Blacklisted",IF(AND(P83>100000,Q83>=4,O83<=10%,V83="Completed"),"Platinum",IF(AND(P83>=50000,Q83>=3,V83="Completed"),"Gold",IF(AND(P83<50000,V83="Completed"),"Silver","")))) | X83: =PROPER(TRIM(F83)) -> Vikas Mehta | Y83: =LEFT(F83,3)&MID(B83,2,3)&LEFT(I83,2) -> Vik005Ko | Z83: =IF(ISNUMBER(SEARCH("@",T83)),LOWER(TRIM(T83)),"invalid email") -> vikas.mehta@company.com | AA83: =IF(H82="","",IFERROR(DATEDIF(IF(ISNUMBER(H82),H82,DATE(VALUE(RIGHT(H82,4)),VALUE(MID(H82,3,2)),VALUE(LEFT(H82,2)))),TODAY(),"Y"),"")) -> 37 | AB83: =IF(OR(D83="",E83=""),"",IFERROR(DATE(MID(E83,7,4),MID(E83,4,2),LEFT(E83,2))-DATE(MID(D83,7,4),MID(D83,4,2),LEFT(D83,2)),"")) | AC83: =IF(E83="","Pending",IF(AB83<=5,"On time","Delayed")) -> Delayed
A84: ORD10083 | B84: C003 | C84: P301 | D84: 19/09/2025 | E84: 27/09/2025 | F84: Rohit Singh | G84: Male | H84: 23/06/2001 | I84: Mumbai | J84: West | K84: Stationery | L84: Notebook | M84: 2 | N84: 60 | O84: 15 | P84: 102 | Q84: 1 | R84: UPI | S84: Neha | T84: rohit.singh@company.com | U84: 9473931904 | V84: Completed | W84: =IF(OR(Q84<=2,V84="Cancelled"),"Blacklisted",IF(AND(P84>100000,Q84>=4,O84<=10%,V84="Completed"),"Platinum",IF(AND(P84>=50000,Q84>=3,V84="Completed"),"Gold",IF(AND(P84<50000,V84="Completed"),"Silver","")))) -> Blacklisted | X84: =PROPER(TRIM(F84)) -> Rohit Singh | Y84: =LEFT(F84,3)&MID(B84,2,3)&LEFT(I84,2) -> Roh003Mu | Z84: =IF(ISNUMBER(SEARCH("@",T84)),LOWER(TRIM(T84)),"invalid email") -> rohit.singh@company.com | AA84: =IF(H83="","",IFERROR(DATEDIF(IF(ISNUMBER(H83),H83,DATE(VALUE(RIGHT(H83,4)),VALUE(MID(H83,3,2)),VALUE(LEFT(H83,2)))),TODAY(),"Y"),"")) | AB84: =IF(OR(D84="",E84=""),"",IFERROR(DATE(MID(E84,7,4),MID(E84,4,2),LEFT(E84,2))-DATE(MID(D84,7,4),MID(D84,4,2),LEFT(D84,2)),"")) -> 8 | AC84: =IF(E84="","Pending",IF(AB84<=5,"On time","Delayed")) -> Delayed
A85: ORD10084 | B85: C003 | C85: P103 | D85: 18/03/2025 | E85: 21/03/2025 | F85: Rohit Singh | G85: Male | H85: 19/07/1983 | I85: Hyderabad | J85: South | K85: Electronics | L85: Keyboard | M85: 18 | N85: 1200 | O85: 15 | P85: 18360 | Q85: 3 | R85: Card | S85: Neha | T85: rohit.singh@company.com | U85: 9287159610 | V85: Pending | W85: =IF(OR(Q85<=2,V85="Cancelled"),"Blacklisted",IF(AND(P85>100000,Q85>=4,O85<=10%,V85="Completed"),"Platinum",IF(AND(P85>=50000,Q85>=3,V85="Completed"),"Gold",IF(AND(P85<50000,V85="Completed"),"Silver","")))) | X85: =PROPER(TRIM(F85)) -> Rohit Singh | Y85: =LEFT(F85,3)&MID(B85,2,3)&LEFT(I85,2) -> Roh003Hy | Z85: =IF(ISNUMBER(SEARCH("@",T85)),LOWER(TRIM(T85)),"invalid email") -> rohit.singh@company.com | AA85: =IF(H84="","",IFERROR(DATEDIF(IF(ISNUMBER(H84),H84,DATE(VALUE(RIGHT(H84,4)),VALUE(MID(H84,3,2)),VALUE(LEFT(H84,2)))),TODAY(),"Y"),"")) | AB85: =IF(OR(D85="",E85=""),"",IFERROR(DATE(MID(E85,7,4),MID(E85,4,2),LEFT(E85,2))-DATE(MID(D85,7,4),MID(D85,4,2),LEFT(D85,2)),"")) -> 3 | AC85: =IF(E85="","Pending",IF(AB85<=5,"On time","Delayed")) -> On time
A86: ORD10085 | B86: C008 | C86: P104 | D86: 30/10/2025 | E86: 31/10/2025 | F86: Kavya Nair | G86: Female | H86: 24/03/1993 | I86: Mumbai | J86: West | K86: Electronics | L86: Monitor | M86: 18 | N86: 12000 | O86: 15 | P86: 183600 | Q86: 2 | R86: Cash | S86: Rahul | T86: kavya.nair@company.com | U86: 9876513858 | V86: Completed | W86: =IF(OR(Q86<=2,V86="Cancelled"),"Blacklisted",IF(AND(P86>100000,Q86>=4,O86<=10%,V86="Completed"),"Platinum",IF(AND(P86>=50000,Q86>=3,V86="Completed"),"Gold",IF(AND(P86<50000,V86="Completed"),"Silver","")))) -> Blacklisted | X86: =PROPER(TRIM(F86)) -> Kavya Nair | Y86: =LEFT(F86,3)&MID(B86,2,3)&LEFT(I86,2) -> Kav008Mu | Z86: =IF(ISNUMBER(SEARCH("@",T86)),LOWER(TRIM(T86)),"invalid email") -> kavya.nair@company.com | AA86: =IF(H85="","",IFERROR(DATEDIF(IF(ISNUMBER(H85),H85,DATE(VALUE(RIGHT(H85,4)),VALUE(MID(H85,3,2)),VALUE(LEFT(H85,2)))),TODAY(),"Y"),"")) | AB86: =IF(OR(D86="",E86=""),"",IFERROR(DATE(MID(E86,7,4),MID(E86,4,2),LEFT(E86,2))-DATE(MID(D86,7,4),MID(D86,4,2),LEFT(D86,2)),"")) -> 1 | AC86: =IF(E86="","Pending",IF(AB86<=5,"On time","Delayed")) -> On time
A87: ORD10086 | B87: C007 | C87: P302 | D87: 31/10/2025 | E87: 45972 | F87: Arjun Rao | G87: Male | H87: 34977 | I87: Ahmedabad | J87: West | K87: Stationery | L87: Pen | M87: 7 | N87: 20 | O87: 0 | P87: 140 | Q87: 2 | R87: Card | S87: Ritika | T87: arjun.rao@company.com | U87: 9237400853 | V87: Cancelled | W87: =IF(OR(Q87<=2,V87="Cancelled"),"Blacklisted",IF(AND(P87>100000,Q87>=4,O87<=10%,V87="Completed"),"Platinum",IF(AND(P87>=50000,Q87>=3,V87="Completed"),"Gold",IF(AND(P87<50000,V87="Completed"),"Silver","")))) -> Blacklisted | X87: =PROPER(TRIM(F87)) -> Arjun Rao | Y87: =LEFT(F87,3)&MID(B87,2,3)&LEFT(I87,2) -> Arj007Ah | Z87: =IF(ISNUMBER(SEARCH("@",T87)),LOWER(TRIM(T87)),"invalid email") -> arjun.rao@company.com | AA87: =IF(H86="","",IFERROR(DATEDIF(IF(ISNUMBER(H86),H86,DATE(VALUE(RIGHT(H86,4)),VALUE(MID(H86,3,2)),VALUE(LEFT(H86,2)))),TODAY(),"Y"),"")) | AB87: =IF(OR(D87="",E87=""),"",IFERROR(DATE(MID(E87,7,4),MID(E87,4,2),LEFT(E87,2))-DATE(MID(D87,7,4),MID(D87,4,2),LEFT(D87,2)),"")) | AC87: =IF(E87="","Pending",IF(AB87<=5,"On time","Delayed")) -> Delayed
A88: ORD10087 | B88: C006 | C88: P201 | D88: 45934 | E88: 18/04/2025 | F88: Sneha Joshi | G88: Female | H88: 15/02/2001 | I88: Pune | J88: West | K88: Home Appliances | L88: Mixer | M88: 20 | N88: 3500 | O88: 20 | P88: 56000 | Q88: 4 | R88: Card | S88: Neha | T88: sneha.joshi@company.com | U88: 9599597595 | V88: Pending | W88: =IF(OR(Q88<=2,V88="Cancelled"),"Blacklisted",IF(AND(P88>100000,Q88>=4,O88<=10%,V88="Completed"),"Platinum",IF(AND(P88>=50000,Q88>=3,V88="Completed"),"Gold",IF(AND(P88<50000,V88="Completed"),"Silver","")))) | X88: =PROPER(TRIM(F88)) -> Sneha Joshi | Y88: =LEFT(F88,3)&MID(B88,2,3)&LEFT(I88,2) -> Sne006Pu | Z88: =IF(ISNUMBER(SEARCH("@",T88)),LOWER(TRIM(T88)),"invalid email") -> sneha.joshi@company.com | AA88: =IF(H87="","",IFERROR(DATEDIF(IF(ISNUMBER(H87),H87,DATE(VALUE(RIGHT(H87,4)),VALUE(MID(H87,3,2)),VALUE(LEFT(H87,2)))),TODAY(),"Y"),"")) -> 31 | AB88: =IF(OR(D88="",E88=""),"",IFERROR(DATE(MID(E88,7,4),MID(E88,4,2),LEFT(E88,2))-DATE(MID(D88,7,4),MID(D88,4,2),LEFT(D88,2)),"")) | AC88: =IF(E88="","Pending",IF(AB88<=5,"On time","Delayed")) -> Delayed
A89: ORD10088 | B89: C002 | C89: P203 | D89: 16/03/2026 | E89: 26/03/2026 | F89: Priya Patel | G89: Female | H89: 14/08/1999 | I89: Ahmedabad | J89: West | K89: Home Appliances | L89: Microwave | M89: 8 | N89: 8500 | O89: 20 | P89: 54400 | Q89: 3 | R89: Card | S89: Neha | T89: priya.patel@company.com | U89: 9230007509 | V89: Pending | W89: =IF(OR(Q89<=2,V89="Cancelled"),"Blacklisted",IF(AND(P89>100000,Q89>=4,O89<=10%,V89="Completed"),"Platinum",IF(AND(P89>=50000,Q89>=3,V89="Completed"),"Gold",IF(AND(P89<50000,V89="Completed"),"Silver","")))) | X89: =PROPER(TRIM(F89)) -> Priya Patel | Y89: =LEFT(F89,3)&MID(B89,2,3)&LEFT(I89,2) -> Pri002Ah | Z89: =IF(ISNUMBER(SEARCH("@",T89)),LOWER(TRIM(T89)),"invalid email") -> priya.patel@company.com | AA89: =IF(H88="","",IFERROR(DATEDIF(IF(ISNUMBER(H88),H88,DATE(VALUE(RIGHT(H88,4)),VALUE(MID(H88,3,2)),VALUE(LEFT(H88,2)))),TODAY(),"Y"),"")) | AB89: =IF(OR(D89="",E89=""),"",IFERROR(DATE(MID(E89,7,4),MID(E89,4,2),LEFT(E89,2))-DATE(MID(D89,7,4),MID(D89,4,2),LEFT(D89,2)),"")) -> 10 | AC89: =IF(E89="","Pending",IF(AB89<=5,"On time","Delayed")) -> Delayed
A90: ORD10089 | B90: C001 | C90: P104 | D90: 15/09/2025 | E90: 24/09/2025 | F90: Amit Sharma | G90: Male | H90: 20/03/2002 | I90: Ahmedabad | J90: north | K90: Electronics | L90: Monitor | M90: 6 | N90: 12000 | O90: 5 | P90: 68400 | Q90: 4 | R90: NetBanking | S90: Ritika | T90: amit.sharma@company.com | U90: 9823428025 | V90: Completed | W90: =IF(OR(Q90<=2,V90="Cancelled"),"Blacklisted",IF(AND(P90>100000,Q90>=4,O90<=10%,V90="Completed"),"Platinum",IF(AND(P90>=50000,Q90>=3,V90="Completed"),"Gold",IF(AND(P90<50000,V90="Completed"),"Silver","")))) -> Gold | X90: =PROPER(TRIM(F90)) -> Amit Sharma | Y90: =LEFT(F90,3)&MID(B90,2,3)&LEFT(I90,2) -> Ami001Ah | Z90: =IF(ISNUMBER(SEARCH("@",T90)),LOWER(TRIM(T90)),"invalid email") -> amit.sharma@company.com | AA90: =IF(H89="","",IFERROR(DATEDIF(IF(ISNUMBER(H89),H89,DATE(VALUE(RIGHT(H89,4)),VALUE(MID(H89,3,2)),VALUE(LEFT(H89,2)))),TODAY(),"Y"),"")) | AB90: =IF(OR(D90="",E90=""),"",IFERROR(DATE(MID(E90,7,4),MID(E90,4,2),LEFT(E90,2))-DATE(MID(D90,7,4),MID(D90,4,2),LEFT(D90,2)),"")) -> 9 | AC90: =IF(E90="","Pending",IF(AB90<=5,"On time","Delayed")) -> Delayed
A91: ORD10090 | B91: C008 | C91: P203 | D91: 46329 | E91: 19/03/2026 | F91: Kavya Nair | G91: Female | H91: 13/06/1992 | I91: Pune | J91: West | K91: Home Appliances | L91: Microwave | M91: 15 | N91: 8500 | O91: 0 | P91: 127500 | Q91: 4 | R91: NetBanking | S91: Ritika | T91: kavya.nair@company.com | U91: 9505048912 | V91: Cancelled | W91: =IF(OR(Q91<=2,V91="Cancelled"),"Blacklisted",IF(AND(P91>100000,Q91>=4,O91<=10%,V91="Completed"),"Platinum",IF(AND(P91>=50000,Q91>=3,V91="Completed"),"Gold",IF(AND(P91<50000,V91="Completed"),"Silver","")))) -> Blacklisted | X91: =PROPER(TRIM(F91)) -> Kavya Nair | Y91: =LEFT(F91,3)&MID(B91,2,3)&LEFT(I91,2) -> Kav008Pu | Z91: =IF(ISNUMBER(SEARCH("@",T91)),LOWER(TRIM(T91)),"invalid email") -> kavya.nair@company.com | AA91: =IF(H90="","",IFERROR(DATEDIF(IF(ISNUMBER(H90),H90,DATE(VALUE(RIGHT(H90,4)),VALUE(MID(H90,3,2)),VALUE(LEFT(H90,2)))),TODAY(),"Y"),"")) | AB91: =IF(OR(D91="",E91=""),"",IFERROR(DATE(MID(E91,7,4),MID(E91,4,2),LEFT(E91,2))-DATE(MID(D91,7,4),MID(D91,4,2),LEFT(D91,2)),"")) | AC91: =IF(E91="","Pending",IF(AB91<=5,"On time","Delayed")) -> Delayed
A92: ORD10091 | B92: C010 | C92: P103 | D92: 20/08/2025 | E92: 23/08/2025 | F92: Pooja Shah | G92: Female | H92: 18/06/1996 | I92: Jaipur | J92: North | K92: Electronics | L92: Keyboard | M92: 5 | N92: 1200 | O92: 15 | P92: 5100 | Q92: 1 | R92: NetBanking | S92: Ritika | T92: pooja.shah@company.com | U92: 9508068393 | V92: Cancelled | W92: =IF(OR(Q92<=2,V92="Cancelled"),"Blacklisted",IF(AND(P92>100000,Q92>=4,O92<=10%,V92="Completed"),"Platinum",IF(AND(P92>=50000,Q92>=3,V92="Completed"),"Gold",IF(AND(P92<50000,V92="Completed"),"Silver","")))) -> Blacklisted | X92: =PROPER(TRIM(F92)) -> Pooja Shah | Y92: =LEFT(F92,3)&MID(B92,2,3)&LEFT(I92,2) -> Poo010Ja | Z92: =IF(ISNUMBER(SEARCH("@",T92)),LOWER(TRIM(T92)),"invalid email") -> pooja.shah@company.com | AA92: =IF(H91="","",IFERROR(DATEDIF(IF(ISNUMBER(H91),H91,DATE(VALUE(RIGHT(H91,4)),VALUE(MID(H91,3,2)),VALUE(LEFT(H91,2)))),TODAY(),"Y"),"")) | AB92: =IF(OR(D92="",E92=""),"",IFERROR(DATE(MID(E92,7,4),MID(E92,4,2),LEFT(E92,2))-DATE(MID(D92,7,4),MID(D92,4,2),LEFT(D92,2)),"")) -> 3 | AC92: =IF(E92="","Pending",IF(AB92<=5,"On time","Delayed")) -> On time
A93: ORD10092 | B93: C010 | C93: P302 | D93: 13/08/2025 | E93: 14/08/2025 | F93: Pooja Shah | G93: Female | H93: 30174 | I93: Hyderabad | J93: South | K93: Stationery | L93: Pen | M93: 4 | N93: 20 | O93: 0 | P93: 80 | Q93: 4 | R93: NetBanking | S93: Rahul | T93: pooja.shah@company.com | U93: 9785807771 | V93: Completed | W93: =IF(OR(Q93<=2,V93="Cancelled"),"Blacklisted",IF(AND(P93>100000,Q93>=4,O93<=10%,V93="Completed"),"Platinum",IF(AND(P93>=50000,Q93>=3,V93="Completed"),"Gold",IF(AND(P93<50000,V93="Completed"),"Silver","")))) -> Silver | X93: =PROPER(TRIM(F93)) -> Pooja Shah | Y93: =LEFT(F93,3)&MID(B93,2,3)&LEFT(I93,2) -> Poo010Hy | Z93: =IF(ISNUMBER(SEARCH("@",T93)),LOWER(TRIM(T93)),"invalid email") -> pooja.shah@company.com | AA93: =IF(H92="","",IFERROR(DATEDIF(IF(ISNUMBER(H92),H92,DATE(VALUE(RIGHT(H92,4)),VALUE(MID(H92,3,2)),VALUE(LEFT(H92,2)))),TODAY(),"Y"),"")) | AB93: =IF(OR(D93="",E93=""),"",IFERROR(DATE(MID(E93,7,4),MID(E93,4,2),LEFT(E93,2))-DATE(MID(D93,7,4),MID(D93,4,2),LEFT(D93,2)),"")) -> 1 | AC93: =IF(E93="","Pending",IF(AB93<=5,"On time","Delayed")) -> On time
A94: ORD10093 | B94: C008 | C94: P302 | D94: 16/03/2025 | E94: 20/03/2025 | F94: Kavya Nair | G94: Female | H94: 25/06/1984 | I94: Bengaluru | J94: South | K94: Stationery | L94: Pen | M94: 10 | N94: 20 | O94: 0 | P94: 200 | Q94: 3 | R94: Cash | S94: Karan | T94: kavya.nair@company.com | U94: 9215250979 | V94: Pending | W94: =IF(OR(Q94<=2,V94="Cancelled"),"Blacklisted",IF(AND(P94>100000,Q94>=4,O94<=10%,V94="Completed"),"Platinum",IF(AND(P94>=50000,Q94>=3,V94="Completed"),"Gold",IF(AND(P94<50000,V94="Completed"),"Silver","")))) | X94: =PROPER(TRIM(F94)) -> Kavya Nair | Y94: =LEFT(F94,3)&MID(B94,2,3)&LEFT(I94,2) -> Kav008Be | Z94: =IF(ISNUMBER(SEARCH("@",T94)),LOWER(TRIM(T94)),"invalid email") -> kavya.nair@company.com | AA94: =IF(H93="","",IFERROR(DATEDIF(IF(ISNUMBER(H93),H93,DATE(VALUE(RIGHT(H93,4)),VALUE(MID(H93,3,2)),VALUE(LEFT(H93,2)))),TODAY(),"Y"),"")) -> 44 | AB94: =IF(OR(D94="",E94=""),"",IFERROR(DATE(MID(E94,7,4),MID(E94,4,2),LEFT(E94,2))-DATE(MID(D94,7,4),MID(D94,4,2),LEFT(D94,2)),"")) -> 4 | AC94: =IF(E94="","Pending",IF(AB94<=5,"On time","Delayed")) -> On time
A95: ORD10094 | B95: C004 | C95: P202 | D95: 45756 | E95: 45939 | F95: Anita Gupta | G95: Female | H95: 21/06/1994 | I95: Delhi | J95: North | K95: Home Appliances | L95: Iron | M95: 18 | N95: 2200 | O95: 10 | P95: 35640 | Q95: 3 | R95: Cash | S95: Ritika | T95: anita.gupta@company.com | U95: 9845884906 | V95: Cancelled | W95: =IF(OR(Q95<=2,V95="Cancelled"),"Blacklisted",IF(AND(P95>100000,Q95>=4,O95<=10%,V95="Completed"),"Platinum",IF(AND(P95>=50000,Q95>=3,V95="Completed"),"Gold",IF(AND(P95<50000,V95="Completed"),"Silver","")))) -> Blacklisted | X95: =PROPER(TRIM(F95)) -> Anita Gupta | Y95: =LEFT(F95,3)&MID(B95,2,3)&LEFT(I95,2) -> Ani004De | Z95: =IF(ISNUMBER(SEARCH("@",T95)),LOWER(TRIM(T95)),"invalid email") -> anita.gupta@company.com | AA95: =IF(H94="","",IFERROR(DATEDIF(IF(ISNUMBER(H94),H94,DATE(VALUE(RIGHT(H94,4)),VALUE(MID(H94,3,2)),VALUE(LEFT(H94,2)))),TODAY(),"Y"),"")) | AB95: =IF(OR(D95="",E95=""),"",IFERROR(DATE(MID(E95,7,4),MID(E95,4,2),LEFT(E95,2))-DATE(MID(D95,7,4),MID(D95,4,2),LEFT(D95,2)),"")) | AC95: =IF(E95="","Pending",IF(AB95<=5,"On time","Delayed")) -> Delayed
A96: ORD10095 | B96: C001 | C96: P201 | D96: 45995 | E96: 15/04/2025 | F96: Amit Sharma | G96: Male | H96: 17/10/1990 | I96: Delhi | J96: North | K96: Home Appliances | L96: Mixer | M96: 7 | N96: 3500 | O96: 15 | P96: 20825 | Q96: 3 | R96: NetBanking | S96: Rahul | T96: amit.sharma@company.com | U96: 9393097397 | V96: Completed | W96: =IF(OR(Q96<=2,V96="Cancelled"),"Blacklisted",IF(AND(P96>100000,Q96>=4,O96<=10%,V96="Completed"),"Platinum",IF(AND(P96>=50000,Q96>=3,V96="Completed"),"Gold",IF(AND(P96<50000,V96="Completed"),"Silver","")))) -> Silver | X96: =PROPER(TRIM(F96)) -> Amit Sharma | Y96: =LEFT(F96,3)&MID(B96,2,3)&LEFT(I96,2) -> Ami001De | Z96: =IF(ISNUMBER(SEARCH("@",T96)),LOWER(TRIM(T96)),"invalid email") -> amit.sharma@company.com | AA96: =IF(H95="","",IFERROR(DATEDIF(IF(ISNUMBER(H95),H95,DATE(VALUE(RIGHT(H95,4)),VALUE(MID(H95,3,2)),VALUE(LEFT(H95,2)))),TODAY(),"Y"),"")) | AB96: =IF(OR(D96="",E96=""),"",IFERROR(DATE(MID(E96,7,4),MID(E96,4,2),LEFT(E96,2))-DATE(MID(D96,7,4),MID(D96,4,2),LEFT(D96,2)),"")) | AC96: =IF(E96="","Pending",IF(AB96<=5,"On time","Delayed")) -> Delayed
A97: ORD10096 | B97: C002 | C97: P203 | D97: 46117 | E97: 46208 | F97: Priya Patel | G97: Female | H97: 28/01/1987 | I97: Kolkata | J97: East | K97: Home Appliances | L97: Microwave | M97: 19 | N97: 8500 | O97: 15 | P97: 137275 | Q97: 4 | R97: Card | S97: Karan | T97: priya.patel@company.com | U97: 9958032109 | V97: Pending | W97: =IF(OR(Q97<=2,V97="Cancelled"),"Blacklisted",IF(AND(P97>100000,Q97>=4,O97<=10%,V97="Completed"),"Platinum",IF(AND(P97>=50000,Q97>=3,V97="Completed"),"Gold",IF(AND(P97<50000,V97="Completed"),"Silver","")))) | X97: =PROPER(TRIM(F97)) -> Priya Patel | Y97: =LEFT(F97,3)&MID(B97,2,3)&LEFT(I97,2) -> Pri002Ko | Z97: =IF(ISNUMBER(SEARCH("@",T97)),LOWER(TRIM(T97)),"invalid email") -> priya.patel@company.com | AA97: =IF(H96="","",IFERROR(DATEDIF(IF(ISNUMBER(H96),H96,DATE(VALUE(RIGHT(H96,4)),VALUE(MID(H96,3,2)),VALUE(LEFT(H96,2)))),TODAY(),"Y"),"")) | AB97: =IF(OR(D97="",E97=""),"",IFERROR(DATE(MID(E97,7,4),MID(E97,4,2),LEFT(E97,2))-DATE(MID(D97,7,4),MID(D97,4,2),LEFT(D97,2)),"")) | AC97: =IF(E97="","Pending",IF(AB97<=5,"On time","Delayed")) -> Delayed
A98: ORD10097 | B98: C006 | C98: P104 | D98: 18/01/2026 | E98: 27/01/2026 | F98: Sneha Joshi | G98: Female | H98: 21/09/1983 | I98: Ahmedabad | J98: West | K98: Electronics | L98: Monitor | M98: 13 | N98: 12000 | O98: 15 | P98: 132600 | Q98: 4 | R98: Cash | S98: Rahul | T98: sneha.joshi@company.com | U98: 9755082957 | V98: Completed | W98: =IF(OR(Q98<=2,V98="Cancelled"),"Blacklisted",IF(AND(P98>100000,Q98>=4,O98<=10%,V98="Completed"),"Platinum",IF(AND(P98>=50000,Q98>=3,V98="Completed"),"Gold",IF(AND(P98<50000,V98="Completed"),"Silver","")))) -> Gold | X98: =PROPER(TRIM(F98)) -> Sneha Joshi | Y98: =LEFT(F98,3)&MID(B98,2,3)&LEFT(I98,2) -> Sne006Ah | Z98: =IF(ISNUMBER(SEARCH("@",T98)),LOWER(TRIM(T98)),"invalid email") -> sneha.joshi@company.com | AA98: =IF(H97="","",IFERROR(DATEDIF(IF(ISNUMBER(H97),H97,DATE(VALUE(RIGHT(H97,4)),VALUE(MID(H97,3,2)),VALUE(LEFT(H97,2)))),TODAY(),"Y"),"")) | AB98: =IF(OR(D98="",E98=""),"",IFERROR(DATE(MID(E98,7,4),MID(E98,4,2),LEFT(E98,2))-DATE(MID(D98,7,4),MID(D98,4,2),LEFT(D98,2)),"")) -> 9 | AC98: =IF(E98="","Pending",IF(AB98<=5,"On time","Delayed")) -> Delayed
A99: ORD10098 | B99: C001 | C99: P302 | D99: 14/03/2026 | E99: 24/03/2026 | F99: Amit Sharma | G99: Male | H99: 32602 | I99: Pune | J99: West | K99: Stationery | L99: Pen | M99: 7 | N99: 20 | O99: 0 | P99: 140 | Q99: 1 | R99: Card | S99: Karan | T99: amit.sharma@company.com | U99: 9872235856 | V99: Cancelled | W99: =IF(OR(Q99<=2,V99="Cancelled"),"Blacklisted",IF(AND(P99>100000,Q99>=4,O99<=10%,V99="Completed"),"Platinum",IF(AND(P99>=50000,Q99>=3,V99="Completed"),"Gold",IF(AND(P99<50000,V99="Completed"),"Silver","")))) -> Blacklisted | X99: =PROPER(TRIM(F99)) -> Amit Sharma | Y99: =LEFT(F99,3)&MID(B99,2,3)&LEFT(I99,2) -> Ami001Pu | Z99: =IF(ISNUMBER(SEARCH("@",T99)),LOWER(TRIM(T99)),"invalid email") -> amit.sharma@company.com | AA99: =IF(H98="","",IFERROR(DATEDIF(IF(ISNUMBER(H98),H98,DATE(VALUE(RIGHT(H98,4)),VALUE(MID(H98,3,2)),VALUE(LEFT(H98,2)))),TODAY(),"Y"),"")) | AB99: =IF(OR(D99="",E99=""),"",IFERROR(DATE(MID(E99,7,4),MID(E99,4,2),LEFT(E99,2))-DATE(MID(D99,7,4),MID(D99,4,2),LEFT(D99,2)),"")) -> 10 | AC99: =IF(E99="","Pending",IF(AB99<=5,"On time","Delayed")) -> Delayed
A100: ORD10099 | B100: C004 | C100: P102 | D100: 45905 | E100: 45966 | F100: Anita Gupta | G100: Female | H100: 25/09/1987 | I100: Delhi | J100: North | K100: Electronics | L100: Mouse | M100: 5 | N100: 700 | O100: 15 | P100: 999999 | Q100: 4 | R100: Card | S100: Ritika | T100: anita.gupta@company.com | U100: 9335138816 | V100: Pending | W100: =IF(OR(Q100<=2,V100="Cancelled"),"Blacklisted",IF(AND(P100>100000,Q100>=4,O100<=10%,V100="Completed"),"Platinum",IF(AND(P100>=50000,Q100>=3,V100="Completed"),"Gold",IF(AND(P100<50000,V100="Completed"),"Silver","")))) | X100: =PROPER(TRIM(F100)) -> Anita Gupta | Y100: =LEFT(F100,3)&MID(B100,2,3)&LEFT(I100,2) -> Ani004De | Z100: =IF(ISNUMBER(SEARCH("@",T100)),LOWER(TRIM(T100)),"invalid email") -> anita.gupta@company.com | AA100: =IF(H99="","",IFERROR(DATEDIF(IF(ISNUMBER(H99),H99,DATE(VALUE(RIGHT(H99,4)),VALUE(MID(H99,3,2)),VALUE(LEFT(H99,2)))),TODAY(),"Y"),"")) -> 37 | AB100: =IF(OR(D100="",E100=""),"",IFERROR(DATE(MID(E100,7,4),MID(E100,4,2),LEFT(E100,2))-DATE(MID(D100,7,4),MID(D100,4,2),LEFT(D100,2)),"")) | AC100: =IF(E100="","Pending",IF(AB100<=5,"On time","Delayed")) -> Delayed
...

Sheet Sales SSummary Report
A1: Sales SummaryReport
A3: Quesstion | B3: Result
A4: Electronics Completed Orders Total Sales | B4: =SUMIFS(Sheet2!S:S,Sheet2!N:N,"Electronics",Sheet2!Y:Y,"Completed") -> 7222090
A5: Neha North Region Total Sales | B5: =SUMIFS(Sheet2!S:S,Sheet2!V:V,"Neha",Sheet2!M:M,"North") -> 1550369.2
A6: Orders With Discount>=15%and UPI | B6: =COUNTIFS(Sheet2!R:R,">=15%",Sheet2!U:U,"UPI") -> 83
A7: Customerss With Rating 5and Completed Orders | B7: =COUNTIFS(Sheet2!T:T,5,Sheet2!Y:Y,"Completed") -> 27
A8: Average Sales in West Region with Quantity>5 | B8: =AVERAGEIFS(Sheet2!S:S,Sheet2!M:M,"West",Sheet2!P:P,">5") -> 82824.451
C12: 0

Sheet Sales Statistics Report
A1: Sales Statistics Report
A3: Statistic | B3: Result
A4: Average Sales | B4: =AVERAGE(Sheet1!P:P) -> 69531.875
A5: Median Sales | B5: =MEDIAN(Sheet1!P:P) -> 10475
A6: Highest Sales | B6: =MAX(Sheet1!P:P) -> 1045000
A7: Lowest Sales | B7: =MIN(Sheet1!P:P) -> 19
A8: Standard Deviation | B8: =_xlfn.STDEV.S(Sheet1!P:P) -> 167151.45
A9: 90th Percentile | B9: =_xlfn.PERCENTILE.INC(Sheet1!P:P,0.9) -> 163880
A10: 90th percentile Meaaning | B10: 90% of Sales Values are less than or equal to this value.

Sheet Financial Analysis Report
A1: Financial Analysis Report
A3: Metrics | B3: Result
A4: Future Value of Monthly Investment | B4: =ROUND(FV(0.1/12,60,-50000,0,0),2) -> 3871853.6
A5: Monthly Investment Required | B5: =ROUND(PMT(10%/12,60,0,-5000000),2) -> 64568.56
A6: Monthly EMI For Equipment Loan | B6: =ROUND(PMT(9%/12,60,1000000)*-1,0) -> 20758

Sheet Product Performance Report
A1: Product Performance Report
A3: Metric | B3: Result
A4: Total Revenue(Quantity*Unit Price) | B4: =SUMPRODUCT(Sheet2!P2:P10000,Sheet2!Q2:Q10000) -> 36610875
A5: Weighted Average Unit Price | B5: =SUMPRODUCT(Sheet2!P2:P10000,Sheet2!Q2:Q10000)/SUM(Sheet2!P2:P10000) -> 6990.8106
A6: Difference Between Calculated Revenue and Sales | B6: =SUMPRODUCT(Sheet2!P2:P10000,Sheet2!Q2:Q10000)-SUM(Sheet2!S2:S10000) -> 1844937.5
A7: Total Discounted Amount | B7: {=SUMPRODUCT(Sheet2!P2:P10000,Sheet2!Q2:Q10000,Sheet2!R2:R10000/100)} -> 2918151.5

Sheet Cleaned_Data
A1: Order ID | B1: Customer_ID | C1: Product_ID | D1: Order_Date | E1: Delivery_Date | F1: Customer_Name | G1: Gender | H1: DOB | I1: City | J1: Region | K1: Category | L1: Product_Name | M1: Quantity | N1: Unit_Price | O1: Discount_% | P1: Sales | Q1: Rating | R1: Payment_Mode | S1: Salesperson | T1: Email | U1: Phone | V1: Order_Status | W1: Customer Classification | X1: Standarized Customer Name | Y1: Customer Code | Z1: Standerized Email | AA1: Customer age | AB1: Delivery Time | AC1: DELIVERY status | AK1: month-year
A2: ORD10001 | B2: C008 | C2: P202 | D2: 18/09/2025 | E2: 22/09/2025 | F2: Kavya Nair | G2: Female | H2: 27767 | I2: Hyderabad | J2: South | K2: Home Appliances | L2: Iron | M2: 4 | N2: 2200 | O2: 10 | P2: 7920 | Q2: 4 | R2: Cash | S2: Ritika | T2: KAvya.nair@company.com | U2: 9431429797 | V2: Completed | W2: =IF(OR(Q2<=2,V2="Cancelled"),"Blacklisted",IF(AND(P2>100000,Q2>=4,O2<=10%,V2="Completed"),"Platinum",IF(AND(P2>=50000,Q2>=3,V2="Completed"),"Gold",IF(AND(P2<50000,V2="Completed"),"Silver","")))) -> Silver | X2: =PROPER(TRIM(F2)) -> Kavya Nair | Y2: =LEFT(F2,3)&MID(B2,2,3)&LEFT(I2,2) -> Kav008Hy | Z2: =IF(ISNUMBER(SEARCH("@",T2)),LOWER(TRIM(T2)),"invalid email") -> kavya.nair@company.com | AA2: =DATEDIF(H2,TODAY(),"Y") -> 50 | AB2: =IF(OR(D2="",E2=""),"",IFERROR(DATE(MID(E2,7,4),MID(E2,4,2),LEFT(E2,2))-DATE(MID(D2,7,4),MID(D2,4,2),LEFT(D2,2)),"")) -> 4 | AC2: =IF(E2="","Pending",IF(AB2<=5,"On time","Delayed")) -> On time | AD2: =IF(TRIM(S2)="","Not Assigned",S2) -> Ritika | AE2: =PROPER(TRIM(F2)) -> Kavya Nair | AF2: =PROPER(TRIM(K2)) -> Home Appliances | AG2: =PROPER(TRIM(J2)) -> South | AH2: =PROPER(TRIM(K2)) -> Home Appliances | AI2: =IF(OR(LOWER(TRIM(K2))="electronic",LOWER(TRIM(K2))="electronics"),"Electronics",PROPER(TRIM(K2))) -> Home Appliances | AK2: =IF(COUNTIF($A$2:A2,A2)=1,1,0) -> 1
A3: ORD10001 | B3: C008 | C3: P104 | D3: 27/04/2025 | E3: 45752 | F3: Kavya Nair | G3: Female | H3: 16/10/2000 | I3: Delhi | J3: North | K3: Electronics | L3: Monitor | M3: 17 | N3: 12000 | O3: 10 | P3: 183600 | Q3: 1 | R3: NetBanking | S3: Rahul | T3: kavya.nair@company.com | U3: 9129865339 | V3: Completed | W3: =IF(OR(Q3<=2,V3="Cancelled"),"Blacklisted",IF(AND(P3>100000,Q3>=4,O3<=10%,V3="Completed"),"Platinum",IF(AND(P3>=50000,Q3>=3,V3="Completed"),"Gold",IF(AND(P3<50000,V3="Completed"),"Silver","")))) -> Blacklisted | X3: =PROPER(TRIM(F3)) -> Kavya Nair | Y3: =LEFT(F3,3)&MID(B3,2,3)&LEFT(I3,2) -> Kav008De | Z3: =IF(ISNUMBER(SEARCH("@",T3)),LOWER(TRIM(T3)),"invalid email") -> kavya.nair@company.com | AA3: =IF(H2="","",IFERROR(DATEDIF(IF(ISNUMBER(H2),H2,DATE(VALUE(RIGHT(H2,4)),VALUE(MID(H2,3,2)),VALUE(LEFT(H2,2)))),TODAY(),"Y"),"")) -> 50 | AB3: =IF(OR(D3="",E3=""),"",IFERROR(DATE(MID(E3,7,4),MID(E3,4,2),LEFT(E3,2))-DATE(MID(D3,7,4),MID(D3,4,2),LEFT(D3,2)),"")) | AC3: =IF(E3="","Pending",IF(AB3<=5,"On time","Delayed")) -> Delayed | AD3: =IF(TRIM(S3)="","Not Assigned",S3) -> Rahul | AE3: =PROPER(TRIM(F3)) -> Kavya Nair | AF3: =PROPER(TRIM(K3)) -> Electronics | AG3: =PROPER(TRIM(J3)) -> North | AH3: =PROPER(TRIM(K3)) -> Electronics | AI3: =IF(OR(LOWER(TRIM(K3))="electronic",LOWER(TRIM(K3))="electronics"),"Electronics",PROPER(TRIM(K3))) -> Electronics | AK3: =IF(COUNTIF($A$2:A3,A3)=1,1,0) -> 0
A4: ORD10006 | B4: C007 | C4: P202 | D4: 46113 | E4: 46357 | F4: Arjun Rao | G4: Male | H4: 32326 | I4: Hyderabad | J4: South | K4: Home Appliances | L4: Iron | M4: 4 | N4: 2200 | O4: 0 | P4: 8800 | Q4: 1 | R4: UPI | S4: Ritika | T4: arjun.rao@company.com | U4: 9780584905 | V4: Completed | W4: =IF(OR(Q4<=2,V4="Cancelled"),"Blacklisted",IF(AND(P4>100000,Q4>=4,O4<=10%,V4="Completed"),"Platinum",IF(AND(P4>=50000,Q4>=3,V4="Completed"),"Gold",IF(AND(P4<50000,V4="Completed"),"Silver","")))) -> Blacklisted | X4: =PROPER(TRIM(F4)) -> Arjun Rao | Y4: =LEFT(F4,3)&MID(B4,2,3)&LEFT(I4,2) -> Arj007Hy | Z4: =IF(ISNUMBER(SEARCH("@",T4)),LOWER(TRIM(T4)),"invalid email") -> arjun.rao@company.com | AA4: =IF(H3="","",IFERROR(DATEDIF(IF(ISNUMBER(H3),H3,DATE(VALUE(RIGHT(H3,4)),VALUE(MID(H3,3,2)),VALUE(LEFT(H3,2)))),TODAY(),"Y"),"")) | AB4: =IF(OR(D4="",E4=""),"",IFERROR(DATE(MID(E4,7,4),MID(E4,4,2),LEFT(E4,2))-DATE(MID(D4,7,4),MID(D4,4,2),LEFT(D4,2)),"")) | AC4: =IF(E4="","Pending",IF(AB4<=5,"On time","Delayed")) -> Delayed | AD4: =IF(TRIM(S4)="","Not Assigned",S4) -> Ritika | AE4: =PROPER(TRIM(F4)) -> Arjun Rao | AF4: =PROPER(TRIM(K4)) -> Home Appliances | AG4: =PROPER(TRIM(J4)) -> South | AH4: =PROPER(TRIM(K4)) -> Home Appliances | AI4: =IF(OR(LOWER(TRIM(K4))="electronic",LOWER(TRIM(K4))="electronics"),"Electronics",PROPER(TRIM(K4))) -> Home Appliances | AK4: =IF(COUNTIF($A$2:A4,A4)=1,1,0) -> 1
A5: ORD10007 | B5: C008 | C5: P201 | D5: 31/02/2025 | E5: 25/02/2026 | F5: Kavya Nair | G5: Female | H5: 20/03/2003 | I5: Hyderabad | J5: South | K5: Home Appliances | L5: Mixer | M5: 2 | N5: 3500 | O5: 5 | P5: 6650 | Q5: 1 | R5: UPI | S5: Ritika | T5: kavya.nair@company.com | U5: 9958252176 | V5: Completed | W5: =IF(OR(Q5<=2,V5="Cancelled"),"Blacklisted",IF(AND(P5>100000,Q5>=4,O5<=10%,V5="Completed"),"Platinum",IF(AND(P5>=50000,Q5>=3,V5="Completed"),"Gold",IF(AND(P5<50000,V5="Completed"),"Silver","")))) -> Blacklisted | X5: =PROPER(TRIM(F5)) -> Kavya Nair | Y5: =LEFT(F5,3)&MID(B5,2,3)&LEFT(I5,2) -> Kav008Hy | Z5: =IF(ISNUMBER(SEARCH("@",T5)),LOWER(TRIM(T5)),"invalid email") -> kavya.nair@company.com | AA5: =IF(H4="","",IFERROR(DATEDIF(IF(ISNUMBER(H4),H4,DATE(VALUE(RIGHT(H4,4)),VALUE(MID(H4,3,2)),VALUE(LEFT(H4,2)))),TODAY(),"Y"),"")) -> 38 | AB5: =IF(OR(D5="",E5=""),"",IFERROR(DATE(MID(E5,7,4),MID(E5,4,2),LEFT(E5,2))-DATE(MID(D5,7,4),MID(D5,4,2),LEFT(D5,2)),"")) -> 359 | AC5: =IF(E5="","Pending",IF(AB5<=5,"On time","Delayed")) -> Delayed | AD5: =IF(TRIM(S5)="","Not Assigned",S5) -> Ritika | AE5: =PROPER(TRIM(F5)) -> Kavya Nair | AF5: =PROPER(TRIM(K5)) -> Home Appliances | AG5: =PROPER(TRIM(J5)) -> South | AH5: =PROPER(TRIM(K5)) -> Home Appliances | AI5: =IF(OR(LOWER(TRIM(K5))="electronic",LOWER(TRIM(K5))="electronics"),"Electronics",PROPER(TRIM(K5))) -> Home Appliances | AK5: =IF(COUNTIF($A$2:A5,A5)=1,1,0) -> 1
A6: ORD10008 | B6: C002 | C6: P104 | D6: 13/04/2025 | E6: 19/04/2025 | F6: Priya Patel | G6: Female | H6: 34883 | I6: Mumbai | J6: West | K6: Electronics | L6: Monitor | M6: 14 | N6: 12000 | O6: 15 | P6: 142800 | Q6: 4 | R6: NetBanking | S6: Ritika | T6: priYa.patel@company.com | U6: 9705521654 | V6: Completed | W6: =IF(OR(Q6<=2,V6="Cancelled"),"Blacklisted",IF(AND(P6>100000,Q6>=4,O6<=10%,V6="Completed"),"Platinum",IF(AND(P6>=50000,Q6>=3,V6="Completed"),"Gold",IF(AND(P6<50000,V6="Completed"),"Silver","")))) -> Gold | X6: =PROPER(TRIM(F6)) -> Priya Patel | Y6: =LEFT(F6,3)&MID(B6,2,3)&LEFT(I6,2) -> Pri002Mu | Z6: =IF(ISNUMBER(SEARCH("@",T6)),LOWER(TRIM(T6)),"invalid email") -> priya.patel@company.com | AA6: =IF(H5="","",IFERROR(DATEDIF(IF(ISNUMBER(H5),H5,DATE(VALUE(RIGHT(H5,4)),VALUE(MID(H5,3,2)),VALUE(LEFT(H5,2)))),TODAY(),"Y"),"")) | AB6: =IF(OR(D6="",E6=""),"",IFERROR(DATE(MID(E6,7,4),MID(E6,4,2),LEFT(E6,2))-DATE(MID(D6,7,4),MID(D6,4,2),LEFT(D6,2)),"")) -> 6 | AC6: =IF(E6="","Pending",IF(AB6<=5,"On time","Delayed")) -> Delayed | AD6: =IF(TRIM(S6)="","Not Assigned",S6) -> Ritika | AE6: =PROPER(TRIM(F6)) -> Priya Patel | AF6: =PROPER(TRIM(K6)) -> Electronics | AG6: =PROPER(TRIM(J6)) -> West | AH6: =PROPER(TRIM(K6)) -> Electronics | AI6: =IF(OR(LOWER(TRIM(K6))="electronic",LOWER(TRIM(K6))="electronics"),"Electronics",PROPER(TRIM(K6))) -> Electronics | AK6: =IF(COUNTIF($A$2:A6,A6)=1,1,0) -> 1
A7: ORD10009 | B7: C008 | C7: P104 | D7: 31/01/2026 | E7: 46055 | F7: Kavya Nair | G7: Female | H7: 35585 | I7: Pune | J7: West | K7: Electronics | L7: Monitor | M7: 4 | N7: 12000 | O7: 15 | P7: 40800 | Q7: 4 | R7: UPI | S7: Neha | T7: kavya.nair@company.com | U7: 9588041011 | V7: Completed | W7: =IF(OR(Q7<=2,V7="Cancelled"),"Blacklisted",IF(AND(P7>100000,Q7>=4,O7<=10%,V7="Completed"),"Platinum",IF(AND(P7>=50000,Q7>=3,V7="Completed"),"Gold",IF(AND(P7<50000,V7="Completed"),"Silver","")))) -> Silver | X7: =PROPER(TRIM(F7)) -> Kavya Nair | Y7: =LEFT(F7,3)&MID(B7,2,3)&LEFT(I7,2) -> Kav008Pu | Z7: =IF(ISNUMBER(SEARCH("@",T7)),LOWER(TRIM(T7)),"invalid email") -> kavya.nair@company.com | AA7: =IF(H6="","",IFERROR(DATEDIF(IF(ISNUMBER(H6),H6,DATE(VALUE(RIGHT(H6,4)),VALUE(MID(H6,3,2)),VALUE(LEFT(H6,2)))),TODAY(),"Y"),"")) -> 31 | AB7: =IF(OR(D7="",E7=""),"",IFERROR(DATE(MID(E7,7,4),MID(E7,4,2),LEFT(E7,2))-DATE(MID(D7,7,4),MID(D7,4,2),LEFT(D7,2)),"")) | AC7: =IF(E7="","Pending",IF(AB7<=5,"On time","Delayed")) -> Delayed | AD7: =IF(TRIM(S7)="","Not Assigned",S7) -> Neha | AE7: =PROPER(TRIM(F7)) -> Kavya Nair | AF7: =PROPER(TRIM(K7)) -> Electronics | AG7: =PROPER(TRIM(J7)) -> West | AH7: =PROPER(TRIM(K7)) -> Electronics | AI7: =IF(OR(LOWER(TRIM(K7))="electronic",LOWER(TRIM(K7))="electronics"),"Electronics",PROPER(TRIM(K7))) -> Electronics | AK7: =IF(COUNTIF($A$2:A7,A7)=1,1,0) -> 1
A8: ORD10010 | B8: C002 | C8: P301 | D8: 25/03/2025 | E8: 27/03/2025 | F8: Priya Patel | G8: Female | H8: 33055 | I8: Mumbai | J8: West | K8: Stationery | L8: Notebook | M8: 6 | N8: 60 | O8: 0 | P8: 360 | Q8: 4 | R8: Card | S8: Neha | T8: PRiya.patel@company.com | U8: 9340540608 | V8: Completed | W8: =IF(OR(Q8<=2,V8="Cancelled"),"Blacklisted",IF(AND(P8>100000,Q8>=4,O8<=10%,V8="Completed"),"Platinum",IF(AND(P8>=50000,Q8>=3,V8="Completed"),"Gold",IF(AND(P8<50000,V8="Completed"),"Silver","")))) -> Silver | X8: =PROPER(TRIM(F8)) -> Priya Patel | Y8: =LEFT(F8,3)&MID(B8,2,3)&LEFT(I8,2) -> Pri002Mu | Z8: =IF(ISNUMBER(SEARCH("@",T8)),LOWER(TRIM(T8)),"invalid email") -> priya.patel@company.com | AA8: =IF(H7="","",IFERROR(DATEDIF(IF(ISNUMBER(H7),H7,DATE(VALUE(RIGHT(H7,4)),VALUE(MID(H7,3,2)),VALUE(LEFT(H7,2)))),TODAY(),"Y"),"")) -> 29 | AB8: =IF(OR(D8="",E8=""),"",IFERROR(DATE(MID(E8,7,4),MID(E8,4,2),LEFT(E8,2))-DATE(MID(D8,7,4),MID(D8,4,2),LEFT(D8,2)),"")) -> 2 | AC8: =IF(E8="","Pending",IF(AB8<=5,"On time","Delayed")) -> On time | AD8: =IF(TRIM(S8)="","Not Assigned",S8) -> Neha | AE8: =PROPER(TRIM(F8)) -> Priya Patel | AF8: =PROPER(TRIM(K8)) -> Stationery | AG8: =PROPER(TRIM(J8)) -> West | AH8: =PROPER(TRIM(K8)) -> Stationery | AI8: =IF(OR(LOWER(TRIM(K8))="electronic",LOWER(TRIM(K8))="electronics"),"Electronics",PROPER(TRIM(K8))) -> Stationery | AK8: =IF(COUNTIF($A$2:A8,A8)=1,1,0) -> 1
A9: ORD10011 | B9: C003 | C9: P202 | D9: 19/09/2025 | E9: 23/09/2025 | F9: Rohit Singh | G9: Male | H9: 30229 | I9: Delhi | J9: North | K9: Home Appliances | L9: Iron | M9: -3 | N9: 2200 | O9: 0 | P9: 35200 | Q9: 2 | R9: Card | S9: Rahul | T9: rohit.singh@company.com | U9: 9521710321 | V9: Pending | W9: =IF(OR(Q9<=2,V9="Cancelled"),"Blacklisted",IF(AND(P9>100000,Q9>=4,O9<=10%,V9="Completed"),"Platinum",IF(AND(P9>=50000,Q9>=3,V9="Completed"),"Gold",IF(AND(P9<50000,V9="Completed"),"Silver","")))) -> Blacklisted | X9: =PROPER(TRIM(F9)) -> Rohit Singh | Y9: =LEFT(F9,3)&MID(B9,2,3)&LEFT(I9,2) -> Roh003De | Z9: =IF(ISNUMBER(SEARCH("@",T9)),LOWER(TRIM(T9)),"invalid email") -> rohit.singh@company.com | AA9: =IF(H8="","",IFERROR(DATEDIF(IF(ISNUMBER(H8),H8,DATE(VALUE(RIGHT(H8,4)),VALUE(MID(H8,3,2)),VALUE(LEFT(H8,2)))),TODAY(),"Y"),"")) -> 36 | AB9: =IF(OR(D9="",E9=""),"",IFERROR(DATE(MID(E9,7,4),MID(E9,4,2),LEFT(E9,2))-DATE(MID(D9,7,4),MID(D9,4,2),LEFT(D9,2)),"")) -> 4 | AC9: =IF(E9="","Pending",IF(AB9<=5,"On time","Delayed")) -> On time | AD9: =IF(TRIM(S9)="","Not Assigned",S9) -> Rahul | AE9: =PROPER(TRIM(F9)) -> Rohit Singh | AF9: =PROPER(TRIM(K9)) -> Home Appliances | AG9: =PROPER(TRIM(J9)) -> North | AH9: =PROPER(TRIM(K9)) -> Home Appliances | AI9: =IF(OR(LOWER(TRIM(K9))="electronic",LOWER(TRIM(K9))="electronics"),"Electronics",PROPER(TRIM(K9))) -> Home Appliances | AK9: =IF(COUNTIF($A$2:A9,A9)=1,1,0) -> 1
A10: ORD10012 | B10: C008 | C10: P201 | D10: 45872 | E10: 15/03/2025 | F10: Kavya Nair | G10: Female | H10: 23/01/1982 | I10: Ahmedabad | J10: West | K10: Home Appliances | L10: Mixer | M10: 10 | N10: 3500 | O10: 5 | P10: 33250 | Q10: 5 | R10: Card | S10: Aisha | T10: kavya.nair@company.com | U10: 9123535241 | V10: Cancelled | W10: =IF(OR(Q10<=2,V10="Cancelled"),"Blacklisted",IF(AND(P10>100000,Q10>=4,O10<=10%,V10="Completed"),"Platinum",IF(AND(P10>=50000,Q10>=3,V10="Completed"),"Gold",IF(AND(P10<50000,V10="Completed"),"Silver","")))) -> Blacklisted | X10: =PROPER(TRIM(F10)) -> Kavya Nair | Y10: =LEFT(F10,3)&MID(B10,2,3)&LEFT(I10,2) -> Kav008Ah | Z10: =IF(ISNUMBER(SEARCH("@",T10)),LOWER(TRIM(T10)),"invalid email") -> kavya.nair@company.com | AA10: =IF(H9="","",IFERROR(DATEDIF(IF(ISNUMBER(H9),H9,DATE(VALUE(RIGHT(H9,4)),VALUE(MID(H9,3,2)),VALUE(LEFT(H9,2)))),TODAY(),"Y"),"")) -> 44 | AB10: =IF(OR(D10="",E10=""),"",IFERROR(DATE(MID(E10,7,4),MID(E10,4,2),LEFT(E10,2))-DATE(MID(D10,7,4),MID(D10,4,2),LEFT(D10,2)),"")) | AC10: =IF(E10="","Pending",IF(AB10<=5,"On time","Delayed")) -> Delayed | AD10: =IF(TRIM(S10)="","Not Assigned",S10) -> Aisha | AE10: =PROPER(TRIM(F10)) -> Kavya Nair | AF10: =PROPER(TRIM(K10)) -> Home Appliances | AG10: =PROPER(TRIM(J10)) -> West | AH10: =PROPER(TRIM(K10)) -> Home Appliances | AI10: =IF(OR(LOWER(TRIM(K10))="electronic",LOWER(TRIM(K10))="electronics"),"Electronics",PROPER(TRIM(K10))) -> Home Appliances | AK10: =IF(COUNTIF($A$2:A10,A10)=1,1,0) -> 1
A11: ORD10013 | B11: C002 | C11: P202 | D11: 45931 | E11: 15/01/2025 | F11: Priya Patel | G11: Female | H11: 33762 | I11: Pune | J11: West | K11: Home Appliances | L11: Iron | M11: 15 | N11: 2200 | O11: 10 | P11: 29700 | Q11: 1 | R11: UPI | S11: Neha | T11: priya.patel@company.com | U11: 9367316892 | V11: Pending | W11: =IF(OR(Q11<=2,V11="Cancelled"),"Blacklisted",IF(AND(P11>100000,Q11>=4,O11<=10%,V11="Completed"),"Platinum",IF(AND(P11>=50000,Q11>=3,V11="Completed"),"Gold",IF(AND(P11<50000,V11="Completed"),"Silver","")))) -> Blacklisted | X11: =PROPER(TRIM(F11)) -> Priya Patel | Y11: =LEFT(F11,3)&MID(B11,2,3)&LEFT(I11,2) -> Pri002Pu | Z11: =IF(ISNUMBER(SEARCH("@",T11)),LOWER(TRIM(T11)),"invalid email") -> priya.patel@company.com | AA11: =IF(H10="","",IFERROR(DATEDIF(IF(ISNUMBER(H10),H10,DATE(VALUE(RIGHT(H10,4)),VALUE(MID(H10,3,2)),VALUE(LEFT(H10,2)))),TODAY(),"Y"),"")) | AB11: =IF(OR(D11="",E11=""),"",IFERROR(DATE(MID(E11,7,4),MID(E11,4,2),LEFT(E11,2))-DATE(MID(D11,7,4),MID(D11,4,2),LEFT(D11,2)),"")) | AC11: =IF(E11="","Pending",IF(AB11<=5,"On time","Delayed")) -> Delayed | AD11: =IF(TRIM(S11)="","Not Assigned",S11) -> Neha | AE11: =PROPER(TRIM(F11)) -> Priya Patel | AF11: =PROPER(TRIM(K11)) -> Home Appliances | AG11: =PROPER(TRIM(J11)) -> West | AH11: =PROPER(TRIM(K11)) -> Home Appliances | AI11: =IF(OR(LOWER(TRIM(K11))="electronic",LOWER(TRIM(K11))="electronics"),"Electronics",PROPER(TRIM(K11))) -> Home Appliances | AK11: =IF(COUNTIF($A$2:A11,A11)=1,1,0) -> 1
A12: ORD10014 | B12: C003 | C12: P202 | D12: 45903 | E12: 13/03/2025 | F12: Rohit Singh | G12: Male | H12: 19/03/2002 | I12: Mumbai | J12: West | K12: Home Appliances | L12: Iron | M12: 17 | N12: 2200 | O12: 5 | P12: 35530 | Q12: 1 | R12: Cash | S12: Karan | T12: rOhit.singh@company.com | U12: 9778489803 | V12: Completed | W12: =IF(OR(Q12<=2,V12="Cancelled"),"Blacklisted",IF(AND(P12>100000,Q12>=4,O12<=10%,V12="Completed"),"Platinum",IF(AND(P12>=50000,Q12>=3,V12="Completed"),"Gold",IF(AND(P12<50000,V12="Completed"),"Silver","")))) -> Blacklisted | X12: =PROPER(TRIM(F12)) -> Rohit Singh | Y12: =LEFT(F12,3)&MID(B12,2,3)&LEFT(I12,2) -> Roh003Mu | Z12: =IF(ISNUMBER(SEARCH("@",T12)),LOWER(TRIM(T12)),"invalid email") -> rohit.singh@company.com | AA12: =IF(H11="","",IFERROR(DATEDIF(IF(ISNUMBER(H11),H11,DATE(VALUE(RIGHT(H11,4)),VALUE(MID(H11,3,2)),VALUE(LEFT(H11,2)))),TODAY(),"Y"),"")) -> 34 | AB12: =IF(OR(D12="",E12=""),"",IFERROR(DATE(MID(E12,7,4),MID(E12,4,2),LEFT(E12,2))-DATE(MID(D12,7,4),MID(D12,4,2),LEFT(D12,2)),"")) | AC12: =IF(E12="","Pending",IF(AB12<=5,"On time","Delayed")) -> Delayed | AD12: =IF(TRIM(S12)="","Not Assigned",S12) -> Karan | AE12: =PROPER(TRIM(F12)) -> Rohit Singh | AF12: =PROPER(TRIM(K12)) -> Home Appliances | AG12: =PROPER(TRIM(J12)) -> West | AH12: =PROPER(TRIM(K12)) -> Home Appliances | AI12: =IF(OR(LOWER(TRIM(K12))="electronic",LOWER(TRIM(K12))="electronics"),"Electronics",PROPER(TRIM(K12))) -> Home Appliances | AK12: =IF(COUNTIF($A$2:A12,A12)=1,1,0) -> 1
A13: ORD10015 | B13: C008 | C13: P201 | D13: 26/07/2025 | E13: 45846 | F13: Kavya Nair | G13: Female | H13: 17/01/2001 | I13: Mumbai | J13: West | K13: Home Appliances | L13: Mixer | M13: 15 | N13: 3500 | O13: 15 | P13: 44625 | Q13: 2 | R13: Cash | S13: Neha | T13: kavya.nair@company.com | U13: 9582960180 | V13: Cancelled | W13: =IF(OR(Q13<=2,V13="Cancelled"),"Blacklisted",IF(AND(P13>100000,Q13>=4,O13<=10%,V13="Completed"),"Platinum",IF(AND(P13>=50000,Q13>=3,V13="Completed"),"Gold",IF(AND(P13<50000,V13="Completed"),"Silver","")))) -> Blacklisted | X13: =PROPER(TRIM(F13)) -> Kavya Nair | Y13: =LEFT(F13,3)&MID(B13,2,3)&LEFT(I13,2) -> Kav008Mu | Z13: =IF(ISNUMBER(SEARCH("@",T13)),LOWER(TRIM(T13)),"invalid email") -> kavya.nair@company.com | AA13: =IF(H12="","",IFERROR(DATEDIF(IF(ISNUMBER(H12),H12,DATE(VALUE(RIGHT(H12,4)),VALUE(MID(H12,3,2)),VALUE(LEFT(H12,2)))),TODAY(),"Y"),"")) | AB13: =IF(OR(D13="",E13=""),"",IFERROR(DATE(MID(E13,7,4),MID(E13,4,2),LEFT(E13,2))-DATE(MID(D13,7,4),MID(D13,4,2),LEFT(D13,2)),"")) | AC13: =IF(E13="","Pending",IF(AB13<=5,"On time","Delayed")) -> Delayed | AD13: =IF(TRIM(S13)="","Not Assigned",S13) -> Neha | AE13: =PROPER(TRIM(F13)) -> Kavya Nair | AF13: =PROPER(TRIM(K13)) -> Home Appliances | AG13: =PROPER(TRIM(J13)) -> West | AH13: =PROPER(TRIM(K13)) -> Home Appliances | AI13: =IF(OR(LOWER(TRIM(K13))="electronic",LOWER(TRIM(K13))="electronics"),"Electronics",PROPER(TRIM(K13))) -> Home Appliances | AK13: =IF(COUNTIF($A$2:A13,A13)=1,1,0) -> 1
A14: ORD10016 | B14: C010 | C14: P103 | D14: 46238 | E14: 46330 | F14: Pooja Shah | G14: Female | H14: 37564 | I14: Hyderabad | J14: South | K14: Electronics | L14: Keyboard | M14: 3 | N14: 1200 | O14: 5 | P14: 3420 | Q14: 5 | R14: UPI | S14: Ritika | T14: pooja.shahcompany.com | U14: 9611394005 | V14: Completed | W14: =IF(OR(Q14<=2,V14="Cancelled"),"Blacklisted",IF(AND(P14>100000,Q14>=4,O14<=10%,V14="Completed"),"Platinum",IF(AND(P14>=50000,Q14>=3,V14="Completed"),"Gold",IF(AND(P14<50000,V14="Completed"),"Silver","")))) -> Silver | X14: =PROPER(TRIM(F14)) -> Pooja Shah | Y14: =LEFT(F14,3)&MID(B14,2,3)&LEFT(I14,2) -> Poo010Hy | Z14: =IF(ISNUMBER(SEARCH("@",T14)),LOWER(TRIM(T14)),"invalid email") -> invalid email | AA14: =IF(H13="","",IFERROR(DATEDIF(IF(ISNUMBER(H13),H13,DATE(VALUE(RIGHT(H13,4)),VALUE(MID(H13,3,2)),VALUE(LEFT(H13,2)))),TODAY(),"Y"),"")) | AB14: =IF(OR(D14="",E14=""),"",IFERROR(DATE(MID(E14,7,4),MID(E14,4,2),LEFT(E14,2))-DATE(MID(D14,7,4),MID(D14,4,2),LEFT(D14,2)),"")) | AC14: =IF(E14="","Pending",IF(AB14<=5,"On time","Delayed")) -> Delayed | AD14: =IF(TRIM(S14)="","Not Assigned",S14) -> Ritika | AE14: =PROPER(TRIM(F14)) -> Pooja Shah | AF14: =PROPER(TRIM(K14)) -> Electronics | AG14: =PROPER(TRIM(J14)) -> South | AH14: =PROPER(TRIM(K14)) -> Electronics | AI14: =IF(OR(LOWER(TRIM(K14))="electronic",LOWER(TRIM(K14))="electronics"),"Electronics",PROPER(TRIM(K14))) -> Electronics | AK14: =IF(COUNTIF($A$2:A14,A14)=1,1,0) -> 1
A15: ORD10017 | B15: C004 | C15: P203 | D15: 22/02/2026 | E15: 46084 | F15: Amit Sharma | G15: Female | H15: 16/01/2002 | I15: Pune | J15: West | K15: Home Appliances | L15: Microwave | M15: 13 | N15: 8500 | O15: 20 | P15: 88400 | Q15: 4 | R15: Card | S15: Rahul | T15: anita.gupta@company.com | U15: 9692599404 | V15: Pending | W15: =IF(OR(Q15<=2,V15="Cancelled"),"Blacklisted",IF(AND(P15>100000,Q15>=4,O15<=10%,V15="Completed"),"Platinum",IF(AND(P15>=50000,Q15>=3,V15="Completed"),"Gold",IF(AND(P15<50000,V15="Completed"),"Silver","")))) | X15: =PROPER(TRIM(F15)) -> Amit Sharma | Y15: =LEFT(F15,3)&MID(B15,2,3)&LEFT(I15,2) -> Ami004Pu | Z15: =IF(ISNUMBER(SEARCH("@",T15)),LOWER(TRIM(T15)),"invalid email") -> anita.gupta@company.com | AA15: =IF(H14="","",IFERROR(DATEDIF(IF(ISNUMBER(H14),H14,DATE(VALUE(RIGHT(H14,4)),VALUE(MID(H14,3,2)),VALUE(LEFT(H14,2)))),TODAY(),"Y"),"")) -> 23 | AB15: =IF(OR(D15="",E15=""),"",IFERROR(DATE(MID(E15,7,4),MID(E15,4,2),LEFT(E15,2))-DATE(MID(D15,7,4),MID(D15,4,2),LEFT(D15,2)),"")) | AC15: =IF(E15="","Pending",IF(AB15<=5,"On time","Delayed")) -> Delayed | AD15: =IF(TRIM(S15)="","Not Assigned",S15) -> Rahul | AE15: =PROPER(TRIM(F15)) -> Amit Sharma | AF15: =PROPER(TRIM(K15)) -> Home Appliances | AG15: =PROPER(TRIM(J15)) -> West | AH15: =PROPER(TRIM(K15)) -> Home Appliances | AI15: =IF(OR(LOWER(TRIM(K15))="electronic",LOWER(TRIM(K15))="electronics"),"Electronics",PROPER(TRIM(K15))) -> Home Appliances | AK15: =IF(COUNTIF($A$2:A15,A15)=1,1,0) -> 1
A16: ORD10018 | B16: C007 | C16: P203 | D16: 28/02/2026 | E16: 46145 | F16: Arjun Rao | G16: Male | H16: 32761 | I16: Ahmedabad | J16: West | K16: Home Appliances | L16: Microwave | M16: 4 | N16: 8500 | O16: 20 | P16: 27200 | Q16: 5 | R16: Card | S16: Aisha | T16: arjun.rao@company.com | U16: 9426119622 | V16: Pending | W16: =IF(OR(Q16<=2,V16="Cancelled"),"Blacklisted",IF(AND(P16>100000,Q16>=4,O16<=10%,V16="Completed"),"Platinum",IF(AND(P16>=50000,Q16>=3,V16="Completed"),"Gold",IF(AND(P16<50000,V16="Completed"),"Silver","")))) | X16: =PROPER(TRIM(F16)) -> Arjun Rao | Y16: =LEFT(F16,3)&MID(B16,2,3)&LEFT(I16,2) -> Arj007Ah | Z16: =IF(ISNUMBER(SEARCH("@",T16)),LOWER(TRIM(T16)),"invalid email") -> arjun.rao@company.com | AA16: =IF(H15="","",IFERROR(DATEDIF(IF(ISNUMBER(H15),H15,DATE(VALUE(RIGHT(H15,4)),VALUE(MID(H15,3,2)),VALUE(LEFT(H15,2)))),TODAY(),"Y"),"")) | AB16: =IF(OR(D16="",E16=""),"",IFERROR(DATE(MID(E16,7,4),MID(E16,4,2),LEFT(E16,2))-DATE(MID(D16,7,4),MID(D16,4,2),LEFT(D16,2)),"")) | AC16: =IF(E16="","Pending",IF(AB16<=5,"On time","Delayed")) -> Delayed | AD16: =IF(TRIM(S16)="","Not Assigned",S16) -> Aisha | AE16: =PROPER(TRIM(F16)) -> Arjun Rao | AF16: =PROPER(TRIM(K16)) -> Home Appliances | AG16: =PROPER(TRIM(J16)) -> West | AH16: =PROPER(TRIM(K16)) -> Home Appliances | AI16: =IF(OR(LOWER(TRIM(K16))="electronic",LOWER(TRIM(K16))="electronics"),"Electronics",PROPER(TRIM(K16))) -> Home Appliances | AK16: =IF(COUNTIF($A$2:A16,A16)=1,1,0) -> 1
A17: ORD10019 | B17: C007 | C17: P102 | D17: 45669 | E17: 45759 | F17: Arjun Rao | G17: Male | H17: 28/10/1991 | I17: Mumbai | J17: West | K17: Electronics | L17: Mouse | M17: 9 | N17: 700 | O17: 5 | P17: 5985 | Q17: 3 | R17: UPI | S17: Ritika | T17: arjun.Rao@company.com | U17: 9184436009 | V17: Pending | W17: =IF(OR(Q17<=2,V17="Cancelled"),"Blacklisted",IF(AND(P17>100000,Q17>=4,O17<=10%,V17="Completed"),"Platinum",IF(AND(P17>=50000,Q17>=3,V17="Completed"),"Gold",IF(AND(P17<50000,V17="Completed"),"Silver","")))) | X17: =PROPER(TRIM(F17)) -> Arjun Rao | Y17: =LEFT(F17,3)&MID(B17,2,3)&LEFT(I17,2) -> Arj007Mu | Z17: =IF(ISNUMBER(SEARCH("@",T17)),LOWER(TRIM(T17)),"invalid email") -> arjun.rao@company.com | AA17: =IF(H16="","",IFERROR(DATEDIF(IF(ISNUMBER(H16),H16,DATE(VALUE(RIGHT(H16,4)),VALUE(MID(H16,3,2)),VALUE(LEFT(H16,2)))),TODAY(),"Y"),"")) -> 37 | AB17: =IF(OR(D17="",E17=""),"",IFERROR(DATE(MID(E17,7,4),MID(E17,4,2),LEFT(E17,2))-DATE(MID(D17,7,4),MID(D17,4,2),LEFT(D17,2)),"")) | AC17: =IF(E17="","Pending",IF(AB17<=5,"On time","Delayed")) -> Delayed | AD17: =IF(TRIM(S17)="","Not Assigned",S17) -> Ritika | AE17: =PROPER(TRIM(F17)) -> Arjun Rao | AF17: =PROPER(TRIM(K17)) -> Electronics | AG17: =PROPER(TRIM(J17)) -> West | AH17: =PROPER(TRIM(K17)) -> Electronics | AI17: =IF(OR(LOWER(TRIM(K17))="electronic",LOWER(TRIM(K17))="electronics"),"Electronics",PROPER(TRIM(K17))) -> Electronics | AK17: =IF(COUNTIF($A$2:A17,A17)=1,1,0) -> 1
A18: ORD10020 | B18: C008 | C18: P101 | D18: 25/06/2025 | E18: 45723 | F18: Kavya Nair | G18: Female | H18: 32876 | I18: Ahmedabad | J18: West | K18: Electronics | L18: Laptop | M18: 8 | N18: 55000 | O18: 20 | P18: 352000 | Q18: 1 | R18: Cash | S18: Karan | T18: kavya.nair@company.com | U18: 9263774934 | V18: Completed | W18: =IF(OR(Q18<=2,V18="Cancelled"),"Blacklisted",IF(AND(P18>100000,Q18>=4,O18<=10%,V18="Completed"),"Platinum",IF(AND(P18>=50000,Q18>=3,V18="Completed"),"Gold",IF(AND(P18<50000,V18="Completed"),"Silver","")))) -> Blacklisted | X18: =PROPER(TRIM(F18)) -> Kavya Nair | Y18: =LEFT(F18,3)&MID(B18,2,3)&LEFT(I18,2) -> Kav008Ah | Z18: =IF(ISNUMBER(SEARCH("@",T18)),LOWER(TRIM(T18)),"invalid email") -> kavya.nair@company.com | AA18: =IF(H17="","",IFERROR(DATEDIF(IF(ISNUMBER(H17),H17,DATE(VALUE(RIGHT(H17,4)),VALUE(MID(H17,3,2)),VALUE(LEFT(H17,2)))),TODAY(),"Y"),"")) | AB18: =IF(OR(D18="",E18=""),"",IFERROR(DATE(MID(E18,7,4),MID(E18,4,2),LEFT(E18,2))-DATE(MID(D18,7,4),MID(D18,4,2),LEFT(D18,2)),"")) | AC18: =IF(E18="","Pending",IF(AB18<=5,"On time","Delayed")) -> Delayed | AD18: =IF(TRIM(S18)="","Not Assigned",S18) -> Karan | AE18: =PROPER(TRIM(F18)) -> Kavya Nair | AF18: =PROPER(TRIM(K18)) -> Electronics | AG18: =PROPER(TRIM(J18)) -> West | AH18: =PROPER(TRIM(K18)) -> Electronics | AI18: =IF(OR(LOWER(TRIM(K18))="electronic",LOWER(TRIM(K18))="electronics"),"Electronics",PROPER(TRIM(K18))) -> Electronics | AK18: =IF(COUNTIF($A$2:A18,A18)=1,1,0) -> 1
A19: ORD10021 | B19: C003 | C19: P102 | D19: 26/04/2025 | E19: 45782 | F19: Rohit Singh | G19: Male | H19: 18/07/2002 | I19: Delhi | J19: North | K19: Electronics | L19: Mouse | M19: 10 | N19: 700 | O19: 20 | P19: 5600 | Q19: 4 | R19: Card | S19: Aisha | T19: rohit.singh@company.com | U19: 9473159572 | V19: Cancelled | W19: =IF(OR(Q19<=2,V19="Cancelled"),"Blacklisted",IF(AND(P19>100000,Q19>=4,O19<=10%,V19="Completed"),"Platinum",IF(AND(P19>=50000,Q19>=3,V19="Completed"),"Gold",IF(AND(P19<50000,V19="Completed"),"Silver","")))) -> Blacklisted | X19: =PROPER(TRIM(F19)) -> Rohit Singh | Y19: =LEFT(F19,3)&MID(B19,2,3)&LEFT(I19,2) -> Roh003De | Z19: =IF(ISNUMBER(SEARCH("@",T19)),LOWER(TRIM(T19)),"invalid email") -> rohit.singh@company.com | AA19: =IF(H18="","",IFERROR(DATEDIF(IF(ISNUMBER(H18),H18,DATE(VALUE(RIGHT(H18,4)),VALUE(MID(H18,3,2)),VALUE(LEFT(H18,2)))),TODAY(),"Y"),"")) -> 36 | AB19: =IF(OR(D19="",E19=""),"",IFERROR(DATE(MID(E19,7,4),MID(E19,4,2),LEFT(E19,2))-DATE(MID(D19,7,4),MID(D19,4,2),LEFT(D19,2)),"")) | AC19: =IF(E19="","Pending",IF(AB19<=5,"On time","Delayed")) -> Delayed | AD19: =IF(TRIM(S19)="","Not Assigned",S19) -> Aisha | AE19: =PROPER(TRIM(F19)) -> Rohit Singh | AF19: =PROPER(TRIM(K19)) -> Electronics | AG19: =PROPER(TRIM(J19)) -> North | AH19: =PROPER(TRIM(K19)) -> Electronics | AI19: =IF(OR(LOWER(TRIM(K19))="electronic",LOWER(TRIM(K19))="electronics"),"Electronics",PROPER(TRIM(K19))) -> Electronics | AK19: =IF(COUNTIF($A$2:A19,A19)=1,1,0) -> 1
A20: ORD10022 | B20: C008 | C20: P201 | D20: 45717 | E20: 45870 | F20: Kavya Nair | G20: Female | H20: 15/12/2004 | I20: Bengaluru | J20: South | K20: Home Appliances | L20: Mixer | M20: 1 | N20: 3500 | O20: 5 | P20: 3325 | Q20: 3 | R20: UPI | S20: Neha | T20: kavya.nair@company.com | U20: 9660493688 | V20: Cancelled | W20: =IF(OR(Q20<=2,V20="Cancelled"),"Blacklisted",IF(AND(P20>100000,Q20>=4,O20<=10%,V20="Completed"),"Platinum",IF(AND(P20>=50000,Q20>=3,V20="Completed"),"Gold",IF(AND(P20<50000,V20="Completed"),"Silver","")))) -> Blacklisted | X20: =PROPER(TRIM(F20)) -> Kavya Nair | Y20: =LEFT(F20,3)&MID(B20,2,3)&LEFT(I20,2) -> Kav008Be | Z20: =IF(ISNUMBER(SEARCH("@",T20)),LOWER(TRIM(T20)),"invalid email") -> kavya.nair@company.com | AA20: =IF(H19="","",IFERROR(DATEDIF(IF(ISNUMBER(H19),H19,DATE(VALUE(RIGHT(H19,4)),VALUE(MID(H19,3,2)),VALUE(LEFT(H19,2)))),TODAY(),"Y"),"")) | AB20: =IF(OR(D20="",E20=""),"",IFERROR(DATE(MID(E20,7,4),MID(E20,4,2),LEFT(E20,2))-DATE(MID(D20,7,4),MID(D20,4,2),LEFT(D20,2)),"")) | AC20: =IF(E20="","Pending",IF(AB20<=5,"On time","Delayed")) -> Delayed | AD20: =IF(TRIM(S20)="","Not Assigned",S20) -> Neha | AE20: =PROPER(TRIM(F20)) -> Kavya Nair | AF20: =PROPER(TRIM(K20)) -> Home Appliances | AG20: =PROPER(TRIM(J20)) -> South | AH20: =PROPER(TRIM(K20)) -> Home Appliances | AI20: =IF(OR(LOWER(TRIM(K20))="electronic",LOWER(TRIM(K20))="electronics"),"Electronics",PROPER(TRIM(K20))) -> Home Appliances | AK20: =IF(COUNTIF($A$2:A20,A20)=1,1,0) -> 1
A21: ORD10023 | B21: C002 | C21: P102 | D21: 19/04/2025 | E21: 30/04/2025 | F21: Priya Patel | G21: Female | H21: 30779 | I21: Jaipur | J21: North | K21: Electronics | L21: Mouse | M21: 19 | N21: 700 | O21: 15 | P21: 11305 | Q21: 3 | R21: NetBanking | S21: Karan | T21: priya.patel@company.com | U21: 9513325819 | V21: Pending | W21: =IF(OR(Q21<=2,V21="Cancelled"),"Blacklisted",IF(AND(P21>100000,Q21>=4,O21<=10%,V21="Completed"),"Platinum",IF(AND(P21>=50000,Q21>=3,V21="Completed"),"Gold",IF(AND(P21<50000,V21="Completed"),"Silver","")))) | X21: =PROPER(TRIM(F21)) -> Priya Patel | Y21: =LEFT(F21,3)&MID(B21,2,3)&LEFT(I21,2) -> Pri002Ja | Z21: =IF(ISNUMBER(SEARCH("@",T21)),LOWER(TRIM(T21)),"invalid email") -> priya.patel@company.com | AA21: =IF(H20="","",IFERROR(DATEDIF(IF(ISNUMBER(H20),H20,DATE(VALUE(RIGHT(H20,4)),VALUE(MID(H20,3,2)),VALUE(LEFT(H20,2)))),TODAY(),"Y"),"")) | AB21: =IF(OR(D21="",E21=""),"",IFERROR(DATE(MID(E21,7,4),MID(E21,4,2),LEFT(E21,2))-DATE(MID(D21,7,4),MID(D21,4,2),LEFT(D21,2)),"")) -> 11 | AC21: =IF(E21="","Pending",IF(AB21<=5,"On time","Delayed")) -> Delayed | AD21: =IF(TRIM(S21)="","Not Assigned",S21) -> Karan | AE21: =PROPER(TRIM(F21)) -> Priya Patel | AF21: =PROPER(TRIM(K21)) -> Electronics | AG21: =PROPER(TRIM(J21)) -> North | AH21: =PROPER(TRIM(K21)) -> Electronics | AI21: =IF(OR(LOWER(TRIM(K21))="electronic",LOWER(TRIM(K21))="electronics"),"Electronics",PROPER(TRIM(K21))) -> Electronics | AK21: =IF(COUNTIF($A$2:A21,A21)=1,1,0) -> 1
A22: ORD10024 | B22: C009 | C22: P101 | D22: 22/12/2025 | E22: 46023 | F22: Mohit Verma | G22: Male | H22: 25/02/1978 | I22: Bengaluru | J22: South | K22: Electronics | L22: Laptop | M22: 12 | N22: 55000 | O22: 0 | P22: 660000 | Q22: 1 | R22: Card | S22: Rahul | T22: mohit.verma@company.com | U22: 9641063242 | V22: Pending | W22: =IF(OR(Q22<=2,V22="Cancelled"),"Blacklisted",IF(AND(P22>100000,Q22>=4,O22<=10%,V22="Completed"),"Platinum",IF(AND(P22>=50000,Q22>=3,V22="Completed"),"Gold",IF(AND(P22<50000,V22="Completed"),"Silver","")))) -> Blacklisted | X22: =PROPER(TRIM(F22)) -> Mohit Verma | Y22: =LEFT(F22,3)&MID(B22,2,3)&LEFT(I22,2) -> Moh009Be | Z22: =IF(ISNUMBER(SEARCH("@",T22)),LOWER(TRIM(T22)),"invalid email") -> mohit.verma@company.com | AA22: =IF(H21="","",IFERROR(DATEDIF(IF(ISNUMBER(H21),H21,DATE(VALUE(RIGHT(H21,4)),VALUE(MID(H21,3,2)),VALUE(LEFT(H21,2)))),TODAY(),"Y"),"")) -> 42 | AB22: =IF(OR(D22="",E22=""),"",IFERROR(DATE(MID(E22,7,4),MID(E22,4,2),LEFT(E22,2))-DATE(MID(D22,7,4),MID(D22,4,2),LEFT(D22,2)),"")) | AC22: =IF(E22="","Pending",IF(AB22<=5,"On time","Delayed")) -> Delayed | AD22: =IF(TRIM(S22)="","Not Assigned",S22) -> Rahul | AE22: =PROPER(TRIM(F22)) -> Mohit Verma | AF22: =PROPER(TRIM(K22)) -> Electronics | AG22: =PROPER(TRIM(J22)) -> South | AH22: =PROPER(TRIM(K22)) -> Electronics | AI22: =IF(OR(LOWER(TRIM(K22))="electronic",LOWER(TRIM(K22))="electronics"),"Electronics",PROPER(TRIM(K22))) -> Electronics | AK22: =IF(COUNTIF($A$2:A22,A22)=1,1,0) -> 1
A23: ORD10025 | B23: C005 | C23: P302 | D23: 46269 | E23: 20/04/2026 | F23: Vikas Mehta | G23: Male | H23: 33305 | I23: Mumbai | J23: West | K23: Stationery | L23: Pen | M23: 1 | N23: 20 | O23: 5 | P23: 19 | Q23: 5 | R23: Card | S23: Ritika | T23: vikas.mehta@company.com | U23: 9277372518 | V23: Cancelled | W23: =IF(OR(Q23<=2,V23="Cancelled"),"Blacklisted",IF(AND(P23>100000,Q23>=4,O23<=10%,V23="Completed"),"Platinum",IF(AND(P23>=50000,Q23>=3,V23="Completed"),"Gold",IF(AND(P23<50000,V23="Completed"),"Silver","")))) -> Blacklisted | X23: =PROPER(TRIM(F23)) -> Vikas Mehta | Y23: =LEFT(F23,3)&MID(B23,2,3)&LEFT(I23,2) -> Vik005Mu | Z23: =IF(ISNUMBER(SEARCH("@",T23)),LOWER(TRIM(T23)),"invalid email") -> vikas.mehta@company.com | AA23: =IF(H22="","",IFERROR(DATEDIF(IF(ISNUMBER(H22),H22,DATE(VALUE(RIGHT(H22,4)),VALUE(MID(H22,3,2)),VALUE(LEFT(H22,2)))),TODAY(),"Y"),"")) | AB23: =IF(OR(D23="",E23=""),"",IFERROR(DATE(MID(E23,7,4),MID(E23,4,2),LEFT(E23,2))-DATE(MID(D23,7,4),MID(D23,4,2),LEFT(D23,2)),"")) | AC23: =IF(E23="","Pending",IF(AB23<=5,"On time","Delayed")) -> Delayed | AD23: =IF(TRIM(S23)="","Not Assigned",S23) -> Ritika | AE23: =PROPER(TRIM(F23)) -> Vikas Mehta | AF23: =PROPER(TRIM(K23)) -> Stationery | AG23: =PROPER(TRIM(J23)) -> West | AH23: =PROPER(TRIM(K23)) -> Stationery | AI23: =IF(OR(LOWER(TRIM(K23))="electronic",LOWER(TRIM(K23))="electronics"),"Electronics",PROPER(TRIM(K23))) -> Stationery | AK23: =IF(COUNTIF($A$2:A23,A23)=1,1,0) -> 1
A24: ORD10026 | B24: C007 | C24: P302 | D24: 24/06/2025 | E24: 45695 | F24: Arjun Rao | G24: Male | H24: 28441 | I24: Mumbai | J24: West | K24: Stationery | L24: Pen | M24: 2 | N24: 20 | O24: 15 | P24: 34 | Q24: 1 | R24: UPI | S24: Ritika | T24: arjun.rao@company.com | U24: 9193154372 | V24: Pending | W24: =IF(OR(Q24<=2,V24="Cancelled"),"Blacklisted",IF(AND(P24>100000,Q24>=4,O24<=10%,V24="Completed"),"Platinum",IF(AND(P24>=50000,Q24>=3,V24="Completed"),"Gold",IF(AND(P24<50000,V24="Completed"),"Silver","")))) -> Blacklisted | X24: =PROPER(TRIM(F24)) -> Arjun Rao | Y24: =LEFT(F24,3)&MID(B24,2,3)&LEFT(I24,2) -> Arj007Mu | Z24: =IF(ISNUMBER(SEARCH("@",T24)),LOWER(TRIM(T24)),"invalid email") -> arjun.rao@company.com | AA24: =IF(H23="","",IFERROR(DATEDIF(IF(ISNUMBER(H23),H23,DATE(VALUE(RIGHT(H23,4)),VALUE(MID(H23,3,2)),VALUE(LEFT(H23,2)))),TODAY(),"Y"),"")) -> 35 | AB24: =IF(OR(D24="",E24=""),"",IFERROR(DATE(MID(E24,7,4),MID(E24,4,2),LEFT(E24,2))-DATE(MID(D24,7,4),MID(D24,4,2),LEFT(D24,2)),"")) | AC24: =IF(E24="","Pending",IF(AB24<=5,"On time","Delayed")) -> Delayed | AD24: =IF(TRIM(S24)="","Not Assigned",S24) -> Ritika | AE24: =PROPER(TRIM(F24)) -> Arjun Rao | AF24: =PROPER(TRIM(K24)) -> Stationery | AG24: =PROPER(TRIM(J24)) -> West | AH24: =PROPER(TRIM(K24)) -> Stationery | AI24: =IF(OR(LOWER(TRIM(K24))="electronic",LOWER(TRIM(K24))="electronics"),"Electronics",PROPER(TRIM(K24))) -> Stationery | AK24: =IF(COUNTIF($A$2:A24,A24)=1,1,0) -> 1
A25: ORD10027 | B25: C009 | C25: P201 | D25: 22/05/2025 | E25: 25/05/2025 | F25: Mohit Verma | G25: Male | H25: 33818 | I25: Ahmedabad | J25: West | K25: Home Appliances | L25: Mixer | M25: 12 | N25: 3500 | O25: 15 | P25: 35700 | Q25: 4 | R25: Cash | S25: Rahul | T25: mohit.verma@company.com | U25: 9400073244 | V25: Cancelled | W25: =IF(OR(Q25<=2,V25="Cancelled"),"Blacklisted",IF(AND(P25>100000,Q25>=4,O25<=10%,V25="Completed"),"Platinum",IF(AND(P25>=50000,Q25>=3,V25="Completed"),"Gold",IF(AND(P25<50000,V25="Completed"),"Silver","")))) -> Blacklisted | X25: =PROPER(TRIM(F25)) -> Mohit Verma | Y25: =LEFT(F25,3)&MID(B25,2,3)&LEFT(I25,2) -> Moh009Ah | Z25: =IF(ISNUMBER(SEARCH("@",T25)),LOWER(TRIM(T25)),"invalid email") -> mohit.verma@company.com | AA25: =IF(H24="","",IFERROR(DATEDIF(IF(ISNUMBER(H24),H24,DATE(VALUE(RIGHT(H24,4)),VALUE(MID(H24,3,2)),VALUE(LEFT(H24,2)))),TODAY(),"Y"),"")) -> 48 | AB25: =IF(OR(D25="",E25=""),"",IFERROR(DATE(MID(E25,7,4),MID(E25,4,2),LEFT(E25,2))-DATE(MID(D25,7,4),MID(D25,4,2),LEFT(D25,2)),"")) -> 3 | AC25: =IF(E25="","Pending",IF(AB25<=5,"On time","Delayed")) -> On time | AD25: =IF(TRIM(S25)="","Not Assigned",S25) -> Rahul | AE25: =PROPER(TRIM(F25)) -> Mohit Verma | AF25: =PROPER(TRIM(K25)) -> Home Appliances | AG25: =PROPER(TRIM(J25)) -> West | AH25: =PROPER(TRIM(K25)) -> Home Appliances | AI25: =IF(OR(LOWER(TRIM(K25))="electronic",LOWER(TRIM(K25))="electronics"),"Electronics",PROPER(TRIM(K25))) -> Home Appliances | AK25: =IF(COUNTIF($A$2:A25,A25)=1,1,0) -> 1
A26: ORD10028 | B26: C008 | C26: P103 | D26: 13/03/2026 | E26: 20/03/2026 | F26: Kavya Nair | G26: Female | H26: 38113 | I26: Ahmedabad | J26: West | K26: Electronics | L26: Keyboard | M26: 11 | N26: 1200 | O26: 0 | P26: 13200 | Q26: 2 | R26: UPI | S26: Karan | T26: kavya.nair@company.com | U26: 9771556720 | V26: Completed | W26: =IF(OR(Q26<=2,V26="Cancelled"),"Blacklisted",IF(AND(P26>100000,Q26>=4,O26<=10%,V26="Completed"),"Platinum",IF(AND(P26>=50000,Q26>=3,V26="Completed"),"Gold",IF(AND(P26<50000,V26="Completed"),"Silver","")))) -> Blacklisted | X26: =PROPER(TRIM(F26)) -> Kavya Nair | Y26: =LEFT(F26,3)&MID(B26,2,3)&LEFT(I26,2) -> Kav008Ah | Z26: =IF(ISNUMBER(SEARCH("@",T26)),LOWER(TRIM(T26)),"invalid email") -> kavya.nair@company.com | AA26: =IF(H25="","",IFERROR(DATEDIF(IF(ISNUMBER(H25),H25,DATE(VALUE(RIGHT(H25,4)),VALUE(MID(H25,3,2)),VALUE(LEFT(H25,2)))),TODAY(),"Y"),"")) -> 34 | AB26: =IF(OR(D26="",E26=""),"",IFERROR(DATE(MID(E26,7,4),MID(E26,4,2),LEFT(E26,2))-DATE(MID(D26,7,4),MID(D26,4,2),LEFT(D26,2)),"")) -> 7 | AC26: =IF(E26="","Pending",IF(AB26<=5,"On time","Delayed")) -> Delayed | AD26: =IF(TRIM(S26)="","Not Assigned",S26) -> Karan | AE26: =PROPER(TRIM(F26)) -> Kavya Nair | AF26: =PROPER(TRIM(K26)) -> Electronics | AG26: =PROPER(TRIM(J26)) -> West | AH26: =PROPER(TRIM(K26)) -> Electronics | AI26: =IF(OR(LOWER(TRIM(K26))="electronic",LOWER(TRIM(K26))="electronics"),"Electronics",PROPER(TRIM(K26))) -> Electronics | AK26: =IF(COUNTIF($A$2:A26,A26)=1,1,0) -> 1
A27: ORD10029 | B27: C003 | C27: P203 | D27: 45878 | E27: 20/09/2025 | F27: Rohit Singh | G27: Male | H27: 37203 | I27: Pune | J27: West | K27: Home Appliances | L27: Microwave | M27: 6 | N27: 8500 | O27: 65 | P27: 51000 | Q27: 1 | R27: Card | S27: Aisha | T27: rohit.singh@company.com | U27: 9127480734 | V27: Completed | W27: =IF(OR(Q27<=2,V27="Cancelled"),"Blacklisted",IF(AND(P27>100000,Q27>=4,O27<=10%,V27="Completed"),"Platinum",IF(AND(P27>=50000,Q27>=3,V27="Completed"),"Gold",IF(AND(P27<50000,V27="Completed"),"Silver","")))) -> Blacklisted | X27: =PROPER(TRIM(F27)) -> Rohit Singh | Y27: =LEFT(F27,3)&MID(B27,2,3)&LEFT(I27,2) -> Roh003Pu | Z27: =IF(ISNUMBER(SEARCH("@",T27)),LOWER(TRIM(T27)),"invalid email") -> rohit.singh@company.com | AA27: =IF(H26="","",IFERROR(DATEDIF(IF(ISNUMBER(H26),H26,DATE(VALUE(RIGHT(H26,4)),VALUE(MID(H26,3,2)),VALUE(LEFT(H26,2)))),TODAY(),"Y"),"")) -> 22 | AB27: =IF(OR(D27="",E27=""),"",IFERROR(DATE(MID(E27,7,4),MID(E27,4,2),LEFT(E27,2))-DATE(MID(D27,7,4),MID(D27,4,2),LEFT(D27,2)),"")) | AC27: =IF(E27="","Pending",IF(AB27<=5,"On time","Delayed")) -> Delayed | AD27: =IF(TRIM(S27)="","Not Assigned",S27) -> Aisha | AE27: =PROPER(TRIM(F27)) -> Rohit Singh | AF27: =PROPER(TRIM(K27)) -> Home Appliances | AG27: =PROPER(TRIM(J27)) -> West | AH27: =PROPER(TRIM(K27)) -> Home Appliances | AI27: =IF(OR(LOWER(TRIM(K27))="electronic",LOWER(TRIM(K27))="electronics"),"Electronics",PROPER(TRIM(K27))) -> Home Appliances | AK27: =IF(COUNTIF($A$2:A27,A27)=1,1,0) -> 1
A28: ORD10030 | B28: C006 | C28: P301 | D28: 46327 | E28: 16/01/2026 | F28: Sneha Joshi | G28: Female | H28: 29680 | I28: Pune | J28: West | K28: Stationery | L28: Notebook | M28: 2 | N28: 60 | O28: 5 | P28: 114 | Q28: 3 | R28: Cash | S28: Karan | T28: sneha.joshi@company.com | U28: 9512997042 | V28: Cancelled | W28: =IF(OR(Q28<=2,V28="Cancelled"),"Blacklisted",IF(AND(P28>100000,Q28>=4,O28<=10%,V28="Completed"),"Platinum",IF(AND(P28>=50000,Q28>=3,V28="Completed"),"Gold",IF(AND(P28<50000,V28="Completed"),"Silver","")))) -> Blacklisted | X28: =PROPER(TRIM(F28)) -> Sneha Joshi | Y28: =LEFT(F28,3)&MID(B28,2,3)&LEFT(I28,2) -> Sne006Pu | Z28: =IF(ISNUMBER(SEARCH("@",T28)),LOWER(TRIM(T28)),"invalid email") -> sneha.joshi@company.com | AA28: =IF(H27="","",IFERROR(DATEDIF(IF(ISNUMBER(H27),H27,DATE(VALUE(RIGHT(H27,4)),VALUE(MID(H27,3,2)),VALUE(LEFT(H27,2)))),TODAY(),"Y"),"")) -> 24 | AB28: =IF(OR(D28="",E28=""),"",IFERROR(DATE(MID(E28,7,4),MID(E28,4,2),LEFT(E28,2))-DATE(MID(D28,7,4),MID(D28,4,2),LEFT(D28,2)),"")) | AC28: =IF(E28="","Pending",IF(AB28<=5,"On time","Delayed")) -> Delayed | AD28: =IF(TRIM(S28)="","Not Assigned",S28) -> Karan | AE28: =PROPER(TRIM(F28)) -> Sneha Joshi | AF28: =PROPER(TRIM(K28)) -> Stationery | AG28: =PROPER(TRIM(J28)) -> West | AH28: =PROPER(TRIM(K28)) -> Stationery | AI28: =IF(OR(LOWER(TRIM(K28))="electronic",LOWER(TRIM(K28))="electronics"),"Electronics",PROPER(TRIM(K28))) -> Stationery | AK28: =IF(COUNTIF($A$2:A28,A28)=1,1,0) -> 1
A29: ORD10031 | B29: C008 | C29: P303 | D29: 16/06/2025 | E29: 26/06/2025 | F29: Kavya Nair | G29: Female | H29: 35102 | I29: Bengaluru | J29: South | K29: Stationery | L29: Marker | M29: 19 | N29: 45 | O29: 20 | P29: 684 | Q29: 4 | R29: NetBanking | S29: Aisha | T29: kavya.nair@company.com | U29: 9372748661 | V29: Cancelled | W29: =IF(OR(Q29<=2,V29="Cancelled"),"Blacklisted",IF(AND(P29>100000,Q29>=4,O29<=10%,V29="Completed"),"Platinum",IF(AND(P29>=50000,Q29>=3,V29="Completed"),"Gold",IF(AND(P29<50000,V29="Completed"),"Silver","")))) -> Blacklisted | X29: =PROPER(TRIM(F29)) -> Kavya Nair | Y29: =LEFT(F29,3)&MID(B29,2,3)&LEFT(I29,2) -> Kav008Be | Z29: =IF(ISNUMBER(SEARCH("@",T29)),LOWER(TRIM(T29)),"invalid email") -> kavya.nair@company.com | AA29: =IF(H28="","",IFERROR(DATEDIF(IF(ISNUMBER(H28),H28,DATE(VALUE(RIGHT(H28,4)),VALUE(MID(H28,3,2)),VALUE(LEFT(H28,2)))),TODAY(),"Y"),"")) -> 45 | AB29: =IF(OR(D29="",E29=""),"",IFERROR(DATE(MID(E29,7,4),MID(E29,4,2),LEFT(E29,2))-DATE(MID(D29,7,4),MID(D29,4,2),LEFT(D29,2)),"")) -> 10 | AC29: =IF(E29="","Pending",IF(AB29<=5,"On time","Delayed")) -> Delayed | AD29: =IF(TRIM(S29)="","Not Assigned",S29) -> Aisha | AE29: =PROPER(TRIM(F29)) -> Kavya Nair | AF29: =PROPER(TRIM(K29)) -> Stationery | AG29: =PROPER(TRIM(J29)) -> South | AH29: =PROPER(TRIM(K29)) -> Stationery | AI29: =IF(OR(LOWER(TRIM(K29))="electronic",LOWER(TRIM(K29))="electronics"),"Electronics",PROPER(TRIM(K29))) -> Stationery | AK29: =IF(COUNTIF($A$2:A29,A29)=1,1,0) -> 1
A30: ORD10032 | B30: C002 | C30: P104 | D30: 45664 | E30: 13/07/2025 | F30: Priya Patel | G30: Female | H30: 15/11/1976 | I30: Ahmedabad | J30: West | K30: Electronics | L30: Monitor | M30: 11 | N30: 12000 | O30: 0 | P30: 132000 | Q30: 3 | R30: UPI | S30: Ritika | T30: priya.patel@company.com | U30: 9570437805 | V30: Pending | W30: =IF(OR(Q30<=2,V30="Cancelled"),"Blacklisted",IF(AND(P30>100000,Q30>=4,O30<=10%,V30="Completed"),"Platinum",IF(AND(P30>=50000,Q30>=3,V30="Completed"),"Gold",IF(AND(P30<50000,V30="Completed"),"Silver","")))) | X30: =PROPER(TRIM(F30)) -> Priya Patel | Y30: =LEFT(F30,3)&MID(B30,2,3)&LEFT(I30,2) -> Pri002Ah | Z30: =IF(ISNUMBER(SEARCH("@",T30)),LOWER(TRIM(T30)),"invalid email") -> priya.patel@company.com | AA30: =IF(H29="","",IFERROR(DATEDIF(IF(ISNUMBER(H29),H29,DATE(VALUE(RIGHT(H29,4)),VALUE(MID(H29,3,2)),VALUE(LEFT(H29,2)))),TODAY(),"Y"),"")) -> 30 | AB30: =IF(OR(D30="",E30=""),"",IFERROR(DATE(MID(E30,7,4),MID(E30,4,2),LEFT(E30,2))-DATE(MID(D30,7,4),MID(D30,4,2),LEFT(D30,2)),"")) | AC30: =IF(E30="","Pending",IF(AB30<=5,"On time","Delayed")) -> Delayed | AD30: =IF(TRIM(S30)="","Not Assigned",S30) -> Ritika | AE30: =PROPER(TRIM(F30)) -> Priya Patel | AF30: =PROPER(TRIM(K30)) -> Electronics | AG30: =PROPER(TRIM(J30)) -> West | AH30: =PROPER(TRIM(K30)) -> Electronics | AI30: =IF(OR(LOWER(TRIM(K30))="electronic",LOWER(TRIM(K30))="electronics"),"Electronics",PROPER(TRIM(K30))) -> Electronics | AK30: =IF(COUNTIF($A$2:A30,A30)=1,1,0) -> 1
A31: ORD10033 | B31: C006 | C31: P202 | D31: 45841 | E31: 15/03/2025 | F31: Sneha Joshi | G31: Female | H31: 28/10/1988 | I31: Bengaluru | J31: South | K31: Home Appliances | L31: Iron | M31: 20 | N31: 2200 | O31: 5 | P31: 41800 | Q31: 1 | R31: Cash | S31: Rahul | T31: sneha.joshi@company.com | U31: 9310669113 | V31: Pending | W31: =IF(OR(Q31<=2,V31="Cancelled"),"Blacklisted",IF(AND(P31>100000,Q31>=4,O31<=10%,V31="Completed"),"Platinum",IF(AND(P31>=50000,Q31>=3,V31="Completed"),"Gold",IF(AND(P31<50000,V31="Completed"),"Silver","")))) -> Blacklisted | X31: =PROPER(TRIM(F31)) -> Sneha Joshi | Y31: =LEFT(F31,3)&MID(B31,2,3)&LEFT(I31,2) -> Sne006Be | Z31: =IF(ISNUMBER(SEARCH("@",T31)),LOWER(TRIM(T31)),"invalid email") -> sneha.joshi@company.com | AA31: =IF(H30="","",IFERROR(DATEDIF(IF(ISNUMBER(H30),H30,DATE(VALUE(RIGHT(H30,4)),VALUE(MID(H30,3,2)),VALUE(LEFT(H30,2)))),TODAY(),"Y"),"")) | AB31: =IF(OR(D31="",E31=""),"",IFERROR(DATE(MID(E31,7,4),MID(E31,4,2),LEFT(E31,2))-DATE(MID(D31,7,4),MID(D31,4,2),LEFT(D31,2)),"")) | AC31: =IF(E31="","Pending",IF(AB31<=5,"On time","Delayed")) -> Delayed | AD31: =IF(TRIM(S31)="","Not Assigned",S31) -> Rahul | AE31: =PROPER(TRIM(F31)) -> Sneha Joshi | AF31: =PROPER(TRIM(K31)) -> Home Appliances | AG31: =PROPER(TRIM(J31)) -> South | AH31: =PROPER(TRIM(K31)) -> Home Appliances | AI31: =IF(OR(LOWER(TRIM(K31))="electronic",LOWER(TRIM(K31))="electronics"),"Electronics",PROPER(TRIM(K31))) -> Home Appliances | AK31: =IF(COUNTIF($A$2:A31,A31)=1,1,0) -> 1
A32: ORD10034 | B32: C007 | C32: P302 | D32: 24/06/2025 | E32: 45754 | F32: Arjun Rao | G32: Male | H32: 23/06/2004 | I32: Ahmedabad | J32: West | K32: Stationery | L32: Pen | M32: 3 | N32: 20 | O32: 0 | P32: 60 | Q32: 2 | R32: Card | S32: Ritika | T32: wrongmail | U32: 9437132894 | V32: Cancelled | W32: =IF(OR(Q32<=2,V32="Cancelled"),"Blacklisted",IF(AND(P32>100000,Q32>=4,O32<=10%,V32="Completed"),"Platinum",IF(AND(P32>=50000,Q32>=3,V32="Completed"),"Gold",IF(AND(P32<50000,V32="Completed"),"Silver","")))) -> Blacklisted | X32: =PROPER(TRIM(F32)) -> Arjun Rao | Y32: =LEFT(F32,3)&MID(B32,2,3)&LEFT(I32,2) -> Arj007Ah | Z32: =IF(ISNUMBER(SEARCH("@",T32)),LOWER(TRIM(T32)),"invalid email") -> invalid email | AA32: =IF(H31="","",IFERROR(DATEDIF(IF(ISNUMBER(H31),H31,DATE(VALUE(RIGHT(H31,4)),VALUE(MID(H31,3,2)),VALUE(LEFT(H31,2)))),TODAY(),"Y"),"")) | AB32: =IF(OR(D32="",E32=""),"",IFERROR(DATE(MID(E32,7,4),MID(E32,4,2),LEFT(E32,2))-DATE(MID(D32,7,4),MID(D32,4,2),LEFT(D32,2)),"")) | AC32: =IF(E32="","Pending",IF(AB32<=5,"On time","Delayed")) -> Delayed | AD32: =IF(TRIM(S32)="","Not Assigned",S32) -> Ritika | AE32: =PROPER(TRIM(F32)) -> Arjun Rao | AF32: =PROPER(TRIM(K32)) -> Stationery | AG32: =PROPER(TRIM(J32)) -> West | AH32: =PROPER(TRIM(K32)) -> Stationery | AI32: =IF(OR(LOWER(TRIM(K32))="electronic",LOWER(TRIM(K32))="electronics"),"Electronics",PROPER(TRIM(K32))) -> Stationery | AK32: =IF(COUNTIF($A$2:A32,A32)=1,1,0) -> 1
A33: ORD10035 | B33: C003 | C33: P303 | D33: 45910 | E33: 19/10/2025 | F33: Rohit Singh | G33: Male | H33: 22/04/1996 | I33: Pune | J33: West | K33: Stationery | L33: Marker | M33: 18 | N33: 45 | O33: 20 | P33: 648 | Q33: 4 | R33: NetBanking | S33: Ritika | T33: rohit.singh@company.com | U33: 9762437243 | V33: Cancelled | W33: =IF(OR(Q33<=2,V33="Cancelled"),"Blacklisted",IF(AND(P33>100000,Q33>=4,O33<=10%,V33="Completed"),"Platinum",IF(AND(P33>=50000,Q33>=3,V33="Completed"),"Gold",IF(AND(P33<50000,V33="Completed"),"Silver","")))) -> Blacklisted | X33: =PROPER(TRIM(F33)) -> Rohit Singh | Y33: =LEFT(F33,3)&MID(B33,2,3)&LEFT(I33,2) -> Roh003Pu | Z33: =IF(ISNUMBER(SEARCH("@",T33)),LOWER(TRIM(T33)),"invalid email") -> rohit.singh@company.com | AA33: =IF(H32="","",IFERROR(DATEDIF(IF(ISNUMBER(H32),H32,DATE(VALUE(RIGHT(H32,4)),VALUE(MID(H32,3,2)),VALUE(LEFT(H32,2)))),TODAY(),"Y"),"")) | AB33: =IF(OR(D33="",E33=""),"",IFERROR(DATE(MID(E33,7,4),MID(E33,4,2),LEFT(E33,2))-DATE(MID(D33,7,4),MID(D33,4,2),LEFT(D33,2)),"")) | AC33: =IF(E33="","Pending",IF(AB33<=5,"On time","Delayed")) -> Delayed | AD33: =IF(TRIM(S33)="","Not Assigned",S33) -> Ritika | AE33: =PROPER(TRIM(F33)) -> Rohit Singh | AF33: =PROPER(TRIM(K33)) -> Stationery | AG33: =PROPER(TRIM(J33)) -> West | AH33: =PROPER(TRIM(K33)) -> Stationery | AI33: =IF(OR(LOWER(TRIM(K33))="electronic",LOWER(TRIM(K33))="electronics"),"Electronics",PROPER(TRIM(K33))) -> Stationery | AK33: =IF(COUNTIF($A$2:A33,A33)=1,1,0) -> 1
A34: ORD10036 | B34: C003 | C34: P103 | D34: 19/11/2025 | E34: 26/11/2025 | F34: Rohit Singh | G34: Male | H34: 29043 | I34: Bengaluru | J34: South | K34: Electronics | L34: Keyboard | M34: 4 | N34: 1200 | O34: 20 | P34: 3840 | Q34: 3 | R34: NetBanking | S34: Aisha | T34: rohit.singh@company.com | U34: 9149046970 | V34: Completed | W34: =IF(OR(Q34<=2,V34="Cancelled"),"Blacklisted",IF(AND(P34>100000,Q34>=4,O34<=10%,V34="Completed"),"Platinum",IF(AND(P34>=50000,Q34>=3,V34="Completed"),"Gold",IF(AND(P34<50000,V34="Completed"),"Silver","")))) -> Silver | X34: =PROPER(TRIM(F34)) -> Rohit Singh | Y34: =LEFT(F34,3)&MID(B34,2,3)&LEFT(I34,2) -> Roh003Be | Z34: =IF(ISNUMBER(SEARCH("@",T34)),LOWER(TRIM(T34)),"invalid email") -> rohit.singh@company.com | AA34: =IF(H33="","",IFERROR(DATEDIF(IF(ISNUMBER(H33),H33,DATE(VALUE(RIGHT(H33,4)),VALUE(MID(H33,3,2)),VALUE(LEFT(H33,2)))),TODAY(),"Y"),"")) | AB34: =IF(OR(D34="",E34=""),"",IFERROR(DATE(MID(E34,7,4),MID(E34,4,2),LEFT(E34,2))-DATE(MID(D34,7,4),MID(D34,4,2),LEFT(D34,2)),"")) -> 7 | AC34: =IF(E34="","Pending",IF(AB34<=5,"On time","Delayed")) -> Delayed | AD34: =IF(TRIM(S34)="","Not Assigned",S34) -> Aisha | AE34: =PROPER(TRIM(F34)) -> Rohit Singh | AF34: =PROPER(TRIM(K34)) -> Electronics | AG34: =PROPER(TRIM(J34)) -> South | AH34: =PROPER(TRIM(K34)) -> Electronics | AI34: =IF(OR(LOWER(TRIM(K34))="electronic",LOWER(TRIM(K34))="electronics"),"Electronics",PROPER(TRIM(K34))) -> Electronics | AK34: =IF(COUNTIF($A$2:A34,A34)=1,1,0) -> 1
A35: ORD10037 | B35: C009 | C35: P101 | D35: 45788 | E35: 14/11/2025 | F35: Mohit Verma | G35: Male | H35: 27/09/1980 | I35: Kolkata | J35: East | K35: Electronics | L35: Laptop | M35: 10 | N35: 55000 | O35: 0 | P35: 550000 | Q35: 1 | R35: UPI | S35: Rahul | T35: mohit.verma@company.com | U35: 9869182901 | V35: Cancelled | W35: =IF(OR(Q35<=2,V35="Cancelled"),"Blacklisted",IF(AND(P35>100000,Q35>=4,O35<=10%,V35="Completed"),"Platinum",IF(AND(P35>=50000,Q35>=3,V35="Completed"),"Gold",IF(AND(P35<50000,V35="Completed"),"Silver","")))) -> Blacklisted | X35: =PROPER(TRIM(F35)) -> Mohit Verma | Y35: =LEFT(F35,3)&MID(B35,2,3)&LEFT(I35,2) -> Moh009Ko | Z35: =IF(ISNUMBER(SEARCH("@",T35)),LOWER(TRIM(T35)),"invalid email") -> mohit.verma@company.com | AA35: =IF(H34="","",IFERROR(DATEDIF(IF(ISNUMBER(H34),H34,DATE(VALUE(RIGHT(H34,4)),VALUE(MID(H34,3,2)),VALUE(LEFT(H34,2)))),TODAY(),"Y"),"")) -> 47 | AB35: =IF(OR(D35="",E35=""),"",IFERROR(DATE(MID(E35,7,4),MID(E35,4,2),LEFT(E35,2))-DATE(MID(D35,7,4),MID(D35,4,2),LEFT(D35,2)),"")) | AC35: =IF(E35="","Pending",IF(AB35<=5,"On time","Delayed")) -> Delayed | AD35: =IF(TRIM(S35)="","Not Assigned",S35) -> Rahul | AE35: =PROPER(TRIM(F35)) -> Mohit Verma | AF35: =PROPER(TRIM(K35)) -> Electronics | AG35: =PROPER(TRIM(J35)) -> East | AH35: =PROPER(TRIM(K35)) -> Electronics | AI35: =IF(OR(LOWER(TRIM(K35))="electronic",LOWER(TRIM(K35))="electronics"),"Electronics",PROPER(TRIM(K35))) -> Electronics | AK35: =IF(COUNTIF($A$2:A35,A35)=1,1,0) -> 1
A36: ORD10038 | B36: C006 | C36: P201 | D36: 46237 | E36: 20/03/2026 | F36: Sneha Joshi | G36: Female | H36: 21/06/1980 | I36: Delhi | J36: North | K36: Home Appliances | L36: Mixer | M36: 20 | N36: 3500 | O36: 10 | P36: 63000 | Q36: 3 | R36: Card | S36: Rahul | T36: sneha.joshi@company.com | U36: 9283578533 | V36: Cancelled | W36: =IF(OR(Q36<=2,V36="Cancelled"),"Blacklisted",IF(AND(P36>100000,Q36>=4,O36<=10%,V36="Completed"),"Platinum",IF(AND(P36>=50000,Q36>=3,V36="Completed"),"Gold",IF(AND(P36<50000,V36="Completed"),"Silver","")))) -> Blacklisted | X36: =PROPER(TRIM(F36)) -> Sneha Joshi | Y36: =LEFT(F36,3)&MID(B36,2,3)&LEFT(I36,2) -> Sne006De | Z36: =IF(ISNUMBER(SEARCH("@",T36)),LOWER(TRIM(T36)),"invalid email") -> sneha.joshi@company.com | AA36: =IF(H35="","",IFERROR(DATEDIF(IF(ISNUMBER(H35),H35,DATE(VALUE(RIGHT(H35,4)),VALUE(MID(H35,3,2)),VALUE(LEFT(H35,2)))),TODAY(),"Y"),"")) | AB36: =IF(OR(D36="",E36=""),"",IFERROR(DATE(MID(E36,7,4),MID(E36,4,2),LEFT(E36,2))-DATE(MID(D36,7,4),MID(D36,4,2),LEFT(D36,2)),"")) | AC36: =IF(E36="","Pending",IF(AB36<=5,"On time","Delayed")) -> Delayed | AD36: =IF(TRIM(S36)="","Not Assigned",S36) -> Rahul | AE36: =PROPER(TRIM(F36)) -> Sneha Joshi | AF36: =PROPER(TRIM(K36)) -> Home Appliances | AG36: =PROPER(TRIM(J36)) -> North | AH36: =PROPER(TRIM(K36)) -> Home Appliances | AI36: =IF(OR(LOWER(TRIM(K36))="electronic",LOWER(TRIM(K36))="electronics"),"Electronics",PROPER(TRIM(K36))) -> Home Appliances | AK36: =IF(COUNTIF($A$2:A36,A36)=1,1,0) -> 1
A37: ORD10039 | B37: C008 | C37: P302 | D37: 13/02/2025 | E37: 19/02/2025 | F37: Kavya Nair | G37: Female | H37: 17/06/1979 | I37: Pune | J37: West | K37: Stationery | L37: Pen | M37: 5 | N37: 1200 | O37: 0 | P37: 100 | Q37: 1 | R37: Cash | S37: Rahul | T37: kavya.nair@company.com | U37: 9963005771 | V37: Cancelled | W37: =IF(OR(Q37<=2,V37="Cancelled"),"Blacklisted",IF(AND(P37>100000,Q37>=4,O37<=10%,V37="Completed"),"Platinum",IF(AND(P37>=50000,Q37>=3,V37="Completed"),"Gold",IF(AND(P37<50000,V37="Completed"),"Silver","")))) -> Blacklisted | X37: =PROPER(TRIM(F37)) -> Kavya Nair | Y37: =LEFT(F37,3)&MID(B37,2,3)&LEFT(I37,2) -> Kav008Pu | Z37: =IF(ISNUMBER(SEARCH("@",T37)),LOWER(TRIM(T37)),"invalid email") -> kavya.nair@company.com | AA37: =IF(H36="","",IFERROR(DATEDIF(IF(ISNUMBER(H36),H36,DATE(VALUE(RIGHT(H36,4)),VALUE(MID(H36,3,2)),VALUE(LEFT(H36,2)))),TODAY(),"Y"),"")) | AB37: =IF(OR(D37="",E37=""),"",IFERROR(DATE(MID(E37,7,4),MID(E37,4,2),LEFT(E37,2))-DATE(MID(D37,7,4),MID(D37,4,2),LEFT(D37,2)),"")) -> 6 | AC37: =IF(E37="","Pending",IF(AB37<=5,"On time","Delayed")) -> Delayed | AD37: =IF(TRIM(S37)="","Not Assigned",S37) -> Rahul | AE37: =PROPER(TRIM(F37)) -> Kavya Nair | AF37: =PROPER(TRIM(K37)) -> Stationery | AG37: =PROPER(TRIM(J37)) -> West | AH37: =PROPER(TRIM(K37)) -> Stationery | AI37: =IF(OR(LOWER(TRIM(K37))="electronic",LOWER(TRIM(K37))="electronics"),"Electronics",PROPER(TRIM(K37))) -> Stationery | AK37: =IF(COUNTIF($A$2:A37,A37)=1,1,0) -> 1
A38: ORD10040 | B38: C010 | C38: P203 | D38: 45787 | E38: 15/10/2025 | F38: Pooja Shah | G38: Female | H38: 18/06/1992 | I38: Mumbai | J38: West | K38: Home Appliances | L38: Microwave | M38: 20 | N38: 8500 | O38: 0 | P38: 170000 | Q38: 1 | R38: UPI | S38: Neha | T38: pooja.shah@company.com | U38: 9484632635 | V38: Cancelled | W38: =IF(OR(Q38<=2,V38="Cancelled"),"Blacklisted",IF(AND(P38>100000,Q38>=4,O38<=10%,V38="Completed"),"Platinum",IF(AND(P38>=50000,Q38>=3,V38="Completed"),"Gold",IF(AND(P38<50000,V38="Completed"),"Silver","")))) -> Blacklisted | X38: =PROPER(TRIM(F38)) -> Pooja Shah | Y38: =LEFT(F38,3)&MID(B38,2,3)&LEFT(I38,2) -> Poo010Mu | Z38: =IF(ISNUMBER(SEARCH("@",T38)),LOWER(TRIM(T38)),"invalid email") -> pooja.shah@company.com | AA38: =IF(H37="","",IFERROR(DATEDIF(IF(ISNUMBER(H37),H37,DATE(VALUE(RIGHT(H37,4)),VALUE(MID(H37,3,2)),VALUE(LEFT(H37,2)))),TODAY(),"Y"),"")) | AB38: =IF(OR(D38="",E38=""),"",IFERROR(DATE(MID(E38,7,4),MID(E38,4,2),LEFT(E38,2))-DATE(MID(D38,7,4),MID(D38,4,2),LEFT(D38,2)),"")) | AC38: =IF(E38="","Pending",IF(AB38<=5,"On time","Delayed")) -> Delayed | AD38: =IF(TRIM(S38)="","Not Assigned",S38) -> Neha | AE38: =PROPER(TRIM(F38)) -> Pooja Shah | AF38: =PROPER(TRIM(K38)) -> Home Appliances | AG38: =PROPER(TRIM(J38)) -> West | AH38: =PROPER(TRIM(K38)) -> Home Appliances | AI38: =IF(OR(LOWER(TRIM(K38))="electronic",LOWER(TRIM(K38))="electronics"),"Electronics",PROPER(TRIM(K38))) -> Home Appliances | AK38: =IF(COUNTIF($A$2:A38,A38)=1,1,0) -> 1
A39: ORD10041 | B39: C007 | C39: P301 | D39: 46297 | E39: 46358 | F39: Arjun Rao | G39: Male | H39: 34491 | I39: Bengaluru | J39: South | K39: Stationery | L39: Notebook | M39: 8 | N39: 60 | O39: 15 | P39: 408 | Q39: 5 | R39: UPI | S39: Rahul | T39: arjun.rao@company.com | U39: 9276319484 | V39: Pending | W39: =IF(OR(Q39<=2,V39="Cancelled"),"Blacklisted",IF(AND(P39>100000,Q39>=4,O39<=10%,V39="Completed"),"Platinum",IF(AND(P39>=50000,Q39>=3,V39="Completed"),"Gold",IF(AND(P39<50000,V39="Completed"),"Silver","")))) | X39: =PROPER(TRIM(F39)) -> Arjun Rao | Y39: =LEFT(F39,3)&MID(B39,2,3)&LEFT(I39,2) -> Arj007Be | Z39: =IF(ISNUMBER(SEARCH("@",T39)),LOWER(TRIM(T39)),"invalid email") -> arjun.rao@company.com | AA39: =IF(H38="","",IFERROR(DATEDIF(IF(ISNUMBER(H38),H38,DATE(VALUE(RIGHT(H38,4)),VALUE(MID(H38,3,2)),VALUE(LEFT(H38,2)))),TODAY(),"Y"),"")) | AB39: =IF(OR(D39="",E39=""),"",IFERROR(DATE(MID(E39,7,4),MID(E39,4,2),LEFT(E39,2))-DATE(MID(D39,7,4),MID(D39,4,2),LEFT(D39,2)),"")) | AC39: =IF(E39="","Pending",IF(AB39<=5,"On time","Delayed")) -> Delayed | AD39: =IF(TRIM(S39)="","Not Assigned",S39) -> Rahul | AE39: =PROPER(TRIM(F39)) -> Arjun Rao | AF39: =PROPER(TRIM(K39)) -> Stationery | AG39: =PROPER(TRIM(J39)) -> South | AH39: =PROPER(TRIM(K39)) -> Stationery | AI39: =IF(OR(LOWER(TRIM(K39))="electronic",LOWER(TRIM(K39))="electronics"),"Electronics",PROPER(TRIM(K39))) -> Stationery | AK39: =IF(COUNTIF($A$2:A39,A39)=1,1,0) -> 1
A40: ORD10042 | B40: C010 | C40: P201 | D40: 45753 | E40: 16/06/2025 | F40: Pooja Shah | G40: Female | H40: 22/09/1988 | I40: Pune | J40: West | K40: Home Appliances | L40: Mixer | M40: 8 | N40: 3500 | O40: 5 | P40: 26600 | Q40: 1 | R40: Card | S40: Neha | T40: pooja.shah@company.com | U40: 9619034852 | V40: Pending | W40: =IF(OR(Q40<=2,V40="Cancelled"),"Blacklisted",IF(AND(P40>100000,Q40>=4,O40<=10%,V40="Completed"),"Platinum",IF(AND(P40>=50000,Q40>=3,V40="Completed"),"Gold",IF(AND(P40<50000,V40="Completed"),"Silver","")))) -> Blacklisted | X40: =PROPER(TRIM(F40)) -> Pooja Shah | Y40: =LEFT(F40,3)&MID(B40,2,3)&LEFT(I40,2) -> Poo010Pu | Z40: =IF(ISNUMBER(SEARCH("@",T40)),LOWER(TRIM(T40)),"invalid email") -> pooja.shah@company.com | AA40: =IF(H39="","",IFERROR(DATEDIF(IF(ISNUMBER(H39),H39,DATE(VALUE(RIGHT(H39,4)),VALUE(MID(H39,3,2)),VALUE(LEFT(H39,2)))),TODAY(),"Y"),"")) -> 32 | AB40: =IF(OR(D40="",E40=""),"",IFERROR(DATE(MID(E40,7,4),MID(E40,4,2),LEFT(E40,2))-DATE(MID(D40,7,4),MID(D40,4,2),LEFT(D40,2)),"")) | AC40: =IF(E40="","Pending",IF(AB40<=5,"On time","Delayed")) -> Delayed | AD40: =IF(TRIM(S40)="","Not Assigned",S40) -> Neha | AE40: =PROPER(TRIM(F40)) -> Pooja Shah | AF40: =PROPER(TRIM(K40)) -> Home Appliances | AG40: =PROPER(TRIM(J40)) -> West | AH40: =PROPER(TRIM(K40)) -> Home Appliances | AI40: =IF(OR(LOWER(TRIM(K40))="electronic",LOWER(TRIM(K40))="electronics"),"Electronics",PROPER(TRIM(K40))) -> Home Appliances | AK40: =IF(COUNTIF($A$2:A40,A40)=1,1,0) -> 1
A41: ORD10043 | B41: C009 | C41: P203 | D41: 46236 | E41: 14/02/2026 | F41: Mohit Verma | G41: Male | H41: 14/07/2001 | I41: Jaipur | J41: North | K41: Home Appliances | L41: Microwave | M41: 1 | N41: 8500 | O41: 0 | P41: 8500 | Q41: 2 | R41: Card | S41: Neha | T41: mohit.verma@company.com | U41: 9636416962 | V41: Pending | W41: =IF(OR(Q41<=2,V41="Cancelled"),"Blacklisted",IF(AND(P41>100000,Q41>=4,O41<=10%,V41="Completed"),"Platinum",IF(AND(P41>=50000,Q41>=3,V41="Completed"),"Gold",IF(AND(P41<50000,V41="Completed"),"Silver","")))) -> Blacklisted | X41: =PROPER(TRIM(F41)) -> Mohit Verma | Y41: =LEFT(F41,3)&MID(B41,2,3)&LEFT(I41,2) -> Moh009Ja | Z41: =IF(ISNUMBER(SEARCH("@",T41)),LOWER(TRIM(T41)),"invalid email") -> mohit.verma@company.com | AA41: =IF(H40="","",IFERROR(DATEDIF(IF(ISNUMBER(H40),H40,DATE(VALUE(RIGHT(H40,4)),VALUE(MID(H40,3,2)),VALUE(LEFT(H40,2)))),TODAY(),"Y"),"")) | AB41: =IF(OR(D41="",E41=""),"",IFERROR(DATE(MID(E41,7,4),MID(E41,4,2),LEFT(E41,2))-DATE(MID(D41,7,4),MID(D41,4,2),LEFT(D41,2)),"")) | AC41: =IF(E41="","Pending",IF(AB41<=5,"On time","Delayed")) -> Delayed | AD41: =IF(TRIM(S41)="","Not Assigned",S41) -> Neha | AE41: =PROPER(TRIM(F41)) -> Mohit Verma | AF41: =PROPER(TRIM(K41)) -> Home Appliances | AG41: =PROPER(TRIM(J41)) -> North | AH41: =PROPER(TRIM(K41)) -> Home Appliances | AI41: =IF(OR(LOWER(TRIM(K41))="electronic",LOWER(TRIM(K41))="electronics"),"Electronics",PROPER(TRIM(K41))) -> Home Appliances | AK41: =IF(COUNTIF($A$2:A41,A41)=1,1,0) -> 1
A42: ORD10044 | B42: C001 | C42: P303 | D42: 30/03/2025 | E42: 31/03/2025 | F42: Amit Sharma | G42: Male | H42: 33489 | I42: Pune | J42: West | K42: Stationery | L42: Marker | M42: 8 | N42: 45 | O42: 15 | P42: 306 | Q42: 2 | R42: Card | S42: Aisha | T42: amit.sharma@company.com | U42: 9357133880 | V42: Completed | W42: =IF(OR(Q42<=2,V42="Cancelled"),"Blacklisted",IF(AND(P42>100000,Q42>=4,O42<=10%,V42="Completed"),"Platinum",IF(AND(P42>=50000,Q42>=3,V42="Completed"),"Gold",IF(AND(P42<50000,V42="Completed"),"Silver","")))) -> Blacklisted | X42: =PROPER(TRIM(F42)) -> Amit Sharma | Y42: =LEFT(F42,3)&MID(B42,2,3)&LEFT(I42,2) -> Ami001Pu | Z42: =IF(ISNUMBER(SEARCH("@",T42)),LOWER(TRIM(T42)),"invalid email") -> amit.sharma@company.com | AA42: =IF(H41="","",IFERROR(DATEDIF(IF(ISNUMBER(H41),H41,DATE(VALUE(RIGHT(H41,4)),VALUE(MID(H41,3,2)),VALUE(LEFT(H41,2)))),TODAY(),"Y"),"")) | AB42: =IF(OR(D42="",E42=""),"",IFERROR(DATE(MID(E42,7,4),MID(E42,4,2),LEFT(E42,2))-DATE(MID(D42,7,4),MID(D42,4,2),LEFT(D42,2)),"")) -> 1 | AC42: =IF(E42="","Pending",IF(AB42<=5,"On time","Delayed")) -> On time | AD42: =IF(TRIM(S42)="","Not Assigned",S42) -> Aisha | AE42: =PROPER(TRIM(F42)) -> Amit Sharma | AF42: =PROPER(TRIM(K42)) -> Stationery | AG42: =PROPER(TRIM(J42)) -> West | AH42: =PROPER(TRIM(K42)) -> Stationery | AI42: =IF(OR(LOWER(TRIM(K42))="electronic",LOWER(TRIM(K42))="electronics"),"Electronics",PROPER(TRIM(K42))) -> Stationery | AK42: =IF(COUNTIF($A$2:A42,A42)=1,1,0) -> 1
A43: ORD10045 | B43: C006 | C43: P202 | D43: 25/04/2025 | E43: 28/04/2025 | F43: Sneha Joshi | G43: Female | H43: 21/10/1988 | I43: Pune | J43: West | K43: Home Appliances | L43: Iron | M43: 16 | N43: 2200 | O43: 5 | P43: 33440 | Q43: 5 | R43: Card | S43: Aisha | T43: sneha.joshi@company.com | U43: 9575210324 | V43: Cancelled | W43: =IF(OR(Q43<=2,V43="Cancelled"),"Blacklisted",IF(AND(P43>100000,Q43>=4,O43<=10%,V43="Completed"),"Platinum",IF(AND(P43>=50000,Q43>=3,V43="Completed"),"Gold",IF(AND(P43<50000,V43="Completed"),"Silver","")))) -> Blacklisted | X43: =PROPER(TRIM(F43)) -> Sneha Joshi | Y43: =LEFT(F43,3)&MID(B43,2,3)&LEFT(I43,2) -> Sne006Pu | Z43: =IF(ISNUMBER(SEARCH("@",T43)),LOWER(TRIM(T43)),"invalid email") -> sneha.joshi@company.com | AA43: =IF(H42="","",IFERROR(DATEDIF(IF(ISNUMBER(H42),H42,DATE(VALUE(RIGHT(H42,4)),VALUE(MID(H42,3,2)),VALUE(LEFT(H42,2)))),TODAY(),"Y"),"")) -> 35 | AB43: =IF(OR(D43="",E43=""),"",IFERROR(DATE(MID(E43,7,4),MID(E43,4,2),LEFT(E43,2))-DATE(MID(D43,7,4),MID(D43,4,2),LEFT(D43,2)),"")) -> 3 | AC43: =IF(E43="","Pending",IF(AB43<=5,"On time","Delayed")) -> On time | AD43: =IF(TRIM(S43)="","Not Assigned",S43) -> Aisha | AE43: =PROPER(TRIM(F43)) -> Sneha Joshi | AF43: =PROPER(TRIM(K43)) -> Home Appliances | AG43: =PROPER(TRIM(J43)) -> West | AH43: =PROPER(TRIM(K43)) -> Home Appliances | AI43: =IF(OR(LOWER(TRIM(K43))="electronic",LOWER(TRIM(K43))="electronics"),"Electronics",PROPER(TRIM(K43))) -> Home Appliances | AK43: =IF(COUNTIF($A$2:A43,A43)=1,1,0) -> 1
A44: ORD10046 | B44: C009 | C44: P201 | D44: 13/10/2025 | E44: 23/10/2025 | F44: Mohit Verma | G44: Male | H44: 19/11/2002 | I44: Bengaluru | J44: South | K44: Home Appliances | L44: Mixer | M44: 19 | N44: 3500 | O44: 20 | P44: 53200 | Q44: 3 | R44: Cash | S44: Karan | T44: mohit.verma@company.com | U44: 9276080204 | V44: Cancelled | W44: =IF(OR(Q44<=2,V44="Cancelled"),"Blacklisted",IF(AND(P44>100000,Q44>=4,O44<=10%,V44="Completed"),"Platinum",IF(AND(P44>=50000,Q44>=3,V44="Completed"),"Gold",IF(AND(P44<50000,V44="Completed"),"Silver","")))) -> Blacklisted | X44: =PROPER(TRIM(F44)) -> Mohit Verma | Y44: =LEFT(F44,3)&MID(B44,2,3)&LEFT(I44,2) -> Moh009Be | Z44: =IF(ISNUMBER(SEARCH("@",T44)),LOWER(TRIM(T44)),"invalid email") -> mohit.verma@company.com | AA44: =IF(H43="","",IFERROR(DATEDIF(IF(ISNUMBER(H43),H43,DATE(VALUE(RIGHT(H43,4)),VALUE(MID(H43,3,2)),VALUE(LEFT(H43,2)))),TODAY(),"Y"),"")) | AB44: =IF(OR(D44="",E44=""),"",IFERROR(DATE(MID(E44,7,4),MID(E44,4,2),LEFT(E44,2))-DATE(MID(D44,7,4),MID(D44,4,2),LEFT(D44,2)),"")) -> 10 | AC44: =IF(E44="","Pending",IF(AB44<=5,"On time","Delayed")) -> Delayed | AD44: =IF(TRIM(S44)="","Not Assigned",S44) -> Karan | AE44: =PROPER(TRIM(F44)) -> Mohit Verma | AF44: =PROPER(TRIM(K44)) -> Home Appliances | AG44: =PROPER(TRIM(J44)) -> South | AH44: =PROPER(TRIM(K44)) -> Home Appliances | AI44: =IF(OR(LOWER(TRIM(K44))="electronic",LOWER(TRIM(K44))="electronics"),"Electronics",PROPER(TRIM(K44))) -> Home Appliances | AK44: =IF(COUNTIF($A$2:A44,A44)=1,1,0) -> 1
A45: ORD10047 | B45: C006 | C45: P102 | D45: 45971 | E45: 14/10/2025 | F45: Sneha Joshi | G45: Female | H45: 36684 | I45: Pune | J45: West | K45: Electronics | L45: Mouse | M45: 15 | N45: 700 | O45: 15 | P45: 8925 | Q45: 4 | R45: UPI | S45: Neha | T45: sneha.joshicompany.com | U45: 9856624471 | V45: Completed | W45: =IF(OR(Q45<=2,V45="Cancelled"),"Blacklisted",IF(AND(P45>100000,Q45>=4,O45<=10%,V45="Completed"),"Platinum",IF(AND(P45>=50000,Q45>=3,V45="Completed"),"Gold",IF(AND(P45<50000,V45="Completed"),"Silver","")))) -> Silver | X45: =PROPER(TRIM(F45)) -> Sneha Joshi | Y45: =LEFT(F45,3)&MID(B45,2,3)&LEFT(I45,2) -> Sne006Pu | Z45: =IF(ISNUMBER(SEARCH("@",T45)),LOWER(TRIM(T45)),"invalid email") -> invalid email | AA45: =IF(H44="","",IFERROR(DATEDIF(IF(ISNUMBER(H44),H44,DATE(VALUE(RIGHT(H44,4)),VALUE(MID(H44,3,2)),VALUE(LEFT(H44,2)))),TODAY(),"Y"),"")) | AB45: =IF(OR(D45="",E45=""),"",IFERROR(DATE(MID(E45,7,4),MID(E45,4,2),LEFT(E45,2))-DATE(MID(D45,7,4),MID(D45,4,2),LEFT(D45,2)),"")) | AC45: =IF(E45="","Pending",IF(AB45<=5,"On time","Delayed")) -> Delayed | AD45: =IF(TRIM(S45)="","Not Assigned",S45) -> Neha | AE45: =PROPER(TRIM(F45)) -> Sneha Joshi | AF45: =PROPER(TRIM(K45)) -> Electronics | AG45: =PROPER(TRIM(J45)) -> West | AH45: =PROPER(TRIM(K45)) -> Electronics | AI45: =IF(OR(LOWER(TRIM(K45))="electronic",LOWER(TRIM(K45))="electronics"),"Electronics",PROPER(TRIM(K45))) -> Electronics | AK45: =IF(COUNTIF($A$2:A45,A45)=1,1,0) -> 1
A46: ORD10048 | B46: C006 | C46: P102 | D46: 27/11/2025 | E46: 45728 | F46: Sneha Joshi | G46: Female | H46: 26/11/1998 | I46: Jaipur | J46: North | K46: Electronics | L46: Mouse | M46: 19 | N46: 700 | O46: 20 | P46: 10640 | Q46: 1 | R46: Cash | S46: Neha | T46: sneha.joshi@company.com | U46: 9238141322 | V46: Completed | W46: =IF(OR(Q46<=2,V46="Cancelled"),"Blacklisted",IF(AND(P46>100000,Q46>=4,O46<=10%,V46="Completed"),"Platinum",IF(AND(P46>=50000,Q46>=3,V46="Completed"),"Gold",IF(AND(P46<50000,V46="Completed"),"Silver","")))) -> Blacklisted | X46: =PROPER(TRIM(F46)) -> Sneha Joshi | Y46: =LEFT(F46,3)&MID(B46,2,3)&LEFT(I46,2) -> Sne006Ja | Z46: =IF(ISNUMBER(SEARCH("@",T46)),LOWER(TRIM(T46)),"invalid email") -> sneha.joshi@company.com | AA46: =IF(H45="","",IFERROR(DATEDIF(IF(ISNUMBER(H45),H45,DATE(VALUE(RIGHT(H45,4)),VALUE(MID(H45,3,2)),VALUE(LEFT(H45,2)))),TODAY(),"Y"),"")) -> 26 | AB46: =IF(OR(D46="",E46=""),"",IFERROR(DATE(MID(E46,7,4),MID(E46,4,2),LEFT(E46,2))-DATE(MID(D46,7,4),MID(D46,4,2),LEFT(D46,2)),"")) | AC46: =IF(E46="","Pending",IF(AB46<=5,"On time","Delayed")) -> Delayed | AD46: =IF(TRIM(S46)="","Not Assigned",S46) -> Neha | AE46: =PROPER(TRIM(F46)) -> Sneha Joshi | AF46: =PROPER(TRIM(K46)) -> Electronics | AG46: =PROPER(TRIM(J46)) -> North | AH46: =PROPER(TRIM(K46)) -> Electronics | AI46: =IF(OR(LOWER(TRIM(K46))="electronic",LOWER(TRIM(K46))="electronics"),"Electronics",PROPER(TRIM(K46))) -> Electronics | AK46: =IF(COUNTIF($A$2:A46,A46)=1,1,0) -> 1
A47: ORD10049 | B47: C009 | C47: P104 | D47: 19/04/2026 | E47: Pending | F47: Mohit Verma | G47: Male | H47: 35130 | I47: Delhi | J47: North | K47: Electronics | L47: Monitor | M47: 19 | N47: 12000 | O47: 0 | P47: 228000 | Q47: 1 | R47: NetBanking | S47: Aisha | T47: mohit.verma@company.com | U47: 9890380030 | V47: Completed | W47: =IF(OR(Q47<=2,V47="Cancelled"),"Blacklisted",IF(AND(P47>100000,Q47>=4,O47<=10%,V47="Completed"),"Platinum",IF(AND(P47>=50000,Q47>=3,V47="Completed"),"Gold",IF(AND(P47<50000,V47="Completed"),"Silver","")))) -> Blacklisted | X47: =PROPER(TRIM(F47)) -> Mohit Verma | Y47: =LEFT(F47,3)&MID(B47,2,3)&LEFT(I47,2) -> Moh009De | Z47: =IF(ISNUMBER(SEARCH("@",T47)),LOWER(TRIM(T47)),"invalid email") -> mohit.verma@company.com | AA47: =IF(H46="","",IFERROR(DATEDIF(IF(ISNUMBER(H46),H46,DATE(VALUE(RIGHT(H46,4)),VALUE(MID(H46,3,2)),VALUE(LEFT(H46,2)))),TODAY(),"Y"),"")) | AB47: =IF(OR(D47="",E47=""),"",IFERROR(DATE(MID(E47,7,4),MID(E47,4,2),LEFT(E47,2))-DATE(MID(D47,7,4),MID(D47,4,2),LEFT(D47,2)),"")) | AC47: =IF(E47="","Pending",IF(AB47<=5,"On time","Delayed")) -> Delayed | AD47: =IF(TRIM(S47)="","Not Assigned",S47) -> Aisha | AE47: =PROPER(TRIM(F47)) -> Mohit Verma | AF47: =PROPER(TRIM(K47)) -> Electronics | AG47: =PROPER(TRIM(J47)) -> North | AH47: =PROPER(TRIM(K47)) -> Electronics | AI47: =IF(OR(LOWER(TRIM(K47))="electronic",LOWER(TRIM(K47))="electronics"),"Electronics",PROPER(TRIM(K47))) -> Electronics | AK47: =IF(COUNTIF($A$2:A47,A47)=1,1,0) -> 1
A48: ORD10050 | B48: C004 | C48: P103 | D48: 19/04/2026 | E48: 21/04/2026 | F48: Anita Gupta | G48: Female | H48: 15/03/1987 | I48: Pune | J48: West | K48: Electronics | L48: Keyboard | M48: 6 | N48: 1200 | O48: 5 | P48: 6840 | Q48: 2 | R48: Cash | S48: Ritika | T48: anita.gupta@company.com | U48: 9495893170 | V48: Pending | W48: =IF(OR(Q48<=2,V48="Cancelled"),"Blacklisted",IF(AND(P48>100000,Q48>=4,O48<=10%,V48="Completed"),"Platinum",IF(AND(P48>=50000,Q48>=3,V48="Completed"),"Gold",IF(AND(P48<50000,V48="Completed"),"Silver","")))) -> Blacklisted | X48: =PROPER(TRIM(F48)) -> Anita Gupta | Y48: =LEFT(F48,3)&MID(B48,2,3)&LEFT(I48,2) -> Ani004Pu | Z48: =IF(ISNUMBER(SEARCH("@",T48)),LOWER(TRIM(T48)),"invalid email") -> anita.gupta@company.com | AA48: =IF(H47="","",IFERROR(DATEDIF(IF(ISNUMBER(H47),H47,DATE(VALUE(RIGHT(H47,4)),VALUE(MID(H47,3,2)),VALUE(LEFT(H47,2)))),TODAY(),"Y"),"")) -> 30 | AB48: =IF(OR(D48="",E48=""),"",IFERROR(DATE(MID(E48,7,4),MID(E48,4,2),LEFT(E48,2))-DATE(MID(D48,7,4),MID(D48,4,2),LEFT(D48,2)),"")) -> 2 | AC48: =IF(E48="","Pending",IF(AB48<=5,"On time","Delayed")) -> On time | AD48: =IF(TRIM(S48)="","Not Assigned",S48) -> Ritika | AE48: =PROPER(TRIM(F48)) -> Anita Gupta | AF48: =PROPER(TRIM(K48)) -> Electronics | AG48: =PROPER(TRIM(J48)) -> West | AH48: =PROPER(TRIM(K48)) -> Electronics | AI48: =IF(OR(LOWER(TRIM(K48))="electronic",LOWER(TRIM(K48))="electronics"),"Electronics",PROPER(TRIM(K48))) -> Electronics | AK48: =IF(COUNTIF($A$2:A48,A48)=1,1,0) -> 1
A49: ORD10051 | B49: C010 | C49: P202 | D49: 28/03/2025 | E49: 45842 | F49: Pooja Shah | G49: Female | H49: 20/02/1979 | I49: Bengaluru | J49: South | K49: Home Appliances | L49: Iron | M49: 7 | N49: 2200 | O49: 15 | P49: 13090 | Q49: 1 | R49: UPI | S49: Aisha | T49: pooja.shah@company.com | U49: 9485166307 | V49: Completed | W49: =IF(OR(Q49<=2,V49="Cancelled"),"Blacklisted",IF(AND(P49>100000,Q49>=4,O49<=10%,V49="Completed"),"Platinum",IF(AND(P49>=50000,Q49>=3,V49="Completed"),"Gold",IF(AND(P49<50000,V49="Completed"),"Silver","")))) -> Blacklisted | X49: =PROPER(TRIM(F49)) -> Pooja Shah | Y49: =LEFT(F49,3)&MID(B49,2,3)&LEFT(I49,2) -> Poo010Be | Z49: =IF(ISNUMBER(SEARCH("@",T49)),LOWER(TRIM(T49)),"invalid email") -> pooja.shah@company.com | AA49: =IF(H48="","",IFERROR(DATEDIF(IF(ISNUMBER(H48),H48,DATE(VALUE(RIGHT(H48,4)),VALUE(MID(H48,3,2)),VALUE(LEFT(H48,2)))),TODAY(),"Y"),"")) | AB49: =IF(OR(D49="",E49=""),"",IFERROR(DATE(MID(E49,7,4),MID(E49,4,2),LEFT(E49,2))-DATE(MID(D49,7,4),MID(D49,4,2),LEFT(D49,2)),"")) | AC49: =IF(E49="","Pending",IF(AB49<=5,"On time","Delayed")) -> Delayed | AD49: =IF(TRIM(S49)="","Not Assigned",S49) -> Aisha | AE49: =PROPER(TRIM(F49)) -> Pooja Shah | AF49: =PROPER(TRIM(K49)) -> Home Appliances | AG49: =PROPER(TRIM(J49)) -> South | AH49: =PROPER(TRIM(K49)) -> Home Appliances | AI49: =IF(OR(LOWER(TRIM(K49))="electronic",LOWER(TRIM(K49))="electronics"),"Electronics",PROPER(TRIM(K49))) -> Home Appliances | AK49: =IF(COUNTIF($A$2:A49,A49)=1,1,0) -> 1
A50: ORD10052 | B50: C002 | C50: P301 | D50: 25/08/2025 | E50: 28/08/2025 | F50: Priya Patel | G50: Female | H50: 36777 | I50: Jaipur | J50: North | K50: Stationery | L50: Notebook | M50: 8 | N50: 60 | O50: 10 | P50: 432 | Q50: 5 | R50: Card | S50: Aisha | T50: priya.patel@company.com | U50: 9924709648 | V50: Cancelled | W50: =IF(OR(Q50<=2,V50="Cancelled"),"Blacklisted",IF(AND(P50>100000,Q50>=4,O50<=10%,V50="Completed"),"Platinum",IF(AND(P50>=50000,Q50>=3,V50="Completed"),"Gold",IF(AND(P50<50000,V50="Completed"),"Silver","")))) -> Blacklisted | X50: =PROPER(TRIM(F50)) -> Priya Patel | Y50: =LEFT(F50,3)&MID(B50,2,3)&LEFT(I50,2) -> Pri002Ja | Z50: =IF(ISNUMBER(SEARCH("@",T50)),LOWER(TRIM(T50)),"invalid email") -> priya.patel@company.com | AA50: =IF(H49="","",IFERROR(DATEDIF(IF(ISNUMBER(H49),H49,DATE(VALUE(RIGHT(H49,4)),VALUE(MID(H49,3,2)),VALUE(LEFT(H49,2)))),TODAY(),"Y"),"")) | AB50: =IF(OR(D50="",E50=""),"",IFERROR(DATE(MID(E50,7,4),MID(E50,4,2),LEFT(E50,2))-DATE(MID(D50,7,4),MID(D50,4,2),LEFT(D50,2)),"")) -> 3 | AC50: =IF(E50="","Pending",IF(AB50<=5,"On time","Delayed")) -> On time | AD50: =IF(TRIM(S50)="","Not Assigned",S50) -> Aisha | AE50: =PROPER(TRIM(F50)) -> Priya Patel | AF50: =PROPER(TRIM(K50)) -> Stationery | AG50: =PROPER(TRIM(J50)) -> North | AH50: =PROPER(TRIM(K50)) -> Stationery | AI50: =IF(OR(LOWER(TRIM(K50))="electronic",LOWER(TRIM(K50))="electronics"),"Electronics",PROPER(TRIM(K50))) -> Stationery | AK50: =IF(COUNTIF($A$2:A50,A50)=1,1,0) -> 1
A51: ORD10053 | B51: C005 | C51: P101 | D51: 19/08/2025 | E51: 23/08/2025 | F51: Vikas Mehta | G51: Male | H51: 17/01/1976 | I51: Kolkata | J51: East | K51: Electronics | L51: Laptop | M51: 12 | N51: 55000 | O51: 5 | P51: 627000 | Q51: 2 | R51: UPI | S51: Rahul | T51: vikas.mehta@company.com | U51: 9350554626 | V51: Pending | W51: =IF(OR(Q51<=2,V51="Cancelled"),"Blacklisted",IF(AND(P51>100000,Q51>=4,O51<=10%,V51="Completed"),"Platinum",IF(AND(P51>=50000,Q51>=3,V51="Completed"),"Gold",IF(AND(P51<50000,V51="Completed"),"Silver","")))) -> Blacklisted | X51: =PROPER(TRIM(F51)) -> Vikas Mehta | Y51: =LEFT(F51,3)&MID(B51,2,3)&LEFT(I51,2) -> Vik005Ko | Z51: =IF(ISNUMBER(SEARCH("@",T51)),LOWER(TRIM(T51)),"invalid email") -> vikas.mehta@company.com | AA51: =IF(H50="","",IFERROR(DATEDIF(IF(ISNUMBER(H50),H50,DATE(VALUE(RIGHT(H50,4)),VALUE(MID(H50,3,2)),VALUE(LEFT(H50,2)))),TODAY(),"Y"),"")) -> 26 | AB51: =IF(OR(D51="",E51=""),"",IFERROR(DATE(MID(E51,7,4),MID(E51,4,2),LEFT(E51,2))-DATE(MID(D51,7,4),MID(D51,4,2),LEFT(D51,2)),"")) -> 4 | AC51: =IF(E51="","Pending",IF(AB51<=5,"On time","Delayed")) -> On time | AD51: =IF(TRIM(S51)="","Not Assigned",S51) -> Rahul | AE51: =PROPER(TRIM(F51)) -> Vikas Mehta | AF51: =PROPER(TRIM(K51)) -> Electronics | AG51: =PROPER(TRIM(J51)) -> East | AH51: =PROPER(TRIM(K51)) -> Electronics | AI51: =IF(OR(LOWER(TRIM(K51))="electronic",LOWER(TRIM(K51))="electronics"),"Electronics",PROPER(TRIM(K51))) -> Electronics | AK51: =IF(COUNTIF($A$2:A51,A51)=1,1,0) -> 1
A52: ORD10054 | B52: C008 | C52: P102 | D52: 27/07/2025 | E52: 45785 | F52: Kavya Nair | G52: Female | H52: 27488 | I52: Jaipur | J52: North | K52: Electronics | L52: Mouse | M52: 3 | N52: 700 | O52: 0 | P52: 2100 | Q52: 3 | R52: Card | S52: Karan | T52: kavya.nair@company.com | U52: 9743295580 | V52: Cancelled | W52: =IF(OR(Q52<=2,V52="Cancelled"),"Blacklisted",IF(AND(P52>100000,Q52>=4,O52<=10%,V52="Completed"),"Platinum",IF(AND(P52>=50000,Q52>=3,V52="Completed"),"Gold",IF(AND(P52<50000,V52="Completed"),"Silver","")))) -> Blacklisted | X52: =PROPER(TRIM(F52)) -> Kavya Nair | Y52: =LEFT(F52,3)&MID(B52,2,3)&LEFT(I52,2) -> Kav008Ja | Z52: =IF(ISNUMBER(SEARCH("@",T52)),LOWER(TRIM(T52)),"invalid email") -> kavya.nair@company.com | AA52: =IF(H51="","",IFERROR(DATEDIF(IF(ISNUMBER(H51),H51,DATE(VALUE(RIGHT(H51,4)),VALUE(MID(H51,3,2)),VALUE(LEFT(H51,2)))),TODAY(),"Y"),"")) | AB52: =IF(OR(D52="",E52=""),"",IFERROR(DATE(MID(E52,7,4),MID(E52,4,2),LEFT(E52,2))-DATE(MID(D52,7,4),MID(D52,4,2),LEFT(D52,2)),"")) | AC52: =IF(E52="","Pending",IF(AB52<=5,"On time","Delayed")) -> Delayed | AD52: =IF(TRIM(S52)="","Not Assigned",S52) -> Karan | AE52: =PROPER(TRIM(F52)) -> Kavya Nair | AF52: =PROPER(TRIM(K52)) -> Electronics | AG52: =PROPER(TRIM(J52)) -> North | AH52: =PROPER(TRIM(K52)) -> Electronics | AI52: =IF(OR(LOWER(TRIM(K52))="electronic",LOWER(TRIM(K52))="electronics"),"Electronics",PROPER(TRIM(K52))) -> Electronics | AK52: =IF(COUNTIF($A$2:A52,A52)=1,1,0) -> 1
A53: ORD10055 | B53: C003 | C53: P301 | D53: 21/02/2025 | E53: 26/02/2025 | F53: Rohit Singh | G53: Male | H53: 28076 | I53: Ahmedabad | J53: West | K53: Stationery | L53: Notebook | M53: 19 | N53: 60 | O53: 15 | P53: 969 | Q53: 4 | R53: Card | S53: Rahul | T53: rohit.singh@company.com | U53: 9822926495 | V53: Cancelled | W53: =IF(OR(Q53<=2,V53="Cancelled"),"Blacklisted",IF(AND(P53>100000,Q53>=4,O53<=10%,V53="Completed"),"Platinum",IF(AND(P53>=50000,Q53>=3,V53="Completed"),"Gold",IF(AND(P53<50000,V53="Completed"),"Silver","")))) -> Blacklisted | X53: =PROPER(TRIM(F53)) -> Rohit Singh | Y53: =LEFT(F53,3)&MID(B53,2,3)&LEFT(I53,2) -> Roh003Ah | Z53: =IF(ISNUMBER(SEARCH("@",T53)),LOWER(TRIM(T53)),"invalid email") -> rohit.singh@company.com | AA53: =IF(H52="","",IFERROR(DATEDIF(IF(ISNUMBER(H52),H52,DATE(VALUE(RIGHT(H52,4)),VALUE(MID(H52,3,2)),VALUE(LEFT(H52,2)))),TODAY(),"Y"),"")) -> 51 | AB53: =IF(OR(D53="",E53=""),"",IFERROR(DATE(MID(E53,7,4),MID(E53,4,2),LEFT(E53,2))-DATE(MID(D53,7,4),MID(D53,4,2),LEFT(D53,2)),"")) -> 5 | AC53: =IF(E53="","Pending",IF(AB53<=5,"On time","Delayed")) -> On time | AD53: =IF(TRIM(S53)="","Not Assigned",S53) -> Rahul | AE53: =PROPER(TRIM(F53)) -> Rohit Singh | AF53: =PROPER(TRIM(K53)) -> Stationery | AG53: =PROPER(TRIM(J53)) -> West | AH53: =PROPER(TRIM(K53)) -> Stationery | AI53: =IF(OR(LOWER(TRIM(K53))="electronic",LOWER(TRIM(K53))="electronics"),"Electronics",PROPER(TRIM(K53))) -> Stationery | AK53: =IF(COUNTIF($A$2:A53,A53)=1,1,0) -> 1
A54: ORD10056 | B54: C001 | C54: P301 | D54: 45938 | E54: 45969 | F54: Amit Sharma | G54: Male | H54: 28926 | I54: Jaipur | J54: North | K54: Stationery | L54: Notebook | M54: 9 | N54: 60 | O54: 20 | P54: 432 | Q54: 1 | R54: NetBanking | S54: Neha | T54: amit.sharma@company.com | U54: 9518298190 | V54: Pending | W54: =IF(OR(Q54<=2,V54="Cancelled"),"Blacklisted",IF(AND(P54>100000,Q54>=4,O54<=10%,V54="Completed"),"Platinum",IF(AND(P54>=50000,Q54>=3,V54="Completed"),"Gold",IF(AND(P54<50000,V54="Completed"),"Silver","")))) -> Blacklisted | X54: =PROPER(TRIM(F54)) -> Amit Sharma | Y54: =LEFT(F54,3)&MID(B54,2,3)&LEFT(I54,2) -> Ami001Ja | Z54: =IF(ISNUMBER(SEARCH("@",T54)),LOWER(TRIM(T54)),"invalid email") -> amit.sharma@company.com | AA54: =IF(H53="","",IFERROR(DATEDIF(IF(ISNUMBER(H53),H53,DATE(VALUE(RIGHT(H53,4)),VALUE(MID(H53,3,2)),VALUE(LEFT(H53,2)))),TODAY(),"Y"),"")) -> 49 | AB54: =IF(OR(D54="",E54=""),"",IFERROR(DATE(MID(E54,7,4),MID(E54,4,2),LEFT(E54,2))-DATE(MID(D54,7,4),MID(D54,4,2),LEFT(D54,2)),"")) | AC54: =IF(E54="","Pending",IF(AB54<=5,"On time","Delayed")) -> Delayed | AD54: =IF(TRIM(S54)="","Not Assigned",S54) -> Neha | AE54: =PROPER(TRIM(F54)) -> Amit Sharma | AF54: =PROPER(TRIM(K54)) -> Stationery | AG54: =PROPER(TRIM(J54)) -> North | AH54: =PROPER(TRIM(K54)) -> Stationery | AI54: =IF(OR(LOWER(TRIM(K54))="electronic",LOWER(TRIM(K54))="electronics"),"Electronics",PROPER(TRIM(K54))) -> Stationery | AK54: =IF(COUNTIF($A$2:A54,A54)=1,1,0) -> 1
A55: ORD10057 | B55: C001 | C55: P102 | D55: 24/03/2026 | E55: 30/03/2026 | F55: Amit Sharma | G55: Male | H55: 27/12/1978 | I55: Bengaluru | J55: South | K55: Electronics | L55: Mouse | M55: 6 | N55: 700 | O55: 0 | P55: 4200 | Q55: 4 | R55: UPI | S55: Rahul | T55: amit.sharmcompany.com | U55: 9366223547 | V55: Cancelled | W55: =IF(OR(Q55<=2,V55="Cancelled"),"Blacklisted",IF(AND(P55>100000,Q55>=4,O55<=10%,V55="Completed"),"Platinum",IF(AND(P55>=50000,Q55>=3,V55="Completed"),"Gold",IF(AND(P55<50000,V55="Completed"),"Silver","")))) -> Blacklisted | X55: =PROPER(TRIM(F55)) -> Amit Sharma | Y55: =LEFT(F55,3)&MID(B55,2,3)&LEFT(I55,2) -> Ami001Be | Z55: =IF(ISNUMBER(SEARCH("@",T55)),LOWER(TRIM(T55)),"invalid email") -> invalid email | AA55: =IF(H54="","",IFERROR(DATEDIF(IF(ISNUMBER(H54),H54,DATE(VALUE(RIGHT(H54,4)),VALUE(MID(H54,3,2)),VALUE(LEFT(H54,2)))),TODAY(),"Y"),"")) -> 47 | AB55: =IF(OR(D55="",E55=""),"",IFERROR(DATE(MID(E55,7,4),MID(E55,4,2),LEFT(E55,2))-DATE(MID(D55,7,4),MID(D55,4,2),LEFT(D55,2)),"")) -> 6 | AC55: =IF(E55="","Pending",IF(AB55<=5,"On time","Delayed")) -> Delayed | AD55: =IF(TRIM(S55)="","Not Assigned",S55) -> Rahul | AE55: =PROPER(TRIM(F55)) -> Amit Sharma | AF55: =PROPER(TRIM(K55)) -> Electronics | AG55: =PROPER(TRIM(J55)) -> South | AH55: =PROPER(TRIM(K55)) -> Electronics | AI55: =IF(OR(LOWER(TRIM(K55))="electronic",LOWER(TRIM(K55))="electronics"),"Electronics",PROPER(TRIM(K55))) -> Electronics | AK55: =IF(COUNTIF($A$2:A55,A55)=1,1,0) -> 1
A56: ORD10058 | B56: C003 | C56: P303 | D56: 13/03/2026 | E56: 19/03/2026 | F56: Rohit Singh | G56: Male | H56: 15/04/1975 | I56: Delhi | J56: North | K56: Stationery | L56: Marker | M56: 18 | N56: 45 | O56: 5 | P56: 769.5 | Q56: 1 | R56: Card | S56: Aisha | T56: rohit.singh@company.com | U56: 9701988524 | V56: Pending | W56: =IF(OR(Q56<=2,V56="Cancelled"),"Blacklisted",IF(AND(P56>100000,Q56>=4,O56<=10%,V56="Completed"),"Platinum",IF(AND(P56>=50000,Q56>=3,V56="Completed"),"Gold",IF(AND(P56<50000,V56="Completed"),"Silver","")))) -> Blacklisted | X56: =PROPER(TRIM(F56)) -> Rohit Singh | Y56: =LEFT(F56,3)&MID(B56,2,3)&LEFT(I56,2) -> Roh003De | Z56: =IF(ISNUMBER(SEARCH("@",T56)),LOWER(TRIM(T56)),"invalid email") -> rohit.singh@company.com | AA56: =IF(H55="","",IFERROR(DATEDIF(IF(ISNUMBER(H55),H55,DATE(VALUE(RIGHT(H55,4)),VALUE(MID(H55,3,2)),VALUE(LEFT(H55,2)))),TODAY(),"Y"),"")) | AB56: =IF(OR(D56="",E56=""),"",IFERROR(DATE(MID(E56,7,4),MID(E56,4,2),LEFT(E56,2))-DATE(MID(D56,7,4),MID(D56,4,2),LEFT(D56,2)),"")) -> 6 | AC56: =IF(E56="","Pending",IF(AB56<=5,"On time","Delayed")) -> Delayed | AD56: =IF(TRIM(S56)="","Not Assigned",S56) -> Aisha | AE56: =PROPER(TRIM(F56)) -> Rohit Singh | AF56: =PROPER(TRIM(K56)) -> Stationery | AG56: =PROPER(TRIM(J56)) -> North | AH56: =PROPER(TRIM(K56)) -> Stationery | AI56: =IF(OR(LOWER(TRIM(K56))="electronic",LOWER(TRIM(K56))="electronics"),"Electronics",PROPER(TRIM(K56))) -> Stationery | AK56: =IF(COUNTIF($A$2:A56,A56)=1,1,0) -> 1
A57: ORD10059 | B57: C007 | C57: P302 | D57: 15/06/2025 | E57: 26/06/2025 | F57: Arjun Rao | G57: Male | H57: 19/12/1988 | I57: Jaipur | J57: North | K57: Stationery | L57: Pen | M57: 8 | N57: 20 | O57: 5 | P57: 152 | Q57: 1 | R57: Card | S57: Ritika | T57: arjun.rao@company.com | U57: 9836327649 | V57: completed | W57: =IF(OR(Q57<=2,V57="Cancelled"),"Blacklisted",IF(AND(P57>100000,Q57>=4,O57<=10%,V57="Completed"),"Platinum",IF(AND(P57>=50000,Q57>=3,V57="Completed"),"Gold",IF(AND(P57<50000,V57="Completed"),"Silver","")))) -> Blacklisted | X57: =PROPER(TRIM(F57)) -> Arjun Rao | Y57: =LEFT(F57,3)&MID(B57,2,3)&LEFT(I57,2) -> Arj007Ja | Z57: =IF(ISNUMBER(SEARCH("@",T57)),LOWER(TRIM(T57)),"invalid email") -> arjun.rao@company.com | AA57: =IF(H56="","",IFERROR(DATEDIF(IF(ISNUMBER(H56),H56,DATE(VALUE(RIGHT(H56,4)),VALUE(MID(H56,3,2)),VALUE(LEFT(H56,2)))),TODAY(),"Y"),"")) | AB57: =IF(OR(D57="",E57=""),"",IFERROR(DATE(MID(E57,7,4),MID(E57,4,2),LEFT(E57,2))-DATE(MID(D57,7,4),MID(D57,4,2),LEFT(D57,2)),"")) -> 11 | AC57: =IF(E57="","Pending",IF(AB57<=5,"On time","Delayed")) -> Delayed | AD57: =IF(TRIM(S57)="","Not Assigned",S57) -> Ritika | AE57: =PROPER(TRIM(F57)) -> Arjun Rao | AF57: =PROPER(TRIM(K57)) -> Stationery | AG57: =PROPER(TRIM(J57)) -> North | AH57: =PROPER(TRIM(K57)) -> Stationery | AI57: =IF(OR(LOWER(TRIM(K57))="electronic",LOWER(TRIM(K57))="electronics"),"Electronics",PROPER(TRIM(K57))) -> Stationery | AK57: =IF(COUNTIF($A$2:A57,A57)=1,1,0) -> 1
A58: ORD10060 | B58: C005 | C58: P102 | D58: 45780 | E58: 45811 | F58: Vikas Mehta | G58: Male | H58: 29039 | I58: Jaipur | J58: North | K58: Electronics | L58: Mouse | M58: 8 | N58: 700 | O58: 10 | P58: 5040 | Q58: 1 | R58: NetBanking | S58: Aisha | T58: Vikas.mehta@company.com | U58: 9261800516 | V58: Cancelled | W58: =IF(OR(Q58<=2,V58="Cancelled"),"Blacklisted",IF(AND(P58>100000,Q58>=4,O58<=10%,V58="Completed"),"Platinum",IF(AND(P58>=50000,Q58>=3,V58="Completed"),"Gold",IF(AND(P58<50000,V58="Completed"),"Silver","")))) -> Blacklisted | X58: =PROPER(TRIM(F58)) -> Vikas Mehta | Y58: =LEFT(F58,3)&MID(B58,2,3)&LEFT(I58,2) -> Vik005Ja | Z58: =IF(ISNUMBER(SEARCH("@",T58)),LOWER(TRIM(T58)),"invalid email") -> vikas.mehta@company.com | AA58: =IF(H57="","",IFERROR(DATEDIF(IF(ISNUMBER(H57),H57,DATE(VALUE(RIGHT(H57,4)),VALUE(MID(H57,3,2)),VALUE(LEFT(H57,2)))),TODAY(),"Y"),"")) | AB58: =IF(OR(D58="",E58=""),"",IFERROR(DATE(MID(E58,7,4),MID(E58,4,2),LEFT(E58,2))-DATE(MID(D58,7,4),MID(D58,4,2),LEFT(D58,2)),"")) | AC58: =IF(E58="","Pending",IF(AB58<=5,"On time","Delayed")) -> Delayed | AD58: =IF(TRIM(S58)="","Not Assigned",S58) -> Aisha | AE58: =PROPER(TRIM(F58)) -> Vikas Mehta | AF58: =PROPER(TRIM(K58)) -> Electronics | AG58: =PROPER(TRIM(J58)) -> North | AH58: =PROPER(TRIM(K58)) -> Electronics | AI58: =IF(OR(LOWER(TRIM(K58))="electronic",LOWER(TRIM(K58))="electronics"),"Electronics",PROPER(TRIM(K58))) -> Electronics | AK58: =IF(COUNTIF($A$2:A58,A58)=1,1,0) -> 1
A59: ORD10061 | B59: C008 | C59: P302 | D59: 46269 | E59: 19/04/2026 | F59: Kavya Nair | G59: Female | H59: 17/12/2003 | I59: Delhi | J59: North | K59: Stationery | L59: Pen | M59: 7 | N59: 20 | O59: 15 | P59: 119 | Q59: 5 | R59: Card | S59: Rahul | T59: kavya.nair@company.com | U59: 9950802015 | V59: Completed | W59: =IF(OR(Q59<=2,V59="Cancelled"),"Blacklisted",IF(AND(P59>100000,Q59>=4,O59<=10%,V59="Completed"),"Platinum",IF(AND(P59>=50000,Q59>=3,V59="Completed"),"Gold",IF(AND(P59<50000,V59="Completed"),"Silver","")))) -> Silver | X59: =PROPER(TRIM(F59)) -> Kavya Nair | Y59: =LEFT(F59,3)&MID(B59,2,3)&LEFT(I59,2) -> Kav008De | Z59: =IF(ISNUMBER(SEARCH("@",T59)),LOWER(TRIM(T59)),"invalid email") -> kavya.nair@company.com | AA59: =IF(H58="","",IFERROR(DATEDIF(IF(ISNUMBER(H58),H58,DATE(VALUE(RIGHT(H58,4)),VALUE(MID(H58,3,2)),VALUE(LEFT(H58,2)))),TODAY(),"Y"),"")) -> 47 | AB59: =IF(OR(D59="",E59=""),"",IFERROR(DATE(MID(E59,7,4),MID(E59,4,2),LEFT(E59,2))-DATE(MID(D59,7,4),MID(D59,4,2),LEFT(D59,2)),"")) | AC59: =IF(E59="","Pending",IF(AB59<=5,"On time","Delayed")) -> Delayed | AD59: =IF(TRIM(S59)="","Not Assigned",S59) -> Rahul | AE59: =PROPER(TRIM(F59)) -> Kavya Nair | AF59: =PROPER(TRIM(K59)) -> Stationery | AG59: =PROPER(TRIM(J59)) -> North | AH59: =PROPER(TRIM(K59)) -> Stationery | AI59: =IF(OR(LOWER(TRIM(K59))="electronic",LOWER(TRIM(K59))="electronics"),"Electronics",PROPER(TRIM(K59))) -> Stationery | AK59: =IF(COUNTIF($A$2:A59,A59)=1,1,0) -> 1
A60: ORD10062 | B60: C002 | C60: P302 | D60: 16/08/2025 | E60: 25/08/2025 | F60: Priya Patel | G60: Female | H60: 30806 | I60: Pune | J60: West | K60: Stationery | L60: Pen | M60: 16 | N60: 20 | O60: 0 | P60: 320 | Q60: 5 | R60: NetBanking | S60: Aisha | T60: priya.patel@company.com | U60: 9595183767 | V60: Pending | W60: =IF(OR(Q60<=2,V60="Cancelled"),"Blacklisted",IF(AND(P60>100000,Q60>=4,O60<=10%,V60="Completed"),"Platinum",IF(AND(P60>=50000,Q60>=3,V60="Completed"),"Gold",IF(AND(P60<50000,V60="Completed"),"Silver","")))) | X60: =PROPER(TRIM(F60)) -> Priya Patel | Y60: =LEFT(F60,3)&MID(B60,2,3)&LEFT(I60,2) -> Pri002Pu | Z60: =IF(ISNUMBER(SEARCH("@",T60)),LOWER(TRIM(T60)),"invalid email") -> priya.patel@company.com | AA60: =IF(H59="","",IFERROR(DATEDIF(IF(ISNUMBER(H59),H59,DATE(VALUE(RIGHT(H59,4)),VALUE(MID(H59,3,2)),VALUE(LEFT(H59,2)))),TODAY(),"Y"),"")) | AB60: =IF(OR(D60="",E60=""),"",IFERROR(DATE(MID(E60,7,4),MID(E60,4,2),LEFT(E60,2))-DATE(MID(D60,7,4),MID(D60,4,2),LEFT(D60,2)),"")) -> 9 | AC60: =IF(E60="","Pending",IF(AB60<=5,"On time","Delayed")) -> Delayed | AD60: =IF(TRIM(S60)="","Not Assigned",S60) -> Aisha | AE60: =PROPER(TRIM(F60)) -> Priya Patel | AF60: =PROPER(TRIM(K60)) -> Stationery | AG60: =PROPER(TRIM(J60)) -> West | AH60: =PROPER(TRIM(K60)) -> Stationery | AI60: =IF(OR(LOWER(TRIM(K60))="electronic",LOWER(TRIM(K60))="electronics"),"Electronics",PROPER(TRIM(K60))) -> Stationery | AK60: =IF(COUNTIF($A$2:A60,A60)=1,1,0) -> 1
